Workbook

Sheet BASE
B3: Orientações:
L5: Semana | M5: De | N5: Até
L6: =WEEKNUM(M6) -> 1 | M6: 45292 | N6: =M6+6 -> 45298 | O6: ="De "&DAY(M6)&"/"&MONTH(M6)&" até "&DAY(N6)&"/"&MONTH(N6) -> De 1/1 até 7/1
L7: =WEEKNUM(M7) -> 2 | M7: 45298 | N7: =M7+6 -> 45304 | O7: ="De "&DAY(M7)&"/"&MONTH(M7)&" até "&DAY(N7)&"/"&MONTH(N7) -> De 7/1 até 13/1
L8: =WEEKNUM(M8) -> 3 | M8: 45305 | N8: =M8+6 -> 45311 | O8: ="De "&DAY(M8)&"/"&MONTH(M8)&" até "&DAY(N8)&"/"&MONTH(N8) -> De 14/1 até 20/1
L9: =WEEKNUM(M9) -> 4 | M9: 45312 | N9: =M9+6 -> 45318 | O9: ="De "&DAY(M9)&"/"&MONTH(M9)&" até "&DAY(N9)&"/"&MONTH(N9) -> De 21/1 até 27/1
L10: =WEEKNUM(M10) -> 5 | M10: 45319 | N10: =M10+6 -> 45325 | O10: ="De "&DAY(M10)&"/"&MONTH(M10)&" até "&DAY(N10)&"/"&MONTH(N10) -> De 28/1 até 3/2
L11: =WEEKNUM(M11) -> 6 | M11: 45326 | N11: =M11+6 -> 45332 | O11: ="De "&DAY(M11)&"/"&MONTH(M11)&" até "&DAY(N11)&"/"&MONTH(N11) -> De 4/2 até 10/2
L12: =WEEKNUM(M12) -> 7 | M12: 45333 | N12: =M12+6 -> 45339 | O12: ="De "&DAY(M12)&"/"&MONTH(M12)&" até "&DAY(N12)&"/"&MONTH(N12) -> De 11/2 até 17/2
L13: =WEEKNUM(M13) -> 8 | M13: 45340 | N13: =M13+6 -> 45346 | O13: ="De "&DAY(M13)&"/"&MONTH(M13)&" até "&DAY(N13)&"/"&MONTH(N13) -> De 18/2 até 24/2
L14: =WEEKNUM(M14) -> 9 | M14: 45347 | N14: =M14+6 -> 45353 | O14: ="De "&DAY(M14)&"/"&MONTH(M14)&" até "&DAY(N14)&"/"&MONTH(N14) -> De 25/2 até 2/3
B15: 1 | C15: segunda-feira | L15: =WEEKNUM(M15) -> 10 | M15: 45354 | N15: =M15+6 -> 45360 | O15: ="De "&DAY(M15)&"/"&MONTH(M15)&" até "&DAY(N15)&"/"&MONTH(N15) -> De 3/3 até 9/3
B16: 2 | C16: terça-feira | F16: 1 | G16: Janeiro | L16: =WEEKNUM(M16) -> 11 | M16: 45361 | N16: =M16+6 -> 45367 | O16: ="De "&DAY(M16)&"/"&MONTH(M16)&" até "&DAY(N16)&"/"&MONTH(N16) -> De 10/3 até 16/3
B17: 3 | C17: quarta-feira | F17: 2 | G17: Fevereiro | L17: =WEEKNUM(M17) -> 12 | M17: 45368 | N17: =M17+6 -> 45374 | O17: ="De "&DAY(M17)&"/"&MONTH(M17)&" até "&DAY(N17)&"/"&MONTH(N17) -> De 17/3 até 23/3
B18: 4 | C18: quinta-feira | F18: 3 | G18: Março | L18: =WEEKNUM(M18) -> 13 | M18: 45375 | N18: =M18+6 -> 45381 | O18: ="De "&DAY(M18)&"/"&MONTH(M18)&" até "&DAY(N18)&"/"&MONTH(N18) -> De 24/3 até 30/3
B19: 5 | C19: sexta-feira | F19: 4 | G19: Abril | L19: =WEEKNUM(M19) -> 14 | M19: 45382 | N19: =M19+6 -> 45388 | O19: ="De "&DAY(M19)&"/"&MONTH(M19)&" até "&DAY(N19)&"/"&MONTH(N19) -> De 31/3 até 6/4
B20: 6 | C20: sábado | F20: 5 | G20: Maio | L20: =WEEKNUM(M20) -> 15 | M20: 45389 | N20: =M20+6 -> 45395 | O20: ="De "&DAY(M20)&"/"&MONTH(M20)&" até "&DAY(N20)&"/"&MONTH(N20) -> De 7/4 até 13/4
B21: 7 | C21: domingo | F21: 6 | G21: Junho | L21: =WEEKNUM(M21) -> 16 | M21: 45396 | N21: =M21+6 -> 45402 | O21: ="De "&DAY(M21)&"/"&MONTH(M21)&" até "&DAY(N21)&"/"&MONTH(N21) -> De 14/4 até 20/4
F22: 7 | G22: Julho | L22: =WEEKNUM(M22) -> 17 | M22: 45403 | N22: =M22+6 -> 45409 | O22: ="De "&DAY(M22)&"/"&MONTH(M22)&" até "&DAY(N22)&"/"&MONTH(N22) -> De 21/4 até 27/4
F23: 8 | G23: Agosto | L23: =WEEKNUM(M23) -> 18 | M23: 45410 | N23: =M23+6 -> 45416 | O23: ="De "&DAY(M23)&"/"&MONTH(M23)&" até "&DAY(N23)&"/"&MONTH(N23) -> De 28/4 até 4/5
F24: 9 | G24: Setembro | L24: =WEEKNUM(M24) -> 19 | M24: 45417 | N24: =M24+6 -> 45423 | O24: ="De "&DAY(M24)&"/"&MONTH(M24)&" até "&DAY(N24)&"/"&MONTH(N24) -> De 5/5 até 11/5
F25: 10 | G25: Outubro | L25: =WEEKNUM(M25) -> 20 | M25: 45424 | N25: =M25+6 -> 45430 | O25: ="De "&DAY(M25)&"/"&MONTH(M25)&" até "&DAY(N25)&"/"&MONTH(N25) -> De 12/5 até 18/5
F26: 11 | G26: Novembro | L26: =WEEKNUM(M26) -> 21 | M26: 45431 | N26: =M26+6 -> 45437 | O26: ="De "&DAY(M26)&"/"&MONTH(M26)&" até "&DAY(N26)&"/"&MONTH(N26) -> De 19/5 até 25/5
F27: 12 | G27: Dezembro | L27: =WEEKNUM(M27) -> 22 | M27: 45438 | N27: =M27+6 -> 45444 | O27: ="De "&DAY(M27)&"/"&MONTH(M27)&" até "&DAY(N27)&"/"&MONTH(N27) -> De 26/5 até 1/6
L28: =WEEKNUM(M28) -> 23 | M28: 45445 | N28: =M28+6 -> 45451 | O28: ="De "&DAY(M28)&"/"&MONTH(M28)&" até "&DAY(N28)&"/"&MONTH(N28) -> De 2/6 até 8/6
L29: =WEEKNUM(M29) -> 24 | M29: 45452 | N29: =M29+6 -> 45458 | O29: ="De "&DAY(M29)&"/"&MONTH(M29)&" até "&DAY(N29)&"/"&MONTH(N29) -> De 9/6 até 15/6
L30: =WEEKNUM(M30) -> 25 | M30: 45459 | N30: =M30+6 -> 45465 | O30: ="De "&DAY(M30)&"/"&MONTH(M30)&" até "&DAY(N30)&"/"&MONTH(N30) -> De 16/6 até 22/6
L31: =WEEKNUM(M31) -> 26 | M31: 45466 | N31: =M31+6 -> 45472 | O31: ="De "&DAY(M31)&"/"&MONTH(M31)&" até "&DAY(N31)&"/"&MONTH(N31) -> De 23/6 até 29/6
L32: =WEEKNUM(M32) -> 27 | M32: 45473 | N32: =M32+6 -> 45479 | O32: ="De "&DAY(M32)&"/"&MONTH(M32)&" até "&DAY(N32)&"/"&MONTH(N32) -> De 30/6 até 6/7
L33: =WEEKNUM(M33) -> 28 | M33: 45480 | N33: =M33+6 -> 45486 | O33: ="De "&DAY(M33)&"/"&MONTH(M33)&" até "&DAY(N33)&"/"&MONTH(N33) -> De 7/7 até 13/7
L34: =WEEKNUM(M34) -> 29 | M34: 45487 | N34: =M34+6 -> 45493 | O34: ="De "&DAY(M34)&"/"&MONTH(M34)&" até "&DAY(N34)&"/"&MONTH(N34) -> De 14/7 até 20/7
L35: =WEEKNUM(M35) -> 30 | M35: 45494 | N35: =M35+6 -> 45500 | O35: ="De "&DAY(M35)&"/"&MONTH(M35)&" até "&DAY(N35)&"/"&MONTH(N35) -> De 21/7 até 27/7
L36: =WEEKNUM(M36) -> 31 | M36: 45501 | N36: =M36+6 -> 45507 | O36: ="De "&DAY(M36)&"/"&MONTH(M36)&" até "&DAY(N36)&"/"&MONTH(N36) -> De 28/7 até 3/8
L37: =WEEKNUM(M37) -> 32 | M37: 45508 | N37: =M37+6 -> 45514 | O37: ="De "&DAY(M37)&"/"&MONTH(M37)&" até "&DAY(N37)&"/"&MONTH(N37) -> De 4/8 até 10/8
L38: =WEEKNUM(M38) -> 33 | M38: 45515 | N38: =M38+6 -> 45521 | O38: ="De "&DAY(M38)&"/"&MONTH(M38)&" até "&DAY(N38)&"/"&MONTH(N38) -> De 11/8 até 17/8
L39: =WEEKNUM(M39) -> 34 | M39: 45522 | N39: =M39+6 -> 45528 | O39: ="De "&DAY(M39)&"/"&MONTH(M39)&" até "&DAY(N39)&"/"&MONTH(N39) -> De 18/8 até 24/8
... L58: =WEEKNUM(M58) -> 53 | M58: 45655 | N58: =M58+6 -> 45661 | O58: ="De "&DAY(M58)&"/"&MONTH(M58)&" até "&DAY(N58)&"/"&MONTH(N58) -> De 29/12 até 4/1

Sheet Leads
A1: Data | B1: Nome | C1: Telefone | D1: email | E1: URL | F1: utm_source | G1: utm_medium | H1: utm_term | I1: utm_content | J1: utm_campaign | K1: formato data | L1: Data Correta | M1: Telefone 8 Digitos | N1: Está no grupo?
A2: 2026-04-07T14:04:53.554Z | B2: William Barbosa | C2: 55199918096 | D2: williamandre742@gmail.com | E2: https://lp.saibai.com.br/?utm_source=MetaAds&utm_medium=ADV+-+%5BIG%5D+%5BFB%5D+%5B30%2B%5D+%5BPIEDADE+-+40KM%5D+V%C3%81RIOS&utm_campaign=07.04.2026+%5BV4%5D+%5BWB%5D+%5BLEADS-GRUPO-WHATS%5D+02&utm_content=07.04+%5BIMG%5D+%5BAD04%5D+Pedidos+abertos&utm_term=Instagram_Stories&utm_id=120248254459350155&fbclid=PAZXh0bgNhZW0BMABhZGlkAas1g0M2JftzcnRjBmFwcF9pZA81NjcwNjczNDMzNTI0MjcAAae-Pi9C5ulqTw1avKSlCfTlAiaFlEjDorhtO4cBmGvSCiUKaU-KCcm7ipMffA_aem_qVPH0fA8b5aEFs-o7UHCZA&campaign_id=120248254459350155&ad_id=120248254459370155 | F2: =IFERROR(__xludf.DUMMYFUNCTION("ARRAYFORMULA(IF($E2:$E1351="""","""",IFERROR(REGEXEXTRACT($E2:$E1351,""[?&]utm_source=([^&]+)""),"""")))"),"MetaAds") -> MetaAds | G2: =IFERROR(__xludf.DUMMYFUNCTION("ARRAYFORMULA(IF($E2:$E1351="""","""",IFERROR( REGEXREPLACE( REGEXREPLACE( SUBSTITUTE(REGEXEXTRACT($E2:$E1351,""[?&]utm_medium=([^&]+)""),""+"","" ""), ""(?i)%5B"",""[""), ""(?i)%5D"",""]"") ,""""))) "),"ADV - [IG] [FB] [30%2B] [PIEDADE - 40KM] V%C3%81RIOS") -> ADV - [IG] [FB] [30%2B] [PIEDADE - 40KM] V%C3%81RIOS | H2: =IFERROR(__xludf.DUMMYFUNCTION("ARRAYFORMULA(IF($E2:$E1351="""","""",IFERROR( REGEXREPLACE( REGEXREPLACE( SUBSTITUTE(REGEXEXTRACT($E2:$E1351,""[?&]utm_term=([^&]+)""),""+"","" ""), ""(?i)%5B"",""[""), ""(?i)%5D"",""]"") ,""""))) "),"Instagram_Stories") -> Instagram_Stories | I2: =IFERROR(__xludf.DUMMYFUNCTION("ARRAYFORMULA(IF($E2:$E1351="""","""",IFERROR( REGEXREPLACE( REGEXREPLACE( SUBSTITUTE(REGEXEXTRACT($E2:$E1351,""[?&]utm_content=([^&]+)""),""+"","" ""), ""(?i)%5B"",""[""), ""(?i)%5D"",""]"") ,""""))) "),"07.04 [IMG] [AD04] Pedidos abertos") -> 07.04 [IMG] [AD04] Pedidos abertos | J2: =IFERROR(__xludf.DUMMYFUNCTION("ARRAYFORMULA(IF($E2:$E1351="""","""",IFERROR( REGEXREPLACE( REGEXREPLACE( SUBSTITUTE(REGEXEXTRACT($E2:$E1351,""[?&]utm_campaign=([^&]+)""),""+"","" ""), ""(?i)%5B"",""[""), ""(?i)%5D"",""]"") ,""""))) "),"07.04.2026 [V4] [WB] [LEADS-GRUPO-WHATS] 02") -> 07.04.2026 [V4] [WB] [LEADS-GRUPO-WHATS] 02 | K2: =LEFT(A2,10) -> 2026-04-07 | L2: =DATE(YEAR(SUBSTITUTE(SUBSTITUTE(K2,"-","/",1),"-","/",1)),MONTH(SUBSTITUTE(SUBSTITUTE(K2,"-","/",1),"-","/",1)),DAY(SUBSTITUTE(SUBSTITUTE(K2,"-","/",1),"-","/",1))) -> 46119 | M2: =RIGHT(C2,8) -> 99918096 | N2: =IFERROR(IF(VLOOKUP(M2,'Leads no grupo Saibai'!C:C,1,FALSE)=M2,"Sim"),"Não") -> Não
A3: 2026-04-10T06:01:53.154Z | B3: lenilze pereiradaldon | C3: 55981355010 | D3: pereiradaldon@hotmail.com | E3: https://lp.saibai.com.br/?utm_source=MetaAds&utm_medium=ADV+-+%5BIG%5D+%5BFB%5D+%5B30%2B%5D+%5BPIEDADE+-+40KM%5D+V%C3%81RIOS&utm_campaign=07.04.2026+%5BV4%5D+%5BWB%5D+%5BLEADS-GRUPO-WHATS%5D+01&utm_content=07.04+%5BIMG%5D+%5BAD04%5D+Pedidos+abertos&utm_term=Instagram_Stories&utm_id=120247452154580155&fbclid=PAZXh0bgNhZW0BMABhZGlkAas0bAfOj7tzcnRjBmFwcF9pZA81NjcwNjczNDMzNTI0MjcAAafhAJfazzKXYAWRJ1dJ-3Yx8wr-kjkNLqLkYIgbyMCz1Rf1plENwmmd43T_YA_aem_KZY9Eo1RU3GvOgoqY-w8hw&campaign_id=120247452154580155&ad_id=120247452938090155 | F3: =IFERROR(__xludf.DUMMYFUNCTION("""COMPUTED_VALUE"""),"MetaAds") -> MetaAds | G3: =IFERROR(__xludf.DUMMYFUNCTION("""COMPUTED_VALUE"""),"ADV - [IG] [FB] [30%2B] [PIEDADE - 40KM] V%C3%81RIOS") -> ADV - [IG] [FB] [30%2B] [PIEDADE - 40KM] V%C3%81RIOS | H3: =IFERROR(__xludf.DUMMYFUNCTION("""COMPUTED_VALUE"""),"Instagram_Stories") -> Instagram_Stories | I3: =IFERROR(__xludf.DUMMYFUNCTION("""COMPUTED_VALUE"""),"07.04 [IMG] [AD04] Pedidos abertos") -> 07.04 [IMG] [AD04] Pedidos abertos | J3: =IFERROR(__xludf.DUMMYFUNCTION("""COMPUTED_VALUE"""),"07.04.2026 [V4] [WB] [LEADS-GRUPO-WHATS] 01") -> 07.04.2026 [V4] [WB] [LEADS-GRUPO-WHATS] 01 | K3: =LEFT(A3,10) -> 2026-04-10 | L3: =DATE(YEAR(SUBSTITUTE(SUBSTITUTE(K3,"-","/",1),"-","/",1)),MONTH(SUBSTITUTE(SUBSTITUTE(K3,"-","/",1),"-","/",1)),DAY(SUBSTITUTE(SUBSTITUTE(K3,"-","/",1),"-","/",1))) -> 46122 | M3: =RIGHT(C3,8) -> 81355010 | N3: =IFERROR(IF(VLOOKUP(M3,'Leads no grupo Saibai'!C:C,1,FALSE)=M3,"Sim"),"Não") -> Não
A4: 2026-04-10T06:02:30.692Z | B4: lenilze pereiradaldon | C4: 55981355010 | D4: pereiradaldon@hotmail.com | E4: https://lp.saibai.com.br/?utm_source=MetaAds&utm_medium=ADV+-+%5BIG%5D+%5BFB%5D+%5B30%2B%5D+%5BPIEDADE+-+40KM%5D+V%C3%81RIOS&utm_campaign=07.04.2026+%5BV4%5D+%5BWB%5D+%5BLEADS-GRUPO-WHATS%5D+01&utm_content=07.04+%5BIMG%5D+%5BAD04%5D+Pedidos+abertos&utm_term=Instagram_Stories&utm_id=120247452154580155&fbclid=PAZXh0bgNhZW0BMABhZGlkAas0bAfOj7tzcnRjBmFwcF9pZA81NjcwNjczNDMzNTI0MjcAAafhAJfazzKXYAWRJ1dJ-3Yx8wr-kjkNLqLkYIgbyMCz1Rf1plENwmmd43T_YA_aem_KZY9Eo1RU3GvOgoqY-w8hw&campaign_id=120247452154580155&ad_id=120247452938090155 | F4: =IFERROR(__xludf.DUMMYFUNCTION("""COMPUTED_VALUE"""),"MetaAds") -> MetaAds | G4: =IFERROR(__xludf.DUMMYFUNCTION("""COMPUTED_VALUE"""),"ADV - [IG] [FB] [30%2B] [PIEDADE - 40KM] V%C3%81RIOS") -> ADV - [IG] [FB] [30%2B] [PIEDADE - 40KM] V%C3%81RIOS | H4: =IFERROR(__xludf.DUMMYFUNCTION("""COMPUTED_VALUE"""),"Instagram_Stories") -> Instagram_Stories | I4: =IFERROR(__xludf.DUMMYFUNCTION("""COMPUTED_VALUE"""),"07.04 [IMG] [AD04] Pedidos abertos") -> 07.04 [IMG] [AD04] Pedidos abertos | J4: =IFERROR(__xludf.DUMMYFUNCTION("""COMPUTED_VALUE"""),"07.04.2026 [V4] [WB] [LEADS-GRUPO-WHATS] 01") -> 07.04.2026 [V4] [WB] [LEADS-GRUPO-WHATS] 01 | K4: =LEFT(A4,10) -> 2026-04-10 | L4: =DATE(YEAR(SUBSTITUTE(SUBSTITUTE(K4,"-","/",1),"-","/",1)),MONTH(SUBSTITUTE(SUBSTITUTE(K4,"-","/",1),"-","/",1)),DAY(SUBSTITUTE(SUBSTITUTE(K4,"-","/",1),"-","/",1))) -> 46122 | M4: =RIGHT(C4,8) -> 81355010 | N4: =IFERROR(IF(VLOOKUP(M4,'Leads no grupo Saibai'!C:C,1,FALSE)=M4,"Sim"),"Não") -> Não
A5: 2026-04-10T07:47:42.252Z | B5: ODILON BUENO | C5: 15997577218 | D5: odilon.bueno@autoescolaabc.com.br | E5: https://lp.saibai.com.br/?utm_source=MetaAds&utm_medium=ADV+-+%5BIG%5D+%5BFB%5D+%5B30%2B%5D+%5BPIEDADE+-+40KM%5D+V%C3%81RIOS&utm_campaign=07.04.2026+%5BV4%5D+%5BWB%5D+%5BLEADS-GRUPO-WHATS%5D+01&utm_content=07.04+%5BIMG%5D+%5BAD04%5D+Pedidos+abertos&utm_term=Instagram_Stories&utm_id=120247452154580155&fbclid=PAZXh0bgNhZW0BMABhZGlkAas0bAW7ZytzcnRjBmFwcF9pZA8xMjQwMjQ1NzQyODc0MTQAAaeEbScr7uc5Bw7yQlSg97yg1D1SgKabzfOnG166KAsAcqQyKH8mzWdxuDGDaA_aem_DqH-FubtkiHGvX0LGSaFzw&campaign_id=120247452154580155&ad_id=120247452938090155 | F5: =IFERROR(__xludf.DUMMYFUNCTION("""COMPUTED_VALUE"""),"MetaAds") -> MetaAds | G5: =IFERROR(__xludf.DUMMYFUNCTION("""COMPUTED_VALUE"""),"ADV - [IG] [FB] [30%2B] [PIEDADE - 40KM] V%C3%81RIOS") -> ADV - [IG] [FB] [30%2B] [PIEDADE - 40KM] V%C3%81RIOS | H5: =IFERROR(__xludf.DUMMYFUNCTION("""COMPUTED_VALUE"""),"Instagram_Stories") -> Instagram_Stories | I5: =IFERROR(__xludf.DUMMYFUNCTION("""COMPUTED_VALUE"""),"07.04 [IMG] [AD04] Pedidos abertos") -> 07.04 [IMG] [AD04] Pedidos abertos | J5: =IFERROR(__xludf.DUMMYFUNCTION("""COMPUTED_VALUE"""),"07.04.2026 [V4] [WB] [LEADS-GRUPO-WHATS] 01") -> 07.04.2026 [V4] [WB] [LEADS-GRUPO-WHATS] 01 | K5: =LEFT(A5,10) -> 2026-04-10 | L5: =DATE(YEAR(SUBSTITUTE(SUBSTITUTE(K5,"-","/",1),"-","/",1)),MONTH(SUBSTITUTE(SUBSTITUTE(K5,"-","/",1),"-","/",1)),DAY(SUBSTITUTE(SUBSTITUTE(K5,"-","/",1),"-","/",1))) -> 46122 | M5: =RIGHT(C5,8) -> 97577218 | N5: =IFERROR(IF(VLOOKUP(M5,'Leads no grupo Saibai'!C:C,1,FALSE)=M5,"Sim"),"Não") -> Sim
A6: 2026-04-10T08:05:20.787Z | B6: andrea pedreira | C6: 15996014055 | D6: andreapedreira15@gmail.com | E6: https://lp.saibai.com.br/?utm_source=MetaAds&utm_medium=ADV+-+%5BIG%5D+%5BFB%5D+%5B30%2B%5D+%5BPIEDADE+-+40KM%5D+V%C3%81RIOS&utm_campaign=07.04.2026+%5BV4%5D+%5BWB%5D+%5BLEADS-GRUPO-WHATS%5D+02&utm_content=07.04+%5BIMG%5D+%5BAD04%5D+Pedidos+abertos&utm_term=Instagram_Stories&utm_id=120248254459350155&fbclid=PAZXh0bgNhZW0BMABhZGlkAas1g0M2JftzcnRjBmFwcF9pZA81NjcwNjczNDMzNTI0MjcAAae-Pi9C5ulqTw1avKSlCfTlAiaFlEjDorhtO4cBmGvSCiUKaU-KCcm7ipMffA_aem_qVPH0fA8b5aEFs-o7UHCZA&campaign_id=120248254459350155&ad_id=120248254459370155 | F6: =IFERROR(__xludf.DUMMYFUNCTION("""COMPUTED_VALUE"""),"MetaAds") -> MetaAds | G6: =IFERROR(__xludf.DUMMYFUNCTION("""COMPUTED_VALUE"""),"ADV - [IG] [FB] [30%2B] [PIEDADE - 40KM] V%C3%81RIOS") -> ADV - [IG] [FB] [30%2B] [PIEDADE - 40KM] V%C3%81RIOS | H6: =IFERROR(__xludf.DUMMYFUNCTION("""COMPUTED_VALUE"""),"Instagram_Stories") -> Instagram_Stories | I6: =IFERROR(__xludf.DUMMYFUNCTION("""COMPUTED_VALUE"""),"07.04 [IMG] [AD04] Pedidos abertos") -> 07.04 [IMG] [AD04] Pedidos abertos | J6: =IFERROR(__xludf.DUMMYFUNCTION("""COMPUTED_VALUE"""),"07.04.2026 [V4] [WB] [LEADS-GRUPO-WHATS] 02") -> 07.04.2026 [V4] [WB] [LEADS-GRUPO-WHATS] 02 | K6: =LEFT(A6,10) -> 2026-04-10 | L6: =DATE(YEAR(SUBSTITUTE(SUBSTITUTE(K6,"-","/",1),"-","/",1)),MONTH(SUBSTITUTE(SUBSTITUTE(K6,"-","/",1),"-","/",1)),DAY(SUBSTITUTE(SUBSTITUTE(K6,"-","/",1),"-","/",1))) -> 46122 | M6: =RIGHT(C6,8) -> 96014055 | N6: =IFERROR(IF(VLOOKUP(M6,'Leads no grupo Saibai'!C:C,1,FALSE)=M6,"Sim"),"Não") -> Sim
A7: 2026-04-10T08:15:22.674Z | B7: Bruno Rocha | C7: 15997000778 | D7: brunokr77@hotmail.com | E7: https://lp.saibai.com.br/?utm_source=MetaAds&utm_medium=ADV+-+%5BIG%5D+%5BFB%5D+%5B30%2B%5D+%5BPIEDADE+-+40KM%5D+V%C3%81RIOS&utm_campaign=07.04.2026+%5BV4%5D+%5BWB%5D+%5BLEADS-GRUPO-WHATS%5D+01&utm_content=07.04+%5BIMG%5D+%5BAD04%5D+Pedidos+abertos&utm_term=Instagram_Stories&utm_id=120247452154580155&fbclid=PAZXh0bgNhZW0BMABhZGlkAas0bAW7ZytzcnRjBmFwcF9pZA81NjcwNjczNDMzNTI0MjcAAafkHLECCqoGBZ18nJzv-QLbVeYATsNjV39JHPvcC8QjSrG8C4kR93mDt3Yv7w_aem_uFBmSIdVrdndo335G3WZYg&campaign_id=120247452154580155&ad_id=120247452938090155 | F7: =IFERROR(__xludf.DUMMYFUNCTION("""COMPUTED_VALUE"""),"MetaAds") -> MetaAds | G7: =IFERROR(__xludf.DUMMYFUNCTION("""COMPUTED_VALUE"""),"ADV - [IG] [FB] [30%2B] [PIEDADE - 40KM] V%C3%81RIOS") -> ADV - [IG] [FB] [30%2B] [PIEDADE - 40KM] V%C3%81RIOS | H7: =IFERROR(__xludf.DUMMYFUNCTION("""COMPUTED_VALUE"""),"Instagram_Stories") -> Instagram_Stories | I7: =IFERROR(__xludf.DUMMYFUNCTION("""COMPUTED_VALUE"""),"07.04 [IMG] [AD04] Pedidos abertos") -> 07.04 [IMG] [AD04] Pedidos abertos | J7: =IFERROR(__xludf.DUMMYFUNCTION("""COMPUTED_VALUE"""),"07.04.2026 [V4] [WB] [LEADS-GRUPO-WHATS] 01") -> 07.04.2026 [V4] [WB] [LEADS-GRUPO-WHATS] 01 | K7: =LEFT(A7,10) -> 2026-04-10 | L7: =DATE(YEAR(SUBSTITUTE(SUBSTITUTE(K7,"-","/",1),"-","/",1)),MONTH(SUBSTITUTE(SUBSTITUTE(K7,"-","/",1),"-","/",1)),DAY(SUBSTITUTE(SUBSTITUTE(K7,"-","/",1),"-","/",1))) -> 46122 | M7: =RIGHT(C7,8) -> 97000778 | N7: =IFERROR(IF(VLOOKUP(M7,'Leads no grupo Saibai'!C:C,1,FALSE)=M7,"Sim"),"Não") -> Sim
A8: 2026-04-10T09:23:53.934Z | B8: olga cipriani | C8: 11953038767 | D8: olga.ciprianis1@gmail.com | E8: https://lp.saibai.com.br/?utm_source=MetaAds&utm_medium=ADV+-+%5BIG%5D+%5BFB%5D+%5B30%2B%5D+%5BPIEDADE+-+40KM%5D+V%C3%81RIOS&utm_campaign=07.04.2026+%5BV4%5D+%5BWB%5D+%5BLEADS-GRUPO-WHATS%5D+01&utm_content=07.04+%5BIMG%5D+%5BAD04%5D+Pedidos+abertos&utm_term=Instagram_Feed&utm_id=120247452154580155&fbclid=PAZXh0bgNhZW0BMABhZGlkAas0bAfOj7tzcnRjBmFwcF9pZA81NjcwNjczNDMzNTI0MjcAAafyRYo2_90IpooxKqGA8j9F7ok0lGg4kYeY5dFCdA92b9PibOmsDkGjC-ap0A_aem_uKOuzVKmqVAxU81O_pOA4w&campaign_id=120247452154580155&ad_id=120247452938090155 | F8: =IFERROR(__xludf.DUMMYFUNCTION("""COMPUTED_VALUE"""),"MetaAds") -> MetaAds | G8: =IFERROR(__xludf.DUMMYFUNCTION("""COMPUTED_VALUE"""),"ADV - [IG] [FB] [30%2B] [PIEDADE - 40KM] V%C3%81RIOS") -> ADV - [IG] [FB] [30%2B] [PIEDADE - 40KM] V%C3%81RIOS | H8: =IFERROR(__xludf.DUMMYFUNCTION("""COMPUTED_VALUE"""),"Instagram_Feed") -> Instagram_Feed | I8: =IFERROR(__xludf.DUMMYFUNCTION("""COMPUTED_VALUE"""),"07.04 [IMG] [AD04] Pedidos abertos") -> 07.04 [IMG] [AD04] Pedidos abertos | J8: =IFERROR(__xludf.DUMMYFUNCTION("""COMPUTED_VALUE"""),"07.04.2026 [V4] [WB] [LEADS-GRUPO-WHATS] 01") -> 07.04.2026 [V4] [WB] [LEADS-GRUPO-WHATS] 01 | K8: =LEFT(A8,10) -> 2026-04-10 | L8: =DATE(YEAR(SUBSTITUTE(SUBSTITUTE(K8,"-","/",1),"-","/",1)),MONTH(SUBSTITUTE(SUBSTITUTE(K8,"-","/",1),"-","/",1)),DAY(SUBSTITUTE(SUBSTITUTE(K8,"-","/",1),"-","/",1))) -> 46122 | M8: =RIGHT(C8,8) -> 53038767 | N8: =IFERROR(IF(VLOOKUP(M8,'Leads no grupo Saibai'!C:C,1,FALSE)=M8,"Sim"),"Não") -> Sim
A9: 2026-04-10T10:33:01.775Z | B9: Luciane Campos | C9: 15991920716 | D9: lucamposmoraes79@gmail.com | E9: https://lp.saibai.com.br/?utm_source=MetaAds&utm_medium=ADV+-+%5BIG%5D+%5BFB%5D+%5B30%2B%5D+%5BPIEDADE+-+40KM%5D+V%C3%81RIOS&utm_campaign=07.04.2026+%5BV4%5D+%5BWB%5D+%5BLEADS-GRUPO-WHATS%5D+01&utm_content=07.04+%5BIMG%5D+%5BAD04%5D+Pedidos+abertos&utm_term=Instagram_Feed&utm_id=120247452154580155&fbclid=PAZXh0bgNhZW0BMABhZGlkAas0bAfOj7tzcnRjBmFwcF9pZA8xMjQwMjQ1NzQyODc0MTQAAafi41HK2ZIMpCodLrKzNuhsjsToZTCTU5UhLxL0mH24dy3pVPGEDwosjG7NdA_aem_lg2YQ_WXpZaScY1I4fUjVg&campaign_id=120247452154580155&ad_id=120247452938090155 | F9: =IFERROR(__xludf.DUMMYFUNCTION("""COMPUTED_VALUE"""),"MetaAds") -> MetaAds | G9: =IFERROR(__xludf.DUMMYFUNCTION("""COMPUTED_VALUE"""),"ADV - [IG] [FB] [30%2B] [PIEDADE - 40KM] V%C3%81RIOS") -> ADV - [IG] [FB] [30%2B] [PIEDADE - 40KM] V%C3%81RIOS | H9: =IFERROR(__xludf.DUMMYFUNCTION("""COMPUTED_VALUE"""),"Instagram_Feed") -> Instagram_Feed | I9: =IFERROR(__xludf.DUMMYFUNCTION("""COMPUTED_VALUE"""),"07.04 [IMG] [AD04] Pedidos abertos") -> 07.04 [IMG] [AD04] Pedidos abertos | J9: =IFERROR(__xludf.DUMMYFUNCTION("""COMPUTED_VALUE"""),"07.04.2026 [V4] [WB] [LEADS-GRUPO-WHATS] 01") -> 07.04.2026 [V4] [WB] [LEADS-GRUPO-WHATS] 01 | K9: =LEFT(A9,10) -> 2026-04-10 | L9: =DATE(YEAR(SUBSTITUTE(SUBSTITUTE(K9,"-","/",1),"-","/",1)),MONTH(SUBSTITUTE(SUBSTITUTE(K9,"-","/",1),"-","/",1)),DAY(SUBSTITUTE(SUBSTITUTE(K9,"-","/",1),"-","/",1))) -> 46122 | M9: =RIGHT(C9,8) -> 91920716 | N9: =IFERROR(IF(VLOOKUP(M9,'Leads no grupo Saibai'!C:C,1,FALSE)=M9,"Sim"),"Não") -> Sim
A10: 2026-04-10T11:58:07.924Z | B10: Mônica Maia | C10: 15991729665 | D10: mo_adv@hotmail.com | E10: https://lp.saibai.com.br/?utm_source=MetaAds&utm_medium=ADV+-+%5BIG%5D+%5BFB%5D+%5B30%2B%5D+%5BPIEDADE+-+40KM%5D+V%C3%81RIOS&utm_campaign=07.04.2026+%5BV4%5D+%5BWB%5D+%5BLEADS-GRUPO-WHATS%5D+01&utm_content=07.04+%5BIMG%5D+%5BAD04%5D+Pedidos+abertos&utm_term=Instagram_Stories&utm_id=120247452154580155&fbclid=PAZXh0bgNhZW0BMABhZGlkAas0bAW7ZytzcnRjBmFwcF9pZA8xMjQwMjQ1NzQyODc0MTQAAad7D3Tpmc6ccGNpA-McIPCMZd0f9qVYEXWoYdN1W4ZFVotKQqsWKVDNYNCYpQ_aem_f_csxX1Gm0Or_AybL4W4YQ&campaign_id=120247452154580155&ad_id=120247452938090155 | F10: =IFERROR(__xludf.DUMMYFUNCTION("""COMPUTED_VALUE"""),"MetaAds") -> MetaAds | G10: =IFERROR(__xludf.DUMMYFUNCTION("""COMPUTED_VALUE"""),"ADV - [IG] [FB] [30%2B] [PIEDADE - 40KM] V%C3%81RIOS") -> ADV - [IG] [FB] [30%2B] [PIEDADE - 40KM] V%C3%81RIOS | H10: =IFERROR(__xludf.DUMMYFUNCTION("""COMPUTED_VALUE"""),"Instagram_Stories") -> Instagram_Stories | I10: =IFERROR(__xludf.DUMMYFUNCTION("""COMPUTED_VALUE"""),"07.04 [IMG] [AD04] Pedidos abertos") -> 07.04 [IMG] [AD04] Pedidos abertos | J10: =IFERROR(__xludf.DUMMYFUNCTION("""COMPUTED_VALUE"""),"07.04.2026 [V4] [WB] [LEADS-GRUPO-WHATS] 01") -> 07.04.2026 [V4] [WB] [LEADS-GRUPO-WHATS] 01 | K10: =LEFT(A10,10) -> 2026-04-10 | L10: =DATE(YEAR(SUBSTITUTE(SUBSTITUTE(K10,"-","/",1),"-","/",1)),MONTH(SUBSTITUTE(SUBSTITUTE(K10,"-","/",1),"-","/",1)),DAY(SUBSTITUTE(SUBSTITUTE(K10,"-","/",1),"-","/",1))) -> 46122 | M10: =RIGHT(C10,8) -> 91729665 | N10: =IFERROR(IF(VLOOKUP(M10,'Leads no grupo Saibai'!C:C,1,FALSE)=M10,"Sim"),"Não") -> Sim
A11: 2026-04-10T12:02:03.351Z | B11: Jose Francisco Gabriotti | C11: 55159815097 | D11: josefranciscogabriotti@gmail.com | E11: https://lp.saibai.com.br/?utm_source=MetaAds&utm_medium=ADV+-+%5BIG%5D+%5BFB%5D+%5B30%2B%5D+%5BPIEDADE+-+40KM%5D+V%C3%81RIOS&utm_campaign=07.04.2026+%5BV4%5D+%5BWB%5D+%5BLEADS-GRUPO-WHATS%5D+01&utm_content=07.04+%5BIMG%5D+%5BAD04%5D+Pedidos+abertos&utm_term=Instagram_Feed&utm_id=120247452154580155&fbclid=PAZXh0bgNhZW0BMABhZGlkAas0bAW7ZytzcnRjBmFwcF9pZA81NjcwNjczNDMzNTI0MjcAAafxyRYJv5YVi6CifZTmm9PDHuPEq1eWVJVRDRYd_BrqVy2ZKPmtaL_Dv5NSEA_aem_6CgVnOQ6Cl01jRgfKwTMPg&campaign_id=120247452154580155&ad_id=120247452938090155 | F11: =IFERROR(__xludf.DUMMYFUNCTION("""COMPUTED_VALUE"""),"MetaAds") -> MetaAds | G11: =IFERROR(__xludf.DUMMYFUNCTION("""COMPUTED_VALUE"""),"ADV - [IG] [FB] [30%2B] [PIEDADE - 40KM] V%C3%81RIOS") -> ADV - [IG] [FB] [30%2B] [PIEDADE - 40KM] V%C3%81RIOS | H11: =IFERROR(__xludf.DUMMYFUNCTION("""COMPUTED_VALUE"""),"Instagram_Feed") -> Instagram_Feed | I11: =IFERROR(__xludf.DUMMYFUNCTION("""COMPUTED_VALUE"""),"07.04 [IMG] [AD04] Pedidos abertos") -> 07.04 [IMG] [AD04] Pedidos abertos | J11: =IFERROR(__xludf.DUMMYFUNCTION("""COMPUTED_VALUE"""),"07.04.2026 [V4] [WB] [LEADS-GRUPO-WHATS] 01") -> 07.04.2026 [V4] [WB] [LEADS-GRUPO-WHATS] 01 | K11: =LEFT(A11,10) -> 2026-04-10 | L11: =DATE(YEAR(SUBSTITUTE(SUBSTITUTE(K11,"-","/",1),"-","/",1)),MONTH(SUBSTITUTE(SUBSTITUTE(K11,"-","/",1),"-","/",1)),DAY(SUBSTITUTE(SUBSTITUTE(K11,"-","/",1),"-","/",1))) -> 46122 | M11: =RIGHT(C11,8) -> 59815097 | N11: =IFERROR(IF(VLOOKUP(M11,'Leads no grupo Saibai'!C:C,1,FALSE)=M11,"Sim"),"Não") -> Não
A12: 2026-04-10T12:07:26.957Z | B12: Eliana Banhete | C12: 55159978270 | D12: lica1755@gmail.com | E12: https://lp.saibai.com.br/?utm_source=MetaAds&utm_medium=ADV+-+%5BIG%5D+%5BFB%5D+%5B30%2B%5D+%5BPIEDADE+-+40KM%5D+V%C3%81RIOS&utm_campaign=07.04.2026+%5BV4%5D+%5BWB%5D+%5BLEADS-GRUPO-WHATS%5D+02&utm_content=07.04+%5BIMG%5D+%5BAD04%5D+Pedidos+abertos&utm_term=Instagram_Stories&utm_id=120248254459350155&fbclid=PAZXh0bgNhZW0BMABhZGlkAas1g0M2JftzcnRjBmFwcF9pZA81NjcwNjczNDMzNTI0MjcAAae-Pi9C5ulqTw1avKSlCfTlAiaFlEjDorhtO4cBmGvSCiUKaU-KCcm7ipMffA_aem_qVPH0fA8b5aEFs-o7UHCZA&campaign_id=120248254459350155&ad_id=120248254459370155 | F12: =IFERROR(__xludf.DUMMYFUNCTION("""COMPUTED_VALUE"""),"MetaAds") -> MetaAds | G12: =IFERROR(__xludf.DUMMYFUNCTION("""COMPUTED_VALUE"""),"ADV - [IG] [FB] [30%2B] [PIEDADE - 40KM] V%C3%81RIOS") -> ADV - [IG] [FB] [30%2B] [PIEDADE - 40KM] V%C3%81RIOS | H12: =IFERROR(__xludf.DUMMYFUNCTION("""COMPUTED_VALUE"""),"Instagram_Stories") -> Instagram_Stories | I12: =IFERROR(__xludf.DUMMYFUNCTION("""COMPUTED_VALUE"""),"07.04 [IMG] [AD04] Pedidos abertos") -> 07.04 [IMG] [AD04] Pedidos abertos | J12: =IFERROR(__xludf.DUMMYFUNCTION("""COMPUTED_VALUE"""),"07.04.2026 [V4] [WB] [LEADS-GRUPO-WHATS] 02") -> 07.04.2026 [V4] [WB] [LEADS-GRUPO-WHATS] 02 | K12: =LEFT(A12,10) -> 2026-04-10 | L12: =DATE(YEAR(SUBSTITUTE(SUBSTITUTE(K12,"-","/",1),"-","/",1)),MONTH(SUBSTITUTE(SUBSTITUTE(K12,"-","/",1),"-","/",1)),DAY(SUBSTITUTE(SUBSTITUTE(K12,"-","/",1),"-","/",1))) -> 46122 | M12: =RIGHT(C12,8) -> 59978270 | N12: =IFERROR(IF(VLOOKUP(M12,'Leads no grupo Saibai'!C:C,1,FALSE)=M12,"Sim"),"Não") -> Não
A13: 2026-04-10T15:53:47.927Z | B13: Clara Espim | C13: 15996081643 | D13: claraespimag@gmail.com | E13: https://lp.saibai.com.br/?utm_source=MetaAds&utm_medium=ADV+-+%5BIG%5D+%5BFB%5D+%5B30%2B%5D+%5BPIEDADE+-+40KM%5D+V%C3%81RIOS&utm_campaign=07.04.2026+%5BV4%5D+%5BWB%5D+%5BLEADS-GRUPO-WHATS%5D+01&utm_content=07.04+%5BIMG%5D+%5BAD04%5D+Pedidos+abertos&utm_term=Instagram_Stories&utm_id=120247452154580155&fbclid=PAZXh0bgNhZW0BMABhZGlkAas0bAW7ZytzcnRjBmFwcF9pZA8xMjQwMjQ1NzQyODc0MTQAAaf9HoTAkjFD5tL3oGfq3V2vAUSfWXAjWQtyelDOo5n9yRZWKbckaeEdc-D0QA_aem_5ljKjwEKKrb7uhuKqWsOAA&campaign_id=120247452154580155&ad_id=120247452938090155 | F13: =IFERROR(__xludf.DUMMYFUNCTION("""COMPUTED_VALUE"""),"MetaAds") -> MetaAds | G13: =IFERROR(__xludf.DUMMYFUNCTION("""COMPUTED_VALUE"""),"ADV - [IG] [FB] [30%2B] [PIEDADE - 40KM] V%C3%81RIOS") -> ADV - [IG] [FB] [30%2B] [PIEDADE - 40KM] V%C3%81RIOS | H13: =IFERROR(__xludf.DUMMYFUNCTION("""COMPUTED_VALUE"""),"Instagram_Stories") -> Instagram_Stories | I13: =IFERROR(__xludf.DUMMYFUNCTION("""COMPUTED_VALUE"""),"07.04 [IMG] [AD04] Pedidos abertos") -> 07.04 [IMG] [AD04] Pedidos abertos | J13: =IFERROR(__xludf.DUMMYFUNCTION("""COMPUTED_VALUE"""),"07.04.2026 [V4] [WB] [LEADS-GRUPO-WHATS] 01") -> 07.04.2026 [V4] [WB] [LEADS-GRUPO-WHATS] 01 | K13: =LEFT(A13,10) -> 2026-04-10 | L13: =DATE(YEAR(SUBSTITUTE(SUBSTITUTE(K13,"-","/",1),"-","/",1)),MONTH(SUBSTITUTE(SUBSTITUTE(K13,"-","/",1),"-","/",1)),DAY(SUBSTITUTE(SUBSTITUTE(K13,"-","/",1),"-","/",1))) -> 46122 | M13: =RIGHT(C13,8) -> 96081643 | N13: =IFERROR(IF(VLOOKUP(M13,'Leads no grupo Saibai'!C:C,1,FALSE)=M13,"Sim"),"Não") -> Sim
A14: 2026-04-10T16:57:01.367Z | B14: Zenaide | C14: 15998141671 | D14: zenaidealmeida_cruz@hotmail.com | E14: https://lp.saibai.com.br/?utm_source=MetaAds&utm_medium=ADV+-+%5BIG%5D+%5BFB%5D+%5B30%2B%5D+%5BPIEDADE+-+40KM%5D+V%C3%81RIOS&utm_campaign=07.04.2026+%5BV4%5D+%5BWB%5D+%5BLEADS-GRUPO-WHATS%5D+01&utm_content=07.04+%5BIMG%5D+%5BAD04%5D+Pedidos+abertos&utm_term=Facebook_Mobile_Feed&fbclid=IwZXh0bgNhZW0BMABhZGlkAas0bAW7ZytzcnRjBmFwcF9pZAwzNTA2ODU1MzE3MjgAAR6g8AzhzvHcJQK1SOp1uFCRSyvd3MHHBZ8f9IGnRmrxu4mx_8AqQ6_KgP6BNQ_aem_k1pDRVarn87y__oJ77WQJg&campaign_id=120247452154580155&ad_id=120247452938090155&utm_id=120247452154580155 | F14: =IFERROR(__xludf.DUMMYFUNCTION("""COMPUTED_VALUE"""),"MetaAds") -> MetaAds | G14: =IFERROR(__xludf.DUMMYFUNCTION("""COMPUTED_VALUE"""),"ADV - [IG] [FB] [30%2B] [PIEDADE - 40KM] V%C3%81RIOS") -> ADV - [IG] [FB] [30%2B] [PIEDADE - 40KM] V%C3%81RIOS | H14: =IFERROR(__xludf.DUMMYFUNCTION("""COMPUTED_VALUE"""),"Facebook_Mobile_Feed") -> Facebook_Mobile_Feed | I14: =IFERROR(__xludf.DUMMYFUNCTION("""COMPUTED_VALUE"""),"07.04 [IMG] [AD04] Pedidos abertos") -> 07.04 [IMG] [AD04] Pedidos abertos | J14: =IFERROR(__xludf.DUMMYFUNCTION("""COMPUTED_VALUE"""),"07.04.2026 [V4] [WB] [LEADS-GRUPO-WHATS] 01") -> 07.04.2026 [V4] [WB] [LEADS-GRUPO-WHATS] 01 | K14: =LEFT(A14,10) -> 2026-04-10 | L14: =DATE(YEAR(SUBSTITUTE(SUBSTITUTE(K14,"-","/",1),"-","/",1)),MONTH(SUBSTITUTE(SUBSTITUTE(K14,"-","/",1),"-","/",1)),DAY(SUBSTITUTE(SUBSTITUTE(K14,"-","/",1),"-","/",1))) -> 46122 | M14: =RIGHT(C14,8) -> 98141671 | N14: =IFERROR(IF(VLOOKUP(M14,'Leads no grupo Saibai'!C:C,1,FALSE)=M14,"Sim"),"Não") -> Sim
A15: 2026-04-11T07:24:44.570Z | B15: Vivian Santos | C15: 15981773711 | D15: vifirmino@gmail.com | E15: https://lp.saibai.com.br/?utm_source=MetaAds&utm_medium=ADV+-+%5BIG%5D+%5BFB%5D+%5B30%2B%5D+%5BPIEDADE+-+40KM%5D+V%C3%81RIOS&utm_campaign=07.04.2026+%5BV4%5D+%5BWB%5D+%5BLEADS-GRUPO-WHATS%5D+01&utm_content=07.04+%5BIMG%5D+%5BAD04%5D+Pedidos+abertos&utm_term=Facebook_Mobile_Feed&fbclid=IwZXh0bgNhZW0BMABhZGlkAas0bAW7ZytzcnRjBmFwcF9pZAwzNTA2ODU1MzE3MjgAAR7oOS-K5DK8biC4NSQcjww51xnw6L40H33qaUuDsve2ZTcbINbSQWzhv2fb0w_aem_KtoMuAMvfgLLnhsIHNpLgw&campaign_id=120247452154580155&ad_id=120247452938090155&utm_id=120247452154580155 | F15: =IFERROR(__xludf.DUMMYFUNCTION("""COMPUTED_VALUE"""),"MetaAds") -> MetaAds | G15: =IFERROR(__xludf.DUMMYFUNCTION("""COMPUTED_VALUE"""),"ADV - [IG] [FB] [30%2B] [PIEDADE - 40KM] V%C3%81RIOS") -> ADV - [IG] [FB] [30%2B] [PIEDADE - 40KM] V%C3%81RIOS | H15: =IFERROR(__xludf.DUMMYFUNCTION("""COMPUTED_VALUE"""),"Facebook_Mobile_Feed") -> Facebook_Mobile_Feed | I15: =IFERROR(__xludf.DUMMYFUNCTION("""COMPUTED_VALUE"""),"07.04 [IMG] [AD04] Pedidos abertos") -> 07.04 [IMG] [AD04] Pedidos abertos | J15: =IFERROR(__xludf.DUMMYFUNCTION("""COMPUTED_VALUE"""),"07.04.2026 [V4] [WB] [LEADS-GRUPO-WHATS] 01") -> 07.04.2026 [V4] [WB] [LEADS-GRUPO-WHATS] 01 | K15: =LEFT(A15,10) -> 2026-04-11 | L15: =DATE(YEAR(SUBSTITUTE(SUBSTITUTE(K15,"-","/",1),"-","/",1)),MONTH(SUBSTITUTE(SUBSTITUTE(K15,"-","/",1),"-","/",1)),DAY(SUBSTITUTE(SUBSTITUTE(K15,"-","/",1),"-","/",1))) -> 46123 | M15: =RIGHT(C15,8) -> 81773711 | N15: =IFERROR(IF(VLOOKUP(M15,'Leads no grupo Saibai'!C:C,1,FALSE)=M15,"Sim"),"Não") -> Sim
A16: 2026-04-11T09:27:25.914Z | B16: Liliane Townsend | C16: 11984977222 | D16: lilianetownsend@hotmail.com | E16: https://lp.saibai.com.br/?utm_source=MetaAds&utm_medium=ADV+-+%5BIG%5D+%5BFB%5D+%5B30%2B%5D+%5BPIEDADE+-+40KM%5D+V%C3%81RIOS&utm_campaign=07.04.2026+%5BV4%5D+%5BWB%5D+%5BLEADS-GRUPO-WHATS%5D+01&utm_content=07.04+%5BIMG%5D+%5BAD04%5D+Pedidos+abertos&utm_term=Instagram_Reels&utm_id=120247452154580155&fbclid=PAZXh0bgNhZW0BMABhZGlkAas0bAfOj7tzcnRjBmFwcF9pZA81NjcwNjczNDMzNTI0MjcAAaely2c8bf5Z1R_xzdtshf9I8Pq7qlA2qC2r8-21ATM-5N_cyYY8dpWvnlwK_A_aem_o7S8fWG0vDPWXqUokMjr4w&campaign_id=120247452154580155&ad_id=120247452938090155 | F16: =IFERROR(__xludf.DUMMYFUNCTION("""COMPUTED_VALUE"""),"MetaAds") -> MetaAds | G16: =IFERROR(__xludf.DUMMYFUNCTION("""COMPUTED_VALUE"""),"ADV - [IG] [FB] [30%2B] [PIEDADE - 40KM] V%C3%81RIOS") -> ADV - [IG] [FB] [30%2B] [PIEDADE - 40KM] V%C3%81RIOS | H16: =IFERROR(__xludf.DUMMYFUNCTION("""COMPUTED_VALUE"""),"Instagram_Reels") -> Instagram_Reels | I16: =IFERROR(__xludf.DUMMYFUNCTION("""COMPUTED_VALUE"""),"07.04 [IMG] [AD04] Pedidos abertos") -> 07.04 [IMG] [AD04] Pedidos abertos | J16: =IFERROR(__xludf.DUMMYFUNCTION("""COMPUTED_VALUE"""),"07.04.2026 [V4] [WB] [LEADS-GRUPO-WHATS] 01") -> 07.04.2026 [V4] [WB] [LEADS-GRUPO-WHATS] 01 | K16: =LEFT(A16,10) -> 2026-04-11 | L16: =DATE(YEAR(SUBSTITUTE(SUBSTITUTE(K16,"-","/",1),"-","/",1)),MONTH(SUBSTITUTE(SUBSTITUTE(K16,"-","/",1),"-","/",1)),DAY(SUBSTITUTE(SUBSTITUTE(K16,"-","/",1),"-","/",1))) -> 46123 | M16: =RIGHT(C16,8) -> 84977222 | N16: =IFERROR(IF(VLOOKUP(M16,'Leads no grupo Saibai'!C:C,1,FALSE)=M16,"Sim"),"Não") -> Sim
A17: 2026-04-11T09:39:23.742Z | B17: Charles Propheta | C17: 55159914599 | D17: lifepraca@gmail.com | E17: https://lp.saibai.com.br/?utm_source=MetaAds&utm_medium=ADV+-+%5BIG%5D+%5BFB%5D+%5B30%2B%5D+%5BPIEDADE+-+40KM%5D+V%C3%81RIOS&utm_campaign=07.04.2026+%5BV4%5D+%5BWB%5D+%5BLEADS-GRUPO-WHATS%5D+01&utm_content=07.04+%5BIMG%5D+%5BAD04%5D+Pedidos+abertos&utm_term=Facebook_Mobile_Feed&fbclid=IwZXh0bgNhZW0BMABhZGlkAas0bAW7ZytzcnRjBmFwcF9pZAwzNTA2ODU1MzE3MjgAAR5fMltPma27TiBvPk6GOBmzcvTbpVrbgAyqNnJOPolpeNUYS08HvvZYGf02Ng_aem_ANy7GA0S2VMWVJgxFfb-Mg&campaign_id=120247452154580155&ad_id=120247452938090155&utm_id=120247452154580155 | F17: =IFERROR(__xludf.DUMMYFUNCTION("""COMPUTED_VALUE"""),"MetaAds") -> MetaAds | G17: =IFERROR(__xludf.DUMMYFUNCTION("""COMPUTED_VALUE"""),"ADV - [IG] [FB] [30%2B] [PIEDADE - 40KM] V%C3%81RIOS") -> ADV - [IG] [FB] [30%2B] [PIEDADE - 40KM] V%C3%81RIOS | H17: =IFERROR(__xludf.DUMMYFUNCTION("""COMPUTED_VALUE"""),"Facebook_Mobile_Feed") -> Facebook_Mobile_Feed | I17: =IFERROR(__xludf.DUMMYFUNCTION("""COMPUTED_VALUE"""),"07.04 [IMG] [AD04] Pedidos abertos") -> 07.04 [IMG] [AD04] Pedidos abertos | J17: =IFERROR(__xludf.DUMMYFUNCTION("""COMPUTED_VALUE"""),"07.04.2026 [V4] [WB] [LEADS-GRUPO-WHATS] 01") -> 07.04.2026 [V4] [WB] [LEADS-GRUPO-WHATS] 01 | K17: =LEFT(A17,10) -> 2026-04-11 | L17: =DATE(YEAR(SUBSTITUTE(SUBSTITUTE(K17,"-","/",1),"-","/",1)),MONTH(SUBSTITUTE(SUBSTITUTE(K17,"-","/",1),"-","/",1)),DAY(SUBSTITUTE(SUBSTITUTE(K17,"-","/",1),"-","/",1))) -> 46123 | M17: =RIGHT(C17,8) -> 59914599 | N17: =IFERROR(IF(VLOOKUP(M17,'Leads no grupo Saibai'!C:C,1,FALSE)=M17,"Sim"),"Não") -> Não
A18: 2026-04-11T09:46:38.100Z | B18: Maira Gatto | C18: 55159912266 | D18: maira.gatto@hotmail.com | E18: https://lp.saibai.com.br/?utm_source=MetaAds&utm_medium=ADV+-+%5BIG%5D+%5BFB%5D+%5B30%2B%5D+%5BPIEDADE+-+40KM%5D+V%C3%81RIOS&utm_campaign=07.04.2026+%5BV4%5D+%5BWB%5D+%5BLEADS-GRUPO-WHATS%5D+01&utm_content=07.04+%5BIMG%5D+%5BAD04%5D+Pedidos+abertos&utm_term=Facebook_Mobile_Feed&fbclid=IwZXh0bgNhZW0BMABhZGlkAas0bAW7ZytzcnRjBmFwcF9pZAwzNTA2ODU1MzE3MjgAAR5Jqo986l2Sci96yOA4olFRL2HBhKuV40DXg7FUazU3UTpbOVoVyCSjXwRfGA_aem_B667vrz-6KHgh2qBxOzaYg&campaign_id=120247452154580155&ad_id=120247452938090155&utm_id=120247452154580155 | F18: =IFERROR(__xludf.DUMMYFUNCTION("""COMPUTED_VALUE"""),"MetaAds") -> MetaAds | G18: =IFERROR(__xludf.DUMMYFUNCTION("""COMPUTED_VALUE"""),"ADV - [IG] [FB] [30%2B] [PIEDADE - 40KM] V%C3%81RIOS") -> ADV - [IG] [FB] [30%2B] [PIEDADE - 40KM] V%C3%81RIOS | H18: =IFERROR(__xludf.DUMMYFUNCTION("""COMPUTED_VALUE"""),"Facebook_Mobile_Feed") -> Facebook_Mobile_Feed | I18: =IFERROR(__xludf.DUMMYFUNCTION("""COMPUTED_VALUE"""),"07.04 [IMG] [AD04] Pedidos abertos") -> 07.04 [IMG] [AD04] Pedidos abertos | J18: =IFERROR(__xludf.DUMMYFUNCTION("""COMPUTED_VALUE"""),"07.04.2026 [V4] [WB] [LEADS-GRUPO-WHATS] 01") -> 07.04.2026 [V4] [WB] [LEADS-GRUPO-WHATS] 01 | K18: =LEFT(A18,10) -> 2026-04-11 | L18: =DATE(YEAR(SUBSTITUTE(SUBSTITUTE(K18,"-","/",1),"-","/",1)),MONTH(SUBSTITUTE(SUBSTITUTE(K18,"-","/",1),"-","/",1)),DAY(SUBSTITUTE(SUBSTITUTE(K18,"-","/",1),"-","/",1))) -> 46123 | M18: =RIGHT(C18,8) -> 59912266 | N18: =IFERROR(IF(VLOOKUP(M18,'Leads no grupo Saibai'!C:C,1,FALSE)=M18,"Sim"),"Não") -> Não
A19: 2026-04-11T10:16:55.353Z | B19: Gilberto Cardoso | C19: 11974751568 | D19: gilbertocardosovie@yahoo.com.br | E19: https://lp.saibai.com.br/?utm_source=MetaAds&utm_medium=ADV+-+%5BIG%5D+%5BFB%5D+%5B30%2B%5D+%5BPIEDADE+-+40KM%5D+V%C3%81RIOS&utm_campaign=07.04.2026+%5BV4%5D+%5BWB%5D+%5BLEADS-GRUPO-WHATS%5D+02&utm_content=07.04+%5BIMG%5D+%5BAD04%5D+Pedidos+abertos&utm_term=Instagram_Stories&utm_id=120248254459350155&fbclid=PAZXh0bgNhZW0BMABhZGlkAas1g0M2JftzcnRjBmFwcF9pZA81NjcwNjczNDMzNTI0MjcAAae-Pi9C5ulqTw1avKSlCfTlAiaFlEjDorhtO4cBmGvSCiUKaU-KCcm7ipMffA_aem_qVPH0fA8b5aEFs-o7UHCZA&campaign_id=120248254459350155&ad_id=120248254459370155 | F19: =IFERROR(__xludf.DUMMYFUNCTION("""COMPUTED_VALUE"""),"MetaAds") -> MetaAds | G19: =IFERROR(__xludf.DUMMYFUNCTION("""COMPUTED_VALUE"""),"ADV - [IG] [FB] [30%2B] [PIEDADE - 40KM] V%C3%81RIOS") -> ADV - [IG] [FB] [30%2B] [PIEDADE - 40KM] V%C3%81RIOS | H19: =IFERROR(__xludf.DUMMYFUNCTION("""COMPUTED_VALUE"""),"Instagram_Stories") -> Instagram_Stories | I19: =IFERROR(__xludf.DUMMYFUNCTION("""COMPUTED_VALUE"""),"07.04 [IMG] [AD04] Pedidos abertos") -> 07.04 [IMG] [AD04] Pedidos abertos | J19: =IFERROR(__xludf.DUMMYFUNCTION("""COMPUTED_VALUE"""),"07.04.2026 [V4] [WB] [LEADS-GRUPO-WHATS] 02") -> 07.04.2026 [V4] [WB] [LEADS-GRUPO-WHATS] 02 | K19: =LEFT(A19,10) -> 2026-04-11 | L19: =DATE(YEAR(SUBSTITUTE(SUBSTITUTE(K19,"-","/",1),"-","/",1)),MONTH(SUBSTITUTE(SUBSTITUTE(K19,"-","/",1),"-","/",1)),DAY(SUBSTITUTE(SUBSTITUTE(K19,"-","/",1),"-","/",1))) -> 46123 | M19: =RIGHT(C19,8) -> 74751568 | N19: =IFERROR(IF(VLOOKUP(M19,'Leads no grupo Saibai'!C:C,1,FALSE)=M19,"Sim"),"Não") -> Sim
A20: 2026-04-11T10:53:19.291Z | B20: Solange da | C20: 15991039369 | D20: sc_marcolini@hotmail.com | E20: https://lp.saibai.com.br/?utm_source=MetaAds&utm_medium=ADV+-+%5BIG%5D+%5BFB%5D+%5B30%2B%5D+%5BPIEDADE+-+40KM%5D+V%C3%81RIOS&utm_campaign=07.04.2026+%5BV4%5D+%5BWB%5D+%5BLEADS-GRUPO-WHATS%5D+01&utm_content=07.04+%5BIMG%5D+%5BAD04%5D+Pedidos+abertos&utm_term=Facebook_Mobile_Reels&fbclid=IwZXh0bgNhZW0BMABhZGlkAas0bAW7ZytzcnRjBmFwcF9pZAwzNTA2ODU1MzE3MjgAAR7EuNGZkOXTRnrvcdFCcgaWIYD3wGDG7rRAAY71NSXZ2Pl_gqg3REC83fAwpA_aem_pnNhTBJcvTiYaZe86OJQgA&campaign_id=120247452154580155&ad_id=120247452938090155&utm_id=120247452154580155 | F20: =IFERROR(__xludf.DUMMYFUNCTION("""COMPUTED_VALUE"""),"MetaAds") -> MetaAds | G20: =IFERROR(__xludf.DUMMYFUNCTION("""COMPUTED_VALUE"""),"ADV - [IG] [FB] [30%2B] [PIEDADE - 40KM] V%C3%81RIOS") -> ADV - [IG] [FB] [30%2B] [PIEDADE - 40KM] V%C3%81RIOS | H20: =IFERROR(__xludf.DUMMYFUNCTION("""COMPUTED_VALUE"""),"Facebook_Mobile_Reels") -> Facebook_Mobile_Reels | I20: =IFERROR(__xludf.DUMMYFUNCTION("""COMPUTED_VALUE"""),"07.04 [IMG] [AD04] Pedidos abertos") -> 07.04 [IMG] [AD04] Pedidos abertos | J20: =IFERROR(__xludf.DUMMYFUNCTION("""COMPUTED_VALUE"""),"07.04.2026 [V4] [WB] [LEADS-GRUPO-WHATS] 01") -> 07.04.2026 [V4] [WB] [LEADS-GRUPO-WHATS] 01 | K20: =LEFT(A20,10) -> 2026-04-11 | L20: =DATE(YEAR(SUBSTITUTE(SUBSTITUTE(K20,"-","/",1),"-","/",1)),MONTH(SUBSTITUTE(SUBSTITUTE(K20,"-","/",1),"-","/",1)),DAY(SUBSTITUTE(SUBSTITUTE(K20,"-","/",1),"-","/",1))) -> 46123 | M20: =RIGHT(C20,8) -> 91039369 | N20: =IFERROR(IF(VLOOKUP(M20,'Leads no grupo Saibai'!C:C,1,FALSE)=M20,"Sim"),"Não") -> Não
A21: 2026-04-11T13:22:18.922Z | B21: Alessandra Augusto Costa | C21: 15996313568 | D21: aaugustocosta@prof.educacao.sp.gov.br | E21: https://lp.saibai.com.br/?utm_source=MetaAds&utm_medium=ADV+-+%5BIG%5D+%5BFB%5D+%5B30%2B%5D+%5BPIEDADE+-+40KM%5D+V%C3%81RIOS&utm_campaign=07.04.2026+%5BV4%5D+%5BWB%5D+%5BLEADS-GRUPO-WHATS%5D+02&utm_content=07.04+%5BIMG%5D+%5BAD04%5D+Pedidos+abertos&utm_term=Instagram_Stories&utm_id=120248254459350155&fbclid=PAZXh0bgNhZW0BMABhZGlkAas1g0M2JftzcnRjBmFwcF9pZA81NjcwNjczNDMzNTI0MjcAAae-Pi9C5ulqTw1avKSlCfTlAiaFlEjDorhtO4cBmGvSCiUKaU-KCcm7ipMffA_aem_qVPH0fA8b5aEFs-o7UHCZA&campaign_id=120248254459350155&ad_id=120248254459370155 | F21: =IFERROR(__xludf.DUMMYFUNCTION("""COMPUTED_VALUE"""),"MetaAds") -> MetaAds | G21: =IFERROR(__xludf.DUMMYFUNCTION("""COMPUTED_VALUE"""),"ADV - [IG] [FB] [30%2B] [PIEDADE - 40KM] V%C3%81RIOS") -> ADV - [IG] [FB] [30%2B] [PIEDADE - 40KM] V%C3%81RIOS | H21: =IFERROR(__xludf.DUMMYFUNCTION("""COMPUTED_VALUE"""),"Instagram_Stories") -> Instagram_Stories | I21: =IFERROR(__xludf.DUMMYFUNCTION("""COMPUTED_VALUE"""),"07.04 [IMG] [AD04] Pedidos abertos") -> 07.04 [IMG] [AD04] Pedidos abertos | J21: =IFERROR(__xludf.DUMMYFUNCTION("""COMPUTED_VALUE"""),"07.04.2026 [V4] [WB] [LEADS-GRUPO-WHATS] 02") -> 07.04.2026 [V4] [WB] [LEADS-GRUPO-WHATS] 02 | K21: =LEFT(A21,10) -> 2026-04-11 | L21: =DATE(YEAR(SUBSTITUTE(SUBSTITUTE(K21,"-","/",1),"-","/",1)),MONTH(SUBSTITUTE(SUBSTITUTE(K21,"-","/",1),"-","/",1)),DAY(SUBSTITUTE(SUBSTITUTE(K21,"-","/",1),"-","/",1))) -> 46123 | M21: =RIGHT(C21,8) -> 96313568 | N21: =IFERROR(IF(VLOOKUP(M21,'Leads no grupo Saibai'!C:C,1,FALSE)=M21,"Sim"),"Não") -> Sim
A22: 2026-04-11T14:20:39.848Z | B22: Aparecida | C22: 15996291515 | D22: cidazanela@hotmail.com | E22: https://lp.saibai.com.br/?utm_source=MetaAds&utm_medium=ADV+-+%5BIG%5D+%5BFB%5D+%5B30%2B%5D+%5BPIEDADE+-+40KM%5D+V%C3%81RIOS&utm_campaign=07.04.2026+%5BV4%5D+%5BWB%5D+%5BLEADS-GRUPO-WHATS%5D+01&utm_content=07.04+%5BIMG%5D+%5BAD04%5D+Pedidos+abertos&utm_term=Facebook_Mobile_Feed&fbclid=IwZXh0bgNhZW0BMABhZGlkAas0bAW7ZytzcnRjBmFwcF9pZAwzNTA2ODU1MzE3MjgAAR4CvRkqhDILzZPGlshiEbcAOWFjQj5UjRNL9-ML4APpZkL2U8r77NRAz2H0RQ_aem_sbI6x_6Q467Ds4gt-qqvXQ&campaign_id=120247452154580155&ad_id=120247452938090155&utm_id=120247452154580155 | F22: =IFERROR(__xludf.DUMMYFUNCTION("""COMPUTED_VALUE"""),"MetaAds") -> MetaAds | G22: =IFERROR(__xludf.DUMMYFUNCTION("""COMPUTED_VALUE"""),"ADV - [IG] [FB] [30%2B] [PIEDADE - 40KM] V%C3%81RIOS") -> ADV - [IG] [FB] [30%2B] [PIEDADE - 40KM] V%C3%81RIOS | H22: =IFERROR(__xludf.DUMMYFUNCTION("""COMPUTED_VALUE"""),"Facebook_Mobile_Feed") -> Facebook_Mobile_Feed | I22: =IFERROR(__xludf.DUMMYFUNCTION("""COMPUTED_VALUE"""),"07.04 [IMG] [AD04] Pedidos abertos") -> 07.04 [IMG] [AD04] Pedidos abertos | J22: =IFERROR(__xludf.DUMMYFUNCTION("""COMPUTED_VALUE"""),"07.04.2026 [V4] [WB] [LEADS-GRUPO-WHATS] 01") -> 07.04.2026 [V4] [WB] [LEADS-GRUPO-WHATS] 01 | K22: =LEFT(A22,10) -> 2026-04-11 | L22: =DATE(YEAR(SUBSTITUTE(SUBSTITUTE(K22,"-","/",1),"-","/",1)),MONTH(SUBSTITUTE(SUBSTITUTE(K22,"-","/",1),"-","/",1)),DAY(SUBSTITUTE(SUBSTITUTE(K22,"-","/",1),"-","/",1))) -> 46123 | M22: =RIGHT(C22,8) -> 96291515 | N22: =IFERROR(IF(VLOOKUP(M22,'Leads no grupo Saibai'!C:C,1,FALSE)=M22,"Sim"),"Não") -> Não
A23: 2026-04-11T14:43:42.537Z | B23: edmaradeoliveira44@gmail.com | C23: 15996667904 | D23: edmaradeoliveira44@gmail.co.com | E23: https://lp.saibai.com.br/?utm_source=MetaAds&utm_medium=ADV+-+%5BIG%5D+%5BFB%5D+%5B30%2B%5D+%5BPIEDADE+-+40KM%5D+V%C3%81RIOS&utm_campaign=07.04.2026+%5BV4%5D+%5BWB%5D+%5BLEADS-GRUPO-WHATS%5D+01&utm_content=07.04+%5BIMG%5D+%5BAD04%5D+Pedidos+abertos&utm_term=Instagram_Feed&utm_id=120247452154580155&fbclid=PAZXh0bgNhZW0BMABhZGlkAas0bAW7ZytzcnRjBmFwcF9pZA81NjcwNjczNDMzNTI0MjcAAaf2PMnI02jF2DvJxBzra9hp8TYq2K4AR3kKRePi_cY_5YRyduph0lZXi5-i9A_aem_YZ9lMCmM6-MXXAoRyV5nbw&campaign_id=120247452154580155&ad_id=120247452938090155 | F23: =IFERROR(__xludf.DUMMYFUNCTION("""COMPUTED_VALUE"""),"MetaAds") -> MetaAds | G23: =IFERROR(__xludf.DUMMYFUNCTION("""COMPUTED_VALUE"""),"ADV - [IG] [FB] [30%2B] [PIEDADE - 40KM] V%C3%81RIOS") -> ADV - [IG] [FB] [30%2B] [PIEDADE - 40KM] V%C3%81RIOS | H23: =IFERROR(__xludf.DUMMYFUNCTION("""COMPUTED_VALUE"""),"Instagram_Feed") -> Instagram_Feed | I23: =IFERROR(__xludf.DUMMYFUNCTION("""COMPUTED_VALUE"""),"07.04 [IMG] [AD04] Pedidos abertos") -> 07.04 [IMG] [AD04] Pedidos abertos | J23: =IFERROR(__xludf.DUMMYFUNCTION("""COMPUTED_VALUE"""),"07.04.2026 [V4] [WB] [LEADS-GRUPO-WHATS] 01") -> 07.04.2026 [V4] [WB] [LEADS-GRUPO-WHATS] 01 | K23: =LEFT(A23,10) -> 2026-04-11 | L23: =DATE(YEAR(SUBSTITUTE(SUBSTITUTE(K23,"-","/",1),"-","/",1)),MONTH(SUBSTITUTE(SUBSTITUTE(K23,"-","/",1),"-","/",1)),DAY(SUBSTITUTE(SUBSTITUTE(K23,"-","/",1),"-","/",1))) -> 46123 | M23: =RIGHT(C23,8) -> 96667904 | N23: =IFERROR(IF(VLOOKUP(M23,'Leads no grupo Saibai'!C:C,1,FALSE)=M23,"Sim"),"Não") -> Sim
A24: 2026-04-11T16:10:54.439Z | B24: Lenice Santos | C24: 15997321884 | D24: lenice.ap.santos@gmail.com | E24: https://lp.saibai.com.br/?utm_source=MetaAds&utm_medium=ADV+-+%5BIG%5D+%5BFB%5D+%5B30%2B%5D+%5BPIEDADE+-+40KM%5D+V%C3%81RIOS&utm_campaign=07.04.2026+%5BV4%5D+%5BWB%5D+%5BLEADS-GRUPO-WHATS%5D+01&utm_content=07.04+%5BIMG%5D+%5BAD04%5D+Pedidos+abertos&utm_term=Facebook_Mobile_Feed&fbclid=IwZXh0bgNhZW0BMABhZGlkAas0bAfOj7tzcnRjBmFwcF9pZAwzNTA2ODU1MzE3MjgAAR4o0x0VZm88HbTlzU_bZzH_d-IXUDKHJV8aNjcrYdEI1jZl0xS7IFYIdOjuTA_aem_GdnH90_FI7_irV8br8itIA&campaign_id=120247452154580155&ad_id=120247452938090155&utm_id=120247452154580155 | F24: =IFERROR(__xludf.DUMMYFUNCTION("""COMPUTED_VALUE"""),"MetaAds") -> MetaAds | G24: =IFERROR(__xludf.DUMMYFUNCTION("""COMPUTED_VALUE"""),"ADV - [IG] [FB] [30%2B] [PIEDADE - 40KM] V%C3%81RIOS") -> ADV - [IG] [FB] [30%2B] [PIEDADE - 40KM] V%C3%81RIOS | H24: =IFERROR(__xludf.DUMMYFUNCTION("""COMPUTED_VALUE"""),"Facebook_Mobile_Feed") -> Facebook_Mobile_Feed | I24: =IFERROR(__xludf.DUMMYFUNCTION("""COMPUTED_VALUE"""),"07.04 [IMG] [AD04] Pedidos abertos") -> 07.04 [IMG] [AD04] Pedidos abertos | J24: =IFERROR(__xludf.DUMMYFUNCTION("""COMPUTED_VALUE"""),"07.04.2026 [V4] [WB] [LEADS-GRUPO-WHATS] 01") -> 07.04.2026 [V4] [WB] [LEADS-GRUPO-WHATS] 01 | K24: =LEFT(A24,10) -> 2026-04-11 | L24: =DATE(YEAR(SUBSTITUTE(SUBSTITUTE(K24,"-","/",1),"-","/",1)),MONTH(SUBSTITUTE(SUBSTITUTE(K24,"-","/",1),"-","/",1)),DAY(SUBSTITUTE(SUBSTITUTE(K24,"-","/",1),"-","/",1))) -> 46123 | M24: =RIGHT(C24,8) -> 97321884 | N24: =IFERROR(IF(VLOOKUP(M24,'Leads no grupo Saibai'!C:C,1,FALSE)=M24,"Sim"),"Não") -> Não
A25: 2026-04-11T19:35:01.479Z | B25: Maisa Torres | C25: 15991143109 | D25: maisapxo@yahoo.com.br | E25: https://lp.saibai.com.br/?utm_source=MetaAds&utm_medium=ADV+-+%5BIG%5D+%5BFB%5D+%5B30%2B%5D+%5BPIEDADE+-+40KM%5D+V%C3%81RIOS&utm_campaign=07.04.2026+%5BV4%5D+%5BWB%5D+%5BLEADS-GRUPO-WHATS%5D+01&utm_content=07.04+%5BIMG%5D+%5BAD04%5D+Pedidos+abertos&utm_term=Instagram_Stories&utm_id=120247452154580155&fbclid=PAZXh0bgNhZW0BMABhZGlkAas0a_lii3tzcnRjBmFwcF9pZA81NjcwNjczNDMzNTI0MjcAAae-K-ywuFXkHPpcn5lIWZjVpFnHSAliaUgsyVFu7MPBd7NtGWxucH_zdNs26g_aem_V8pnN_tD-7Sd8qyolMoDew&campaign_id=120247452154580155&ad_id=120247452938090155 | F25: =IFERROR(__xludf.DUMMYFUNCTION("""COMPUTED_VALUE"""),"MetaAds") -> MetaAds | G25: =IFERROR(__xludf.DUMMYFUNCTION("""COMPUTED_VALUE"""),"ADV - [IG] [FB] [30%2B] [PIEDADE - 40KM] V%C3%81RIOS") -> ADV - [IG] [FB] [30%2B] [PIEDADE - 40KM] V%C3%81RIOS | H25: =IFERROR(__xludf.DUMMYFUNCTION("""COMPUTED_VALUE"""),"Instagram_Stories") -> Instagram_Stories | I25: =IFERROR(__xludf.DUMMYFUNCTION("""COMPUTED_VALUE"""),"07.04 [IMG] [AD04] Pedidos abertos") -> 07.04 [IMG] [AD04] Pedidos abertos | J25: =IFERROR(__xludf.DUMMYFUNCTION("""COMPUTED_VALUE"""),"07.04.2026 [V4] [WB] [LEADS-GRUPO-WHATS] 01") -> 07.04.2026 [V4] [WB] [LEADS-GRUPO-WHATS] 01 | K25: =LEFT(A25,10) -> 2026-04-11 | L25: =DATE(YEAR(SUBSTITUTE(SUBSTITUTE(K25,"-","/",1),"-","/",1)),MONTH(SUBSTITUTE(SUBSTITUTE(K25,"-","/",1),"-","/",1)),DAY(SUBSTITUTE(SUBSTITUTE(K25,"-","/",1),"-","/",1))) -> 46123 | M25: =RIGHT(C25,8) -> 91143109 | N25: =IFERROR(IF(VLOOKUP(M25,'Leads no grupo Saibai'!C:C,1,FALSE)=M25,"Sim"),"Não") -> Sim
A26: 2026-04-11T20:58:48.045Z | B26: Suely A foschi tomazoli | C26: 11917539658 | D26: sufoschi@hotmail.com | E26: https://lp.saibai.com.br/?utm_source=MetaAds&utm_medium=ADV+-+%5BIG%5D+%5BFB%5D+%5B30%2B%5D+%5BPIEDADE+-+40KM%5D+V%C3%81RIOS&utm_campaign=07.04.2026+%5BV4%5D+%5BWB%5D+%5BLEADS-GRUPO-WHATS%5D+01&utm_content=07.04+%5BIMG%5D+%5BAD04%5D+Pedidos+abertos&utm_term=Instagram_Stories&utm_id=120247452154580155&fbclid=PAZXh0bgNhZW0BMABhZGlkAas0bAW7ZytzcnRjBmFwcF9pZA81NjcwNjczNDMzNTI0MjcAAadAxH3LT6FELi8bDGwd1vAmuhZ0tpf_dxifFPpTLpahm2EHVGei94hN4-wA8Q_aem_umlTAOYv8wHa8qH-QrvxkA&campaign_id=120247452154580155&ad_id=120247452938090155 | F26: =IFERROR(__xludf.DUMMYFUNCTION("""COMPUTED_VALUE"""),"MetaAds") -> MetaAds | G26: =IFERROR(__xludf.DUMMYFUNCTION("""COMPUTED_VALUE"""),"ADV - [IG] [FB] [30%2B] [PIEDADE - 40KM] V%C3%81RIOS") -> ADV - [IG] [FB] [30%2B] [PIEDADE - 40KM] V%C3%81RIOS | H26: =IFERROR(__xludf.DUMMYFUNCTION("""COMPUTED_VALUE"""),"Instagram_Stories") -> Instagram_Stories | I26: =IFERROR(__xludf.DUMMYFUNCTION("""COMPUTED_VALUE"""),"07.04 [IMG] [AD04] Pedidos abertos") -> 07.04 [IMG] [AD04] Pedidos abertos | J26: =IFERROR(__xludf.DUMMYFUNCTION("""COMPUTED_VALUE"""),"07.04.2026 [V4] [WB] [LEADS-GRUPO-WHATS] 01") -> 07.04.2026 [V4] [WB] [LEADS-GRUPO-WHATS] 01 | K26: =LEFT(A26,10) -> 2026-04-11 | L26: =DATE(YEAR(SUBSTITUTE(SUBSTITUTE(K26,"-","/",1),"-","/",1)),MONTH(SUBSTITUTE(SUBSTITUTE(K26,"-","/",1),"-","/",1)),DAY(SUBSTITUTE(SUBSTITUTE(K26,"-","/",1),"-","/",1))) -> 46123 | M26: =RIGHT(C26,8) -> 17539658 | N26: =IFERROR(IF(VLOOKUP(M26,'Leads no grupo Saibai'!C:C,1,FALSE)=M26,"Sim"),"Não") -> Sim
A27: 2026-04-12T03:09:06.634Z | B27: Kelly Hollen | C27: 15988211837 | D27: damaris.hollen@gmail.com | E27: https://lp.saibai.com.br/?utm_source=MetaAds&utm_medium=ADV+-+%5BIG%5D+%5BFB%5D+%5B30%2B%5D+%5BPIEDADE+-+40KM%5D+V%C3%81RIOS&utm_campaign=07.04.2026+%5BV4%5D+%5BWB%5D+%5BLEADS-GRUPO-WHATS%5D+01&utm_content=07.04+%5BIMG%5D+%5BAD04%5D+Pedidos+abertos&utm_term=Facebook_Mobile_Feed&fbclid=IwZXh0bgNhZW0BMABhZGlkAas0bAW7ZytzcnRjBmFwcF9pZAwzNTA2ODU1MzE3MjgAAR7w8SeqRb8h8EvmPYCA7gNfTn1K-lKEeGUPkD0_ZBStGWUp2RrqZ_T6RaEz9g_aem_nCmRvMh7BrM-_rsWkPmvmQ&campaign_id=120247452154580155&ad_id=120247452938090155&utm_id=120247452154580155 | F27: =IFERROR(__xludf.DUMMYFUNCTION("""COMPUTED_VALUE"""),"MetaAds") -> MetaAds | G27: =IFERROR(__xludf.DUMMYFUNCTION("""COMPUTED_VALUE"""),"ADV - [IG] [FB] [30%2B] [PIEDADE - 40KM] V%C3%81RIOS") -> ADV - [IG] [FB] [30%2B] [PIEDADE - 40KM] V%C3%81RIOS | H27: =IFERROR(__xludf.DUMMYFUNCTION("""COMPUTED_VALUE"""),"Facebook_Mobile_Feed") -> Facebook_Mobile_Feed | I27: =IFERROR(__xludf.DUMMYFUNCTION("""COMPUTED_VALUE"""),"07.04 [IMG] [AD04] Pedidos abertos") -> 07.04 [IMG] [AD04] Pedidos abertos | J27: =IFERROR(__xludf.DUMMYFUNCTION("""COMPUTED_VALUE"""),"07.04.2026 [V4] [WB] [LEADS-GRUPO-WHATS] 01") -> 07.04.2026 [V4] [WB] [LEADS-GRUPO-WHATS] 01 | K27: =LEFT(A27,10) -> 2026-04-12 | L27: =DATE(YEAR(SUBSTITUTE(SUBSTITUTE(K27,"-","/",1),"-","/",1)),MONTH(SUBSTITUTE(SUBSTITUTE(K27,"-","/",1),"-","/",1)),DAY(SUBSTITUTE(SUBSTITUTE(K27,"-","/",1),"-","/",1))) -> 46124 | M27: =RIGHT(C27,8) -> 88211837 | N27: =IFERROR(IF(VLOOKUP(M27,'Leads no grupo Saibai'!C:C,1,FALSE)=M27,"Sim"),"Não") -> Sim
A28: 2026-04-12T03:39:29.364Z | B28: Girlane Sousa | C28: 15988030611 | D28: girlanesouza2014@gmail.com | E28: https://lp.saibai.com.br/?utm_source=MetaAds&utm_medium=ADV+-+%5BIG%5D+%5BFB%5D+%5B30%2B%5D+%5BPIEDADE+-+40KM%5D+V%C3%81RIOS&utm_campaign=07.04.2026+%5BV4%5D+%5BWB%5D+%5BLEADS-GRUPO-WHATS%5D+01&utm_content=07.04+%5BIMG%5D+%5BAD04%5D+Pedidos+abertos&utm_term=Facebook_Mobile_Feed&fbclid=IwZXh0bgNhZW0BMABhZGlkAas0bAW7ZytzcnRjBmFwcF9pZAwzNTA2ODU1MzE3MjgAAR6v67-LuhXYM-RpYXTVFX4MMcZjvWW79d5VE5p-VmkBuPiWFbuD2AyYE1E9Xg_aem_fkRBUDx8LS4EAP6T7hYglA&campaign_id=120247452154580155&ad_id=120247452938090155&utm_id=120247452154580155 | F28: =IFERROR(__xludf.DUMMYFUNCTION("""COMPUTED_VALUE"""),"MetaAds") -> MetaAds | G28: =IFERROR(__xludf.DUMMYFUNCTION("""COMPUTED_VALUE"""),"ADV - [IG] [FB] [30%2B] [PIEDADE - 40KM] V%C3%81RIOS") -> ADV - [IG] [FB] [30%2B] [PIEDADE - 40KM] V%C3%81RIOS | H28: =IFERROR(__xludf.DUMMYFUNCTION("""COMPUTED_VALUE"""),"Facebook_Mobile_Feed") -> Facebook_Mobile_Feed | I28: =IFERROR(__xludf.DUMMYFUNCTION("""COMPUTED_VALUE"""),"07.04 [IMG] [AD04] Pedidos abertos") -> 07.04 [IMG] [AD04] Pedidos abertos | J28: =IFERROR(__xludf.DUMMYFUNCTION("""COMPUTED_VALUE"""),"07.04.2026 [V4] [WB] [LEADS-GRUPO-WHATS] 01") -> 07.04.2026 [V4] [WB] [LEADS-GRUPO-WHATS] 01 | K28: =LEFT(A28,10) -> 2026-04-12 | L28: =DATE(YEAR(SUBSTITUTE(SUBSTITUTE(K28,"-","/",1),"-","/",1)),MONTH(SUBSTITUTE(SUBSTITUTE(K28,"-","/",1),"-","/",1)),DAY(SUBSTITUTE(SUBSTITUTE(K28,"-","/",1),"-","/",1))) -> 46124 | M28: =RIGHT(C28,8) -> 88030611 | N28: =IFERROR(IF(VLOOKUP(M28,'Leads no grupo Saibai'!C:C,1,FALSE)=M28,"Sim"),"Não") -> Sim
A29: 2026-04-12T03:39:56.328Z | B29: Girlane Sousa | C29: 15988030611 | D29: girlanesouza2014@gmail.com | E29: https://lp.saibai.com.br/?utm_source=MetaAds&utm_medium=ADV+-+%5BIG%5D+%5BFB%5D+%5B30%2B%5D+%5BPIEDADE+-+40KM%5D+V%C3%81RIOS&utm_campaign=07.04.2026+%5BV4%5D+%5BWB%5D+%5BLEADS-GRUPO-WHATS%5D+01&utm_content=07.04+%5BIMG%5D+%5BAD04%5D+Pedidos+abertos&utm_term=Facebook_Mobile_Feed&fbclid=IwZXh0bgNhZW0BMABhZGlkAas0bAW7ZytzcnRjBmFwcF9pZAwzNTA2ODU1MzE3MjgAAR6v67-LuhXYM-RpYXTVFX4MMcZjvWW79d5VE5p-VmkBuPiWFbuD2AyYE1E9Xg_aem_fkRBUDx8LS4EAP6T7hYglA&campaign_id=120247452154580155&ad_id=120247452938090155&utm_id=120247452154580155 | F29: =IFERROR(__xludf.DUMMYFUNCTION("""COMPUTED_VALUE"""),"MetaAds") -> MetaAds | G29: =IFERROR(__xludf.DUMMYFUNCTION("""COMPUTED_VALUE"""),"ADV - [IG] [FB] [30%2B] [PIEDADE - 40KM] V%C3%81RIOS") -> ADV - [IG] [FB] [30%2B] [PIEDADE - 40KM] V%C3%81RIOS | H29: =IFERROR(__xludf.DUMMYFUNCTION("""COMPUTED_VALUE"""),"Facebook_Mobile_Feed") -> Facebook_Mobile_Feed | I29: =IFERROR(__xludf.DUMMYFUNCTION("""COMPUTED_VALUE"""),"07.04 [IMG] [AD04] Pedidos abertos") -> 07.04 [IMG] [AD04] Pedidos abertos | J29: =IFERROR(__xludf.DUMMYFUNCTION("""COMPUTED_VALUE"""),"07.04.2026 [V4] [WB] [LEADS-GRUPO-WHATS] 01") -> 07.04.2026 [V4] [WB] [LEADS-GRUPO-WHATS] 01 | K29: =LEFT(A29,10) -> 2026-04-12 | L29: =DATE(YEAR(SUBSTITUTE(SUBSTITUTE(K29,"-","/",1),"-","/",1)),MONTH(SUBSTITUTE(SUBSTITUTE(K29,"-","/",1),"-","/",1)),DAY(SUBSTITUTE(SUBSTITUTE(K29,"-","/",1),"-","/",1))) -> 46124 | M29: =RIGHT(C29,8) -> 88030611 | N29: =IFERROR(IF(VLOOKUP(M29,'Leads no grupo Saibai'!C:C,1,FALSE)=M29,"Sim"),"Não") -> Sim
A30: 2026-04-12T04:14:08.925Z | B30: Celso Fiszbeyn | C30: 11985843932 | D30: fiszbeyn@terra.com.br | E30: https://lp.saibai.com.br/?utm_source=MetaAds&utm_medium=ADV+-+%5BIG%5D+%5BFB%5D+%5B30%2B%5D+%5BPIEDADE+-+40KM%5D+V%C3%81RIOS&utm_campaign=07.04.2026+%5BV4%5D+%5BWB%5D+%5BLEADS-GRUPO-WHATS%5D+01&utm_content=07.04+%5BIMG%5D+%5BAD01%5D+A+safra+come%C3%A7ou&utm_term=Facebook_Mobile_Feed&fbclid=IwZXh0bgNhZW0BMABhZGlkAas0a_chJvtzcnRjBmFwcF9pZAwzNTA2ODU1MzE3MjgAAR6EcW4KwQkvPDQw168P-NKhi-OG7DUh-hlnToKUGL7g57mEjwtnHqCR0cApzg_aem_m1GgtNyhBt04gOoDEn8ZDA&campaign_id=120247452154580155&ad_id=120247452154590155&utm_id=120247452154580155 | F30: =IFERROR(__xludf.DUMMYFUNCTION("""COMPUTED_VALUE"""),"MetaAds") -> MetaAds | G30: =IFERROR(__xludf.DUMMYFUNCTION("""COMPUTED_VALUE"""),"ADV - [IG] [FB] [30%2B] [PIEDADE - 40KM] V%C3%81RIOS") -> ADV - [IG] [FB] [30%2B] [PIEDADE - 40KM] V%C3%81RIOS | H30: =IFERROR(__xludf.DUMMYFUNCTION("""COMPUTED_VALUE"""),"Facebook_Mobile_Feed") -> Facebook_Mobile_Feed | I30: =IFERROR(__xludf.DUMMYFUNCTION("""COMPUTED_VALUE"""),"07.04 [IMG] [AD01] A safra come%C3%A7ou") -> 07.04 [IMG] [AD01] A safra come%C3%A7ou | J30: =IFERROR(__xludf.DUMMYFUNCTION("""COMPUTED_VALUE"""),"07.04.2026 [V4] [WB] [LEADS-GRUPO-WHATS] 01") -> 07.04.2026 [V4] [WB] [LEADS-GRUPO-WHATS] 01 | K30: =LEFT(A30,10) -> 2026-04-12 | L30: =DATE(YEAR(SUBSTITUTE(SUBSTITUTE(K30,"-","/",1),"-","/",1)),MONTH(SUBSTITUTE(SUBSTITUTE(K30,"-","/",1),"-","/",1)),DAY(SUBSTITUTE(SUBSTITUTE(K30,"-","/",1),"-","/",1))) -> 46124 | M30: =RIGHT(C30,8) -> 85843932 | N30: =IFERROR(IF(VLOOKUP(M30,'Leads no grupo Saibai'!C:C,1,FALSE)=M30,"Sim"),"Não") -> Sim
A31: 2026-04-12T04:14:23.331Z | B31: Celso Fiszbeyn | C31: 11985843932 | D31: fiszbeyn@terra.com.br | E31: https://lp.saibai.com.br/?utm_source=MetaAds&utm_medium=ADV+-+%5BIG%5D+%5BFB%5D+%5B30%2B%5D+%5BPIEDADE+-+40KM%5D+V%C3%81RIOS&utm_campaign=07.04.2026+%5BV4%5D+%5BWB%5D+%5BLEADS-GRUPO-WHATS%5D+01&utm_content=07.04+%5BIMG%5D+%5BAD01%5D+A+safra+come%C3%A7ou&utm_term=Facebook_Mobile_Feed&fbclid=IwZXh0bgNhZW0BMABhZGlkAas0a_chJvtzcnRjBmFwcF9pZAwzNTA2ODU1MzE3MjgAAR6EcW4KwQkvPDQw168P-NKhi-OG7DUh-hlnToKUGL7g57mEjwtnHqCR0cApzg_aem_m1GgtNyhBt04gOoDEn8ZDA&campaign_id=120247452154580155&ad_id=120247452154590155&utm_id=120247452154580155 | F31: =IFERROR(__xludf.DUMMYFUNCTION("""COMPUTED_VALUE"""),"MetaAds") -> MetaAds | G31: =IFERROR(__xludf.DUMMYFUNCTION("""COMPUTED_VALUE"""),"ADV - [IG] [FB] [30%2B] [PIEDADE - 40KM] V%C3%81RIOS") -> ADV - [IG] [FB] [30%2B] [PIEDADE - 40KM] V%C3%81RIOS | H31: =IFERROR(__xludf.DUMMYFUNCTION("""COMPUTED_VALUE"""),"Facebook_Mobile_Feed") -> Facebook_Mobile_Feed | I31: =IFERROR(__xludf.DUMMYFUNCTION("""COMPUTED_VALUE"""),"07.04 [IMG] [AD01] A safra come%C3%A7ou") -> 07.04 [IMG] [AD01] A safra come%C3%A7ou | J31: =IFERROR(__xludf.DUMMYFUNCTION("""COMPUTED_VALUE"""),"07.04.2026 [V4] [WB] [LEADS-GRUPO-WHATS] 01") -> 07.04.2026 [V4] [WB] [LEADS-GRUPO-WHATS] 01 | K31: =LEFT(A31,10) -> 2026-04-12 | L31: =DATE(YEAR(SUBSTITUTE(SUBSTITUTE(K31,"-","/",1),"-","/",1)),MONTH(SUBSTITUTE(SUBSTITUTE(K31,"-","/",1),"-","/",1)),DAY(SUBSTITUTE(SUBSTITUTE(K31,"-","/",1),"-","/",1))) -> 46124 | M31: =RIGHT(C31,8) -> 85843932 | N31: =IFERROR(IF(VLOOKUP(M31,'Leads no grupo Saibai'!C:C,1,FALSE)=M31,"Sim"),"Não") -> Sim
A32: 2026-04-12T12:10:42.857Z | B32: Celso Fiszbeyn | C32: 11985843932 | D32: fiszbeyn@terra.com.br | E32: https://lp.saibai.com.br/?utm_source=MetaAds&utm_medium=ADV+-+%5BIG%5D+%5BFB%5D+%5B30%2B%5D+%5BPIEDADE+-+40KM%5D+V%C3%81RIOS&utm_campaign=07.04.2026+%5BV4%5D+%5BWB%5D+%5BLEADS-GRUPO-WHATS%5D+01&utm_content=07.04+%5BIMG%5D+%5BAD04%5D+Pedidos+abertos&utm_term=Facebook_Mobile_Feed&fbclid=IwZXh0bgNhZW0BMABhZGlkAas0bAW7ZytzcnRjBmFwcF9pZAwzNTA2ODU1MzE3MjgAAR6WOLrOPXnfYiyksmTBGYNaDAKqJ5-QSTjW0-BaeKjAR4hQeICzVlJ7CYBtgA_aem_rVGvF9I4taAyMROApCsCow&campaign_id=120247452154580155&ad_id=120247452938090155&utm_id=120247452154580155 | F32: =IFERROR(__xludf.DUMMYFUNCTION("""COMPUTED_VALUE"""),"MetaAds") -> MetaAds | G32: =IFERROR(__xludf.DUMMYFUNCTION("""COMPUTED_VALUE"""),"ADV - [IG] [FB] [30%2B] [PIEDADE - 40KM] V%C3%81RIOS") -> ADV - [IG] [FB] [30%2B] [PIEDADE - 40KM] V%C3%81RIOS | H32: =IFERROR(__xludf.DUMMYFUNCTION("""COMPUTED_VALUE"""),"Facebook_Mobile_Feed") -> Facebook_Mobile_Feed | I32: =IFERROR(__xludf.DUMMYFUNCTION("""COMPUTED_VALUE"""),"07.04 [IMG] [AD04] Pedidos abertos") -> 07.04 [IMG] [AD04] Pedidos abertos | J32: =IFERROR(__xludf.DUMMYFUNCTION("""COMPUTED_VALUE"""),"07.04.2026 [V4] [WB] [LEADS-GRUPO-WHATS] 01") -> 07.04.2026 [V4] [WB] [LEADS-GRUPO-WHATS] 01 | K32: =LEFT(A32,10) -> 2026-04-12 | L32: =DATE(YEAR(SUBSTITUTE(SUBSTITUTE(K32,"-","/",1),"-","/",1)),MONTH(SUBSTITUTE(SUBSTITUTE(K32,"-","/",1),"-","/",1)),DAY(SUBSTITUTE(SUBSTITUTE(K32,"-","/",1),"-","/",1))) -> 46124 | M32: =RIGHT(C32,8) -> 85843932 | N32: =IFERROR(IF(VLOOKUP(M32,'Leads no grupo Saibai'!C:C,1,FALSE)=M32,"Sim"),"Não") -> Sim
A33: 2026-04-12T12:20:14.074Z | B33: Renata Funchal | C33: 15981595553 | D33: renatapires.adv@gmail.com | E33: https://lp.saibai.com.br/?utm_source=MetaAds&utm_medium=ADV+-+%5BIG%5D+%5BFB%5D+%5B30%2B%5D+%5BPIEDADE+-+40KM%5D+V%C3%81RIOS&utm_campaign=07.04.2026+%5BV4%5D+%5BWB%5D+%5BLEADS-GRUPO-WHATS%5D+01&utm_content=07.04+%5BIMG%5D+%5BAD04%5D+Pedidos+abertos&utm_term=Instagram_Stories&utm_id=120247452154580155&fbclid=PAZXh0bgNhZW0BMABhZGlkAas0bAW7ZytzcnRjBmFwcF9pZA8xMjQwMjQ1NzQyODc0MTQAAado_HsUkVrToCTLgI5OWkFw_iE_k_-sbGAhzbRxE4kfpyZMIDNUC2LWe2vJsw_aem_wzs0o74Ym8t2vWSwLvHUng&campaign_id=120247452154580155&ad_id=120247452938090155 | F33: =IFERROR(__xludf.DUMMYFUNCTION("""COMPUTED_VALUE"""),"MetaAds") -> MetaAds | G33: =IFERROR(__xludf.DUMMYFUNCTION("""COMPUTED_VALUE"""),"ADV - [IG] [FB] [30%2B] [PIEDADE - 40KM] V%C3%81RIOS") -> ADV - [IG] [FB] [30%2B] [PIEDADE - 40KM] V%C3%81RIOS | H33: =IFERROR(__xludf.DUMMYFUNCTION("""COMPUTED_VALUE"""),"Instagram_Stories") -> Instagram_Stories | I33: =IFERROR(__xludf.DUMMYFUNCTION("""COMPUTED_VALUE"""),"07.04 [IMG] [AD04] Pedidos abertos") -> 07.04 [IMG] [AD04] Pedidos abertos | J33: =IFERROR(__xludf.DUMMYFUNCTION("""COMPUTED_VALUE"""),"07.04.2026 [V4] [WB] [LEADS-GRUPO-WHATS] 01") -> 07.04.2026 [V4] [WB] [LEADS-GRUPO-WHATS] 01 | K33: =LEFT(A33,10) -> 2026-04-12 | L33: =DATE(YEAR(SUBSTITUTE(SUBSTITUTE(K33,"-","/",1),"-","/",1)),MONTH(SUBSTITUTE(SUBSTITUTE(K33,"-","/",1),"-","/",1)),DAY(SUBSTITUTE(SUBSTITUTE(K33,"-","/",1),"-","/",1))) -> 46124 | M33: =RIGHT(C33,8) -> 81595553 | N33: =IFERROR(IF(VLOOKUP(M33,'Leads no grupo Saibai'!C:C,1,FALSE)=M33,"Sim"),"Não") -> Sim
A34: 2026-04-12T13:50:51.153Z | B34: Ana Luiza | C34: 15997442004 | D34: analuizacardamoni@hotmail.com | E34: https://lp.saibai.com.br/?utm_source=MetaAds&utm_medium=ADV+-+%5BIG%5D+%5BFB%5D+%5B30%2B%5D+%5BPIEDADE+-+40KM%5D+V%C3%81RIOS&utm_campaign=07.04.2026+%5BV4%5D+%5BWB%5D+%5BLEADS-GRUPO-WHATS%5D+01&utm_content=07.04+%5BIMG%5D+%5BAD04%5D+Pedidos+abertos&utm_term=Instagram_Feed&utm_id=120247452154580155&fbclid=PAZXh0bgNhZW0BMABhZGlkAas0bAfOj7tzcnRjBmFwcF9pZA81NjcwNjczNDMzNTI0MjcAAafeSKCjtmXj7sCjkaiE7HDHw04V12xI5oBJYYIrwQhIcvbNa7gkXkbWq4UANQ_aem_gpWdIfrNCAUgoQPoK2grVQ&campaign_id=120247452154580155&ad_id=120247452938090155 | F34: =IFERROR(__xludf.DUMMYFUNCTION("""COMPUTED_VALUE"""),"MetaAds") -> MetaAds | G34: =IFERROR(__xludf.DUMMYFUNCTION("""COMPUTED_VALUE"""),"ADV - [IG] [FB] [30%2B] [PIEDADE - 40KM] V%C3%81RIOS") -> ADV - [IG] [FB] [30%2B] [PIEDADE - 40KM] V%C3%81RIOS | H34: =IFERROR(__xludf.DUMMYFUNCTION("""COMPUTED_VALUE"""),"Instagram_Feed") -> Instagram_Feed | I34: =IFERROR(__xludf.DUMMYFUNCTION("""COMPUTED_VALUE"""),"07.04 [IMG] [AD04] Pedidos abertos") -> 07.04 [IMG] [AD04] Pedidos abertos | J34: =IFERROR(__xludf.DUMMYFUNCTION("""COMPUTED_VALUE"""),"07.04.2026 [V4] [WB] [LEADS-GRUPO-WHATS] 01") -> 07.04.2026 [V4] [WB] [LEADS-GRUPO-WHATS] 01 | K34: =LEFT(A34,10) -> 2026-04-12 | L34: =DATE(YEAR(SUBSTITUTE(SUBSTITUTE(K34,"-","/",1),"-","/",1)),MONTH(SUBSTITUTE(SUBSTITUTE(K34,"-","/",1),"-","/",1)),DAY(SUBSTITUTE(SUBSTITUTE(K34,"-","/",1),"-","/",1))) -> 46124 | M34: =RIGHT(C34,8) -> 97442004 | N34: =IFERROR(IF(VLOOKUP(M34,'Leads no grupo Saibai'!C:C,1,FALSE)=M34,"Sim"),"Não") -> Sim
A35: 2026-04-12T14:17:44.325Z | B35: Marizilda | C35: 15991956401 | D35: marireis127@gmail.com | E35: https://lp.saibai.com.br/?utm_source=MetaAds&utm_medium=ADV+-+%5BIG%5D+%5BFB%5D+%5B30%2B%5D+%5BPIEDADE+-+40KM%5D+V%C3%81RIOS&utm_campaign=07.04.2026+%5BV4%5D+%5BWB%5D+%5BLEADS-GRUPO-WHATS%5D+01&utm_content=07.04+%5BIMG%5D+%5BAD04%5D+Pedidos+abertos&utm_term=Facebook_Mobile_Feed&fbclid=IwZXh0bgNhZW0BMABhZGlkAas0bAW7ZytzcnRjBmFwcF9pZAo2NjI4NTY4Mzc5AAEe9jK7CE_zajp1t-JFujpoG6LgAc8gfbKqAswpiGyT9KCIJ6gWLpNfPKkUvG8_aem_YT2FfFdmNthace4_CZf8Jw&campaign_id=120247452154580155&ad_id=120247452938090155&utm_id=120247452154580155 | F35: =IFERROR(__xludf.DUMMYFUNCTION("""COMPUTED_VALUE"""),"MetaAds") -> MetaAds | G35: =IFERROR(__xludf.DUMMYFUNCTION("""COMPUTED_VALUE"""),"ADV - [IG] [FB] [30%2B] [PIEDADE - 40KM] V%C3%81RIOS") -> ADV - [IG] [FB] [30%2B] [PIEDADE - 40KM] V%C3%81RIOS | H35: =IFERROR(__xludf.DUMMYFUNCTION("""COMPUTED_VALUE"""),"Facebook_Mobile_Feed") -> Facebook_Mobile_Feed | I35: =IFERROR(__xludf.DUMMYFUNCTION("""COMPUTED_VALUE"""),"07.04 [IMG] [AD04] Pedidos abertos") -> 07.04 [IMG] [AD04] Pedidos abertos | J35: =IFERROR(__xludf.DUMMYFUNCTION("""COMPUTED_VALUE"""),"07.04.2026 [V4] [WB] [LEADS-GRUPO-WHATS] 01") -> 07.04.2026 [V4] [WB] [LEADS-GRUPO-WHATS] 01 | K35: =LEFT(A35,10) -> 2026-04-12 | L35: =DATE(YEAR(SUBSTITUTE(SUBSTITUTE(K35,"-","/",1),"-","/",1)),MONTH(SUBSTITUTE(SUBSTITUTE(K35,"-","/",1),"-","/",1)),DAY(SUBSTITUTE(SUBSTITUTE(K35,"-","/",1),"-","/",1))) -> 46124 | M35: =RIGHT(C35,8) -> 91956401 | N35: =IFERROR(IF(VLOOKUP(M35,'Leads no grupo Saibai'!C:C,1,FALSE)=M35,"Sim"),"Não") -> Sim
A36: 2026-04-12T14:26:32.692Z | B36: REGINA FARABOLINI | C36: 55119923986 | D36: reginafarabolinipala@gmail.com | E36: https://lp.saibai.com.br/?utm_source=MetaAds&utm_medium=ADV+-+%5BIG%5D+%5BFB%5D+%5B30%2B%5D+%5BPIEDADE+-+40KM%5D+V%C3%81RIOS&utm_campaign=07.04.2026+%5BV4%5D+%5BWB%5D+%5BLEADS-GRUPO-WHATS%5D+02&utm_content=07.04+%5BIMG%5D+%5BAD04%5D+Pedidos+abertos&utm_term=Instagram_Stories&utm_id=120248254459350155&fbclid=PAZXh0bgNhZW0BMABhZGlkAas1g0M2JftzcnRjBmFwcF9pZA81NjcwNjczNDMzNTI0MjcAAae-Pi9C5ulqTw1avKSlCfTlAiaFlEjDorhtO4cBmGvSCiUKaU-KCcm7ipMffA_aem_qVPH0fA8b5aEFs-o7UHCZA&campaign_id=120248254459350155&ad_id=120248254459370155 | F36: =IFERROR(__xludf.DUMMYFUNCTION("""COMPUTED_VALUE"""),"MetaAds") -> MetaAds | G36: =IFERROR(__xludf.DUMMYFUNCTION("""COMPUTED_VALUE"""),"ADV - [IG] [FB] [30%2B] [PIEDADE - 40KM] V%C3%81RIOS") -> ADV - [IG] [FB] [30%2B] [PIEDADE - 40KM] V%C3%81RIOS | H36: =IFERROR(__xludf.DUMMYFUNCTION("""COMPUTED_VALUE"""),"Instagram_Stories") -> Instagram_Stories | I36: =IFERROR(__xludf.DUMMYFUNCTION("""COMPUTED_VALUE"""),"07.04 [IMG] [AD04] Pedidos abertos") -> 07.04 [IMG] [AD04] Pedidos abertos | J36: =IFERROR(__xludf.DUMMYFUNCTION("""COMPUTED_VALUE"""),"07.04.2026 [V4] [WB] [LEADS-GRUPO-WHATS] 02") -> 07.04.2026 [V4] [WB] [LEADS-GRUPO-WHATS] 02 | K36: =LEFT(A36,10) -> 2026-04-12 | L36: =DATE(YEAR(SUBSTITUTE(SUBSTITUTE(K36,"-","/",1),"-","/",1)),MONTH(SUBSTITUTE(SUBSTITUTE(K36,"-","/",1),"-","/",1)),DAY(SUBSTITUTE(SUBSTITUTE(K36,"-","/",1),"-","/",1))) -> 46124 | M36: =RIGHT(C36,8) -> 19923986 | N36: =IFERROR(IF(VLOOKUP(M36,'Leads no grupo Saibai'!C:C,1,FALSE)=M36,"Sim"),"Não") -> Não
A37: 2026-04-12T15:36:56.057Z | B37: Raquel Godinho | C37: 11992292684 | D37: quelgodinho@gmail.com | E37: https://lp.saibai.com.br/?utm_source=MetaAds&utm_medium=ADV+-+%5BIG%5D+%5BFB%5D+%5B30%2B%5D+%5BPIEDADE+-+40KM%5D+V%C3%81RIOS&utm_campaign=07.04.2026+%5BV4%5D+%5BWB%5D+%5BLEADS-GRUPO-WHATS%5D+01&utm_content=07.04+%5BIMG%5D+%5BAD04%5D+Pedidos+abertos&utm_term=Instagram_Stories&utm_id=120247452154580155&fbclid=PAZXh0bgNhZW0BMABhZGlkAas0bAW7ZytzcnRjBmFwcF9pZA81NjcwNjczNDMzNTI0MjcAAadp7gnYVGORL_tuQ_8n1nAAApwHuI-rh3sbQYYie1ktHqEyFxr5027YxMllXw_aem_QqPH-6EFmulWlz_hogOPSg&campaign_id=120247452154580155&ad_id=120247452938090155 | F37: =IFERROR(__xludf.DUMMYFUNCTION("""COMPUTED_VALUE"""),"MetaAds") -> MetaAds | G37: =IFERROR(__xludf.DUMMYFUNCTION("""COMPUTED_VALUE"""),"ADV - [IG] [FB] [30%2B] [PIEDADE - 40KM] V%C3%81RIOS") -> ADV - [IG] [FB] [30%2B] [PIEDADE - 40KM] V%C3%81RIOS | H37: =IFERROR(__xludf.DUMMYFUNCTION("""COMPUTED_VALUE"""),"Instagram_Stories") -> Instagram_Stories | I37: =IFERROR(__xludf.DUMMYFUNCTION("""COMPUTED_VALUE"""),"07.04 [IMG] [AD04] Pedidos abertos") -> 07.04 [IMG] [AD04] Pedidos abertos | J37: =IFERROR(__xludf.DUMMYFUNCTION("""COMPUTED_VALUE"""),"07.04.2026 [V4] [WB] [LEADS-GRUPO-WHATS] 01") -> 07.04.2026 [V4] [WB] [LEADS-GRUPO-WHATS] 01 | K37: =LEFT(A37,10) -> 2026-04-12 | L37: =DATE(YEAR(SUBSTITUTE(SUBSTITUTE(K37,"-","/",1),"-","/",1)),MONTH(SUBSTITUTE(SUBSTITUTE(K37,"-","/",1),"-","/",1)),DAY(SUBSTITUTE(SUBSTITUTE(K37,"-","/",1),"-","/",1))) -> 46124 | M37: =RIGHT(C37,8) -> 92292684 | N37: =IFERROR(IF(VLOOKUP(M37,'Leads no grupo Saibai'!C:C,1,FALSE)=M37,"Sim"),"Não") -> Sim
A38: 2026-04-12T16:22:38.288Z | B38: Gilberto Lima | C38: 15997789191 | D38: gibajlima1000@gmail.com | E38: https://lp.saibai.com.br/?utm_source=MetaAds&utm_medium=ADV+-+%5BIG%5D+%5BFB%5D+%5B30%2B%5D+%5BPIEDADE+-+40KM%5D+V%C3%81RIOS&utm_campaign=07.04.2026+%5BV4%5D+%5BWB%5D+%5BLEADS-GRUPO-WHATS%5D+01&utm_content=07.04+%5BIMG%5D+%5BAD04%5D+Pedidos+abertos&utm_term=Facebook_Mobile_Reels&fbclid=IwZXh0bgNhZW0BMABhZGlkAas0bAW7ZytzcnRjBmFwcF9pZAwzNTA2ODU1MzE3MjgAAR4YddERmVsRRNORRCPz8ke7GStFy4DVeNPUXpM9Ajm-0-phaNjOk5yy4m0Fcg_aem_-u2RCuZge2fUZBa611trSA&campaign_id=120247452154580155&ad_id=120247452938090155&utm_id=120247452154580155 | F38: =IFERROR(__xludf.DUMMYFUNCTION("""COMPUTED_VALUE"""),"MetaAds") -> MetaAds | G38: =IFERROR(__xludf.DUMMYFUNCTION("""COMPUTED_VALUE"""),"ADV - [IG] [FB] [30%2B] [PIEDADE - 40KM] V%C3%81RIOS") -> ADV - [IG] [FB] [30%2B] [PIEDADE - 40KM] V%C3%81RIOS | H38: =IFERROR(__xludf.DUMMYFUNCTION("""COMPUTED_VALUE"""),"Facebook_Mobile_Reels") -> Facebook_Mobile_Reels | I38: =IFERROR(__xludf.DUMMYFUNCTION("""COMPUTED_VALUE"""),"07.04 [IMG] [AD04] Pedidos abertos") -> 07.04 [IMG] [AD04] Pedidos abertos | J38: =IFERROR(__xludf.DUMMYFUNCTION("""COMPUTED_VALUE"""),"07.04.2026 [V4] [WB] [LEADS-GRUPO-WHATS] 01") -> 07.04.2026 [V4] [WB] [LEADS-GRUPO-WHATS] 01 | K38: =LEFT(A38,10) -> 2026-04-12 | L38: =DATE(YEAR(SUBSTITUTE(SUBSTITUTE(K38,"-","/",1),"-","/",1)),MONTH(SUBSTITUTE(SUBSTITUTE(K38,"-","/",1),"-","/",1)),DAY(SUBSTITUTE(SUBSTITUTE(K38,"-","/",1),"-","/",1))) -> 46124 | M38: =RIGHT(C38,8) -> 97789191 | N38: =IFERROR(IF(VLOOKUP(M38,'Leads no grupo Saibai'!C:C,1,FALSE)=M38,"Sim"),"Não") -> Sim
A39: 2026-04-12T16:28:07.518Z | B39: Maria Dalva | C39: 55159911523 | D39: mariadalvasilvanod@gmail.com | E39: https://lp.saibai.com.br/?utm_source=MetaAds&utm_medium=ADV+-+%5BIG%5D+%5BFB%5D+%5B30%2B%5D+%5BPIEDADE+-+40KM%5D+V%C3%81RIOS&utm_campaign=07.04.2026+%5BV4%5D+%5BWB%5D+%5BLEADS-GRUPO-WHATS%5D+01&utm_content=07.04+%5BIMG%5D+%5BAD04%5D+Pedidos+abertos&utm_term=Facebook_Mobile_Feed&fbclid=IwZXh0bgNhZW0BMABhZGlkAas0bAW7ZytzcnRjBmFwcF9pZAwzNTA2ODU1MzE3MjgAAR7-OlI7WMw6oSGOmbzHIVFy6KZc3cpPC3b37cwOx63Ocg6NIYhTQzdWVAE42A_aem_R66TJY_Gu-VxZGmf_phaNg&campaign_id=120247452154580155&ad_id=120247452938090155&utm_id=120247452154580155 | F39: =IFERROR(__xludf.DUMMYFUNCTION("""COMPUTED_VALUE"""),"MetaAds") -> MetaAds | G39: =IFERROR(__xludf.DUMMYFUNCTION("""COMPUTED_VALUE"""),"ADV - [IG] [FB] [30%2B] [PIEDADE - 40KM] V%C3%81RIOS") -> ADV - [IG] [FB] [30%2B] [PIEDADE - 40KM] V%C3%81RIOS | H39: =IFERROR(__xludf.DUMMYFUNCTION("""COMPUTED_VALUE"""),"Facebook_Mobile_Feed") -> Facebook_Mobile_Feed | I39: =IFERROR(__xludf.DUMMYFUNCTION("""COMPUTED_VALUE"""),"07.04 [IMG] [AD04] Pedidos abertos") -> 07.04 [IMG] [AD04] Pedidos abertos | J39: =IFERROR(__xludf.DUMMYFUNCTION("""COMPUTED_VALUE"""),"07.04.2026 [V4] [WB] [LEADS-GRUPO-WHATS] 01") -> 07.04.2026 [V4] [WB] [LEADS-GRUPO-WHATS] 01 | K39: =LEFT(A39,10) -> 2026-04-12 | L39: =DATE(YEAR(SUBSTITUTE(SUBSTITUTE(K39,"-","/",1),"-","/",1)),MONTH(SUBSTITUTE(SUBSTITUTE(K39,"-","/",1),"-","/",1)),DAY(SUBSTITUTE(SUBSTITUTE(K39,"-","/",1),"-","/",1))) -> 46124 | M39: =RIGHT(C39,8) -> 59911523 | N39: =IFERROR(IF(VLOOKUP(M39,'Leads no grupo Saibai'!C:C,1,FALSE)=M39,"Sim"),"Não") -> Não
A40: 2026-04-12T18:03:02.863Z | B40: Nilo | C40: 11999885590 | D40: nilojaime.nilo@hotmail.com | E40: https://lp.saibai.com.br/?utm_source=MetaAds&utm_medium=ADV+-+%5BIG%5D+%5BFB%5D+%5B30%2B%5D+%5BPIEDADE+-+40KM%5D+V%C3%81RIOS&utm_campaign=07.04.2026+%5BV4%5D+%5BWB%5D+%5BLEADS-GRUPO-WHATS%5D+02&utm_content=07.04+%5BIMG%5D+%5BAD04%5D+Pedidos+abertos&utm_term=Instagram_Stories&utm_id=120248254459350155&fbclid=PAZXh0bgNhZW0BMABhZGlkAas1g0M2JftzcnRjBmFwcF9pZA81NjcwNjczNDMzNTI0MjcAAae-Pi9C5ulqTw1avKSlCfTlAiaFlEjDorhtO4cBmGvSCiUKaU-KCcm7ipMffA_aem_qVPH0fA8b5aEFs-o7UHCZA&campaign_id=120248254459350155&ad_id=120248254459370155 | F40: =IFERROR(__xludf.DUMMYFUNCTION("""COMPUTED_VALUE"""),"MetaAds") -> MetaAds | G40: =IFERROR(__xludf.DUMMYFUNCTION("""COMPUTED_VALUE"""),"ADV - [IG] [FB] [30%2B] [PIEDADE - 40KM] V%C3%81RIOS") -> ADV - [IG] [FB] [30%2B] [PIEDADE - 40KM] V%C3%81RIOS | H40: =IFERROR(__xludf.DUMMYFUNCTION("""COMPUTED_VALUE"""),"Instagram_Stories") -> Instagram_Stories | I40: =IFERROR(__xludf.DUMMYFUNCTION("""COMPUTED_VALUE"""),"07.04 [IMG] [AD04] Pedidos abertos") -> 07.04 [IMG] [AD04] Pedidos abertos | J40: =IFERROR(__xludf.DUMMYFUNCTION("""COMPUTED_VALUE"""),"07.04.2026 [V4] [WB] [LEADS-GRUPO-WHATS] 02") -> 07.04.2026 [V4] [WB] [LEADS-GRUPO-WHATS] 02 | K40: =LEFT(A40,10) -> 2026-04-12 | L40: =DATE(YEAR(SUBSTITUTE(SUBSTITUTE(K40,"-","/",1),"-","/",1)),MONTH(SUBSTITUTE(SUBSTITUTE(K40,"-","/",1),"-","/",1)),DAY(SUBSTITUTE(SUBSTITUTE(K40,"-","/",1),"-","/",1))) -> 46124 | M40: =RIGHT(C40,8) -> 99885590 | N40: =IFERROR(IF(VLOOKUP(M40,'Leads no grupo Saibai'!C:C,1,FALSE)=M40,"Sim"),"Não") -> Sim
A41: 2026-04-12T18:46:05.297Z | B41: Antonio Neto | C41: 15988052505 | D41: antoniolyrioneto@gmail.com | E41: https://lp.saibai.com.br/?utm_source=MetaAds&utm_medium=ADV+-+%5BIG%5D+%5BFB%5D+%5B30%2B%5D+%5BPIEDADE+-+40KM%5D+V%C3%81RIOS&utm_campaign=07.04.2026+%5BV4%5D+%5BWB%5D+%5BLEADS-GRUPO-WHATS%5D+01&utm_content=07.04+%5BIMG%5D+%5BAD04%5D+Pedidos+abertos&utm_term=Facebook_Mobile_Feed&fbclid=IwZXh0bgNhZW0BMABhZGlkAas0bAW7ZytzcnRjBmFwcF9pZAwzNTA2ODU1MzE3MjgAAR7j7TXVSeRzQCmgL-HNIf6fprMYwOhdIiDeqYL9_F6EFmrN1TvrgMa1hb870A_aem_t9l55dUHn_-k6SgD8RIj-A&campaign_id=120247452154580155&ad_id=120247452938090155&utm_id=120247452154580155 | F41: =IFERROR(__xludf.DUMMYFUNCTION("""COMPUTED_VALUE"""),"MetaAds") -> MetaAds | G41: =IFERROR(__xludf.DUMMYFUNCTION("""COMPUTED_VALUE"""),"ADV - [IG] [FB] [30%2B] [PIEDADE - 40KM] V%C3%81RIOS") -> ADV - [IG] [FB] [30%2B] [PIEDADE - 40KM] V%C3%81RIOS | H41: =IFERROR(__xludf.DUMMYFUNCTION("""COMPUTED_VALUE"""),"Facebook_Mobile_Feed") -> Facebook_Mobile_Feed | I41: =IFERROR(__xludf.DUMMYFUNCTION("""COMPUTED_VALUE"""),"07.04 [IMG] [AD04] Pedidos abertos") -> 07.04 [IMG] [AD04] Pedidos abertos | J41: =IFERROR(__xludf.DUMMYFUNCTION("""COMPUTED_VALUE"""),"07.04.2026 [V4] [WB] [LEADS-GRUPO-WHATS] 01") -> 07.04.2026 [V4] [WB] [LEADS-GRUPO-WHATS] 01 | K41: =LEFT(A41,10) -> 2026-04-12 | L41: =DATE(YEAR(SUBSTITUTE(SUBSTITUTE(K41,"-","/",1),"-","/",1)),MONTH(SUBSTITUTE(SUBSTITUTE(K41,"-","/",1),"-","/",1)),DAY(SUBSTITUTE(SUBSTITUTE(K41,"-","/",1),"-","/",1))) -> 46124 | M41: =RIGHT(C41,8) -> 88052505 | N41: =IFERROR(IF(VLOOKUP(M41,'Leads no grupo Saibai'!C:C,1,FALSE)=M41,"Sim"),"Não") -> Sim
A42: 2026-04-12T20:42:52.606Z | B42: Leda Tagliaferro | C42: 15997662422 | D42: tagliaferro.leda30@gmail.com | E42: https://lp.saibai.com.br/?utm_source=MetaAds&utm_medium=ADV+-+%5BIG%5D+%5BFB%5D+%5B30%2B%5D+%5BPIEDADE+-+40KM%5D+V%C3%81RIOS&utm_campaign=07.04.2026+%5BV4%5D+%5BWB%5D+%5BLEADS-GRUPO-WHATS%5D+01&utm_content=07.04+%5BIMG%5D+%5BAD04%5D+Pedidos+abertos&utm_term=Facebook_Mobile_Feed&fbclid=IwZXh0bgNhZW0BMABhZGlkAas0bAfOj7tzcnRjBmFwcF9pZAwzNTA2ODU1MzE3MjgAAR7Rd5SefmRmIHeFcpvyELGs9awHvgYywscRUaxRp083cgILbQohDmZQcjjYTQ_aem_h16RRQfLBLUyXXXgeNpvqw&campaign_id=120247452154580155&ad_id=120247452938090155&utm_id=120247452154580155 | F42: =IFERROR(__xludf.DUMMYFUNCTION("""COMPUTED_VALUE"""),"MetaAds") -> MetaAds | G42: =IFERROR(__xludf.DUMMYFUNCTION("""COMPUTED_VALUE"""),"ADV - [IG] [FB] [30%2B] [PIEDADE - 40KM] V%C3%81RIOS") -> ADV - [IG] [FB] [30%2B] [PIEDADE - 40KM] V%C3%81RIOS | H42: =IFERROR(__xludf.DUMMYFUNCTION("""COMPUTED_VALUE"""),"Facebook_Mobile_Feed") -> Facebook_Mobile_Feed | I42: =IFERROR(__xludf.DUMMYFUNCTION("""COMPUTED_VALUE"""),"07.04 [IMG] [AD04] Pedidos abertos") -> 07.04 [IMG] [AD04] Pedidos abertos | J42: =IFERROR(__xludf.DUMMYFUNCTION("""COMPUTED_VALUE"""),"07.04.2026 [V4] [WB] [LEADS-GRUPO-WHATS] 01") -> 07.04.2026 [V4] [WB] [LEADS-GRUPO-WHATS] 01 | K42: =LEFT(A42,10) -> 2026-04-12 | L42: =DATE(YEAR(SUBSTITUTE(SUBSTITUTE(K42,"-","/",1),"-","/",1)),MONTH(SUBSTITUTE(SUBSTITUTE(K42,"-","/",1),"-","/",1)),DAY(SUBSTITUTE(SUBSTITUTE(K42,"-","/",1),"-","/",1))) -> 46124 | M42: =RIGHT(C42,8) -> 97662422 | N42: =IFERROR(IF(VLOOKUP(M42,'Leads no grupo Saibai'!C:C,1,FALSE)=M42,"Sim"),"Não") -> Não
A43: 2026-04-12T20:48:52.105Z | B43: Maria Scuracchio | C43: 16999934108 | D43: rescuracchio@uol.com.br | E43: https://lp.saibai.com.br/?utm_source=MetaAds&utm_medium=ADV+-+%5BIG%5D+%5BFB%5D+%5B30%2B%5D+%5BPIEDADE+-+40KM%5D+V%C3%81RIOS&utm_campaign=07.04.2026+%5BV4%5D+%5BWB%5D+%5BLEADS-GRUPO-WHATS%5D+01&utm_content=07.04+%5BIMG%5D+%5BAD04%5D+Pedidos+abertos&utm_term=Facebook_Mobile_Reels&fbclid=IwZXh0bgNhZW0BMABhZGlkAas0bAW7ZytzcnRjBmFwcF9pZAo2NjI4NTY4Mzc5AAEeM91l-LHCK4n_BRmHiRvxVrXdpLVudRySp3jSyCqmmlznRx7FYYeuV4ZY0zY_aem_jPr04v7taRk16y5Js5xiNg&campaign_id=120247452154580155&ad_id=120247452938090155&utm_id=120247452154580155 | F43: =IFERROR(__xludf.DUMMYFUNCTION("""COMPUTED_VALUE"""),"MetaAds") -> MetaAds | G43: =IFERROR(__xludf.DUMMYFUNCTION("""COMPUTED_VALUE"""),"ADV - [IG] [FB] [30%2B] [PIEDADE - 40KM] V%C3%81RIOS") -> ADV - [IG] [FB] [30%2B] [PIEDADE - 40KM] V%C3%81RIOS | H43: =IFERROR(__xludf.DUMMYFUNCTION("""COMPUTED_VALUE"""),"Facebook_Mobile_Reels") -> Facebook_Mobile_Reels | I43: =IFERROR(__xludf.DUMMYFUNCTION("""COMPUTED_VALUE"""),"07.04 [IMG] [AD04] Pedidos abertos") -> 07.04 [IMG] [AD04] Pedidos abertos | J43: =IFERROR(__xludf.DUMMYFUNCTION("""COMPUTED_VALUE"""),"07.04.2026 [V4] [WB] [LEADS-GRUPO-WHATS] 01") -> 07.04.2026 [V4] [WB] [LEADS-GRUPO-WHATS] 01 | K43: =LEFT(A43,10) -> 2026-04-12 | L43: =DATE(YEAR(SUBSTITUTE(SUBSTITUTE(K43,"-","/",1),"-","/",1)),MONTH(SUBSTITUTE(SUBSTITUTE(K43,"-","/",1),"-","/",1)),DAY(SUBSTITUTE(SUBSTITUTE(K43,"-","/",1),"-","/",1))) -> 46124 | M43: =RIGHT(C43,8) -> 99934108 | N43: =IFERROR(IF(VLOOKUP(M43,'Leads no grupo Saibai'!C:C,1,FALSE)=M43,"Sim"),"Não") -> Sim
A44: 2026-04-12T21:02:58.488Z | B44: Juliana | C44: 95991136088 | D44: mc4475634@gmail.com | E44: https://lp.saibai.com.br/?utm_source=MetaAds&utm_medium=ADV+-+%5BIG%5D+%5BFB%5D+%5B30%2B%5D+%5BPIEDADE+-+40KM%5D+V%C3%81RIOS&utm_campaign=07.04.2026+%5BV4%5D+%5BWB%5D+%5BLEADS-GRUPO-WHATS%5D+01&utm_content=07.04+%5BIMG%5D+%5BAD04%5D+Pedidos+abertos&utm_term=Facebook_Mobile_Feed&fbclid=IwZXh0bgNhZW0BMABhZGlkAas0bAW7ZytzcnRjBmFwcF9pZAwzNTA2ODU1MzE3MjgAAR4Kup1aatJk-57G4z8VZVUsJFnFk477rHEL0PZrehaXIb5OUSWHwKFbPFBdbw_aem_FucqPlHHul2yYz80ajOmPQ&campaign_id=120247452154580155&ad_id=120247452938090155&utm_id=120247452154580155 | F44: =IFERROR(__xludf.DUMMYFUNCTION("""COMPUTED_VALUE"""),"MetaAds") -> MetaAds | G44: =IFERROR(__xludf.DUMMYFUNCTION("""COMPUTED_VALUE"""),"ADV - [IG] [FB] [30%2B] [PIEDADE - 40KM] V%C3%81RIOS") -> ADV - [IG] [FB] [30%2B] [PIEDADE - 40KM] V%C3%81RIOS | H44: =IFERROR(__xludf.DUMMYFUNCTION("""COMPUTED_VALUE"""),"Facebook_Mobile_Feed") -> Facebook_Mobile_Feed | I44: =IFERROR(__xludf.DUMMYFUNCTION("""COMPUTED_VALUE"""),"07.04 [IMG] [AD04] Pedidos abertos") -> 07.04 [IMG] [AD04] Pedidos abertos | J44: =IFERROR(__xludf.DUMMYFUNCTION("""COMPUTED_VALUE"""),"07.04.2026 [V4] [WB] [LEADS-GRUPO-WHATS] 01") -> 07.04.2026 [V4] [WB] [LEADS-GRUPO-WHATS] 01 | K44: =LEFT(A44,10) -> 2026-04-12 | L44: =DATE(YEAR(SUBSTITUTE(SUBSTITUTE(K44,"-","/",1),"-","/",1)),MONTH(SUBSTITUTE(SUBSTITUTE(K44,"-","/",1),"-","/",1)),DAY(SUBSTITUTE(SUBSTITUTE(K44,"-","/",1),"-","/",1))) -> 46124 | M44: =RIGHT(C44,8) -> 91136088 | N44: =IFERROR(IF(VLOOKUP(M44,'Leads no grupo Saibai'!C:C,1,FALSE)=M44,"Sim"),"Não") -> Sim
A45: 2026-04-12T21:06:58.906Z | B45: Pedro Gali | C45: 15981147296 | D45: pedrogali01@hotmail.com | E45: https://lp.saibai.com.br/?utm_source=MetaAds&utm_medium=ADV+-+%5BIG%5D+%5BFB%5D+%5B30%2B%5D+%5BPIEDADE+-+40KM%5D+V%C3%81RIOS&utm_campaign=07.04.2026+%5BV4%5D+%5BWB%5D+%5BLEADS-GRUPO-WHATS%5D+01&utm_content=07.04+%5BIMG%5D+%5BAD04%5D+Pedidos+abertos&utm_term=Instagram_Feed&utm_id=120247452154580155&fbclid=PAZXh0bgNhZW0BMABhZGlkAas0bAW7ZytzcnRjBmFwcF9pZA81NjcwNjczNDMzNTI0MjcAAad1DnLBUxIVRi-y6CPJIxZfAmFPEM3Jv8ghuCy75_ocUY11fYUOePDwf0JMNg_aem_MwjS4-BWpo3ZdyEz6QQE-Q&campaign_id=120247452154580155&ad_id=120247452938090155 | F45: =IFERROR(__xludf.DUMMYFUNCTION("""COMPUTED_VALUE"""),"MetaAds") -> MetaAds | G45: =IFERROR(__xludf.DUMMYFUNCTION("""COMPUTED_VALUE"""),"ADV - [IG] [FB] [30%2B] [PIEDADE - 40KM] V%C3%81RIOS") -> ADV - [IG] [FB] [30%2B] [PIEDADE - 40KM] V%C3%81RIOS | H45: =IFERROR(__xludf.DUMMYFUNCTION("""COMPUTED_VALUE"""),"Instagram_Feed") -> Instagram_Feed | I45: =IFERROR(__xludf.DUMMYFUNCTION("""COMPUTED_VALUE"""),"07.04 [IMG] [AD04] Pedidos abertos") -> 07.04 [IMG] [AD04] Pedidos abertos | J45: =IFERROR(__xludf.DUMMYFUNCTION("""COMPUTED_VALUE"""),"07.04.2026 [V4] [WB] [LEADS-GRUPO-WHATS] 01") -> 07.04.2026 [V4] [WB] [LEADS-GRUPO-WHATS] 01 | K45: =LEFT(A45,10) -> 2026-04-12 | L45: =DATE(YEAR(SUBSTITUTE(SUBSTITUTE(K45,"-","/",1),"-","/",1)),MONTH(SUBSTITUTE(SUBSTITUTE(K45,"-","/",1),"-","/",1)),DAY(SUBSTITUTE(SUBSTITUTE(K45,"-","/",1),"-","/",1))) -> 46124 | M45: =RIGHT(C45,8) -> 81147296 | N45: =IFERROR(IF(VLOOKUP(M45,'Leads no grupo Saibai'!C:C,1,FALSE)=M45,"Sim"),"Não") -> Sim
A46: 2026-04-12T21:30:11.978Z | B46: Luciana Camargo | C46: 15997476861 | D46: llandulpho@hotmail.com | E46: https://lp.saibai.com.br/?utm_source=MetaAds&utm_medium=ADV+-+%5BIG%5D+%5BFB%5D+%5B30%2B%5D+%5BPIEDADE+-+40KM%5D+V%C3%81RIOS&utm_campaign=07.04.2026+%5BV4%5D+%5BWB%5D+%5BLEADS-GRUPO-WHATS%5D+01&utm_content=07.04+%5BIMG%5D+%5BAD04%5D+Pedidos+abertos&utm_term=Instagram_Reels&utm_id=120247452154580155&fbclid=PAZXh0bgNhZW0BMABhZGlkAas0bAfOj7tzcnRjBmFwcF9pZA81NjcwNjczNDMzNTI0MjcAAafusM8OGl8tCc4cP44fL3_Hd5pOskbHl2MF8Z5WPH6726_HbmpqYJV5oZESTg_aem_LFt7CEVQR7gvpRpR5HnTvw&campaign_id=120247452154580155&ad_id=120247452938090155 | F46: =IFERROR(__xludf.DUMMYFUNCTION("""COMPUTED_VALUE"""),"MetaAds") -> MetaAds | G46: =IFERROR(__xludf.DUMMYFUNCTION("""COMPUTED_VALUE"""),"ADV - [IG] [FB] [30%2B] [PIEDADE - 40KM] V%C3%81RIOS") -> ADV - [IG] [FB] [30%2B] [PIEDADE - 40KM] V%C3%81RIOS | H46: =IFERROR(__xludf.DUMMYFUNCTION("""COMPUTED_VALUE"""),"Instagram_Reels") -> Instagram_Reels | I46: =IFERROR(__xludf.DUMMYFUNCTION("""COMPUTED_VALUE"""),"07.04 [IMG] [AD04] Pedidos abertos") -> 07.04 [IMG] [AD04] Pedidos abertos | J46: =IFERROR(__xludf.DUMMYFUNCTION("""COMPUTED_VALUE"""),"07.04.2026 [V4] [WB] [LEADS-GRUPO-WHATS] 01") -> 07.04.2026 [V4] [WB] [LEADS-GRUPO-WHATS] 01 | K46: =LEFT(A46,10) -> 2026-04-12 | L46: =DATE(YEAR(SUBSTITUTE(SUBSTITUTE(K46,"-","/",1),"-","/",1)),MONTH(SUBSTITUTE(SUBSTITUTE(K46,"-","/",1),"-","/",1)),DAY(SUBSTITUTE(SUBSTITUTE(K46,"-","/",1),"-","/",1))) -> 46124 | M46: =RIGHT(C46,8) -> 97476861 | N46: =IFERROR(IF(VLOOKUP(M46,'Leads no grupo Saibai'!C:C,1,FALSE)=M46,"Sim"),"Não") -> Sim
A47: 2026-04-12T21:44:51.181Z | B47: Camila | C47: 15996897606 | D47: loja.adoleta@yahoo.com.br | E47: https://lp.saibai.com.br/?utm_source=MetaAds&utm_medium=ADV+-+%5BIG%5D+%5BFB%5D+%5B30%2B%5D+%5BPIEDADE+-+40KM%5D+V%C3%81RIOS&utm_campaign=07.04.2026+%5BV4%5D+%5BWB%5D+%5BLEADS-GRUPO-WHATS%5D+01&utm_content=07.04+%5BIMG%5D+%5BAD04%5D+Pedidos+abertos&utm_term=Facebook_Mobile_Feed&fbclid=IwZXh0bgNhZW0BMABhZGlkAas0bAW7ZytzcnRjBmFwcF9pZAo2NjI4NTY4Mzc5AAEeVWSADMFPlOn6c4Fym4xaOWUx4dBNWPH5Jbn36z0l0eTTTYeaTyga-Tn9Hx8_aem_25sKqRp8muui3joscMmISg&campaign_id=120247452154580155&ad_id=120247452938090155&utm_id=120247452154580155 | F47: =IFERROR(__xludf.DUMMYFUNCTION("""COMPUTED_VALUE"""),"MetaAds") -> MetaAds | G47: =IFERROR(__xludf.DUMMYFUNCTION("""COMPUTED_VALUE"""),"ADV - [IG] [FB] [30%2B] [PIEDADE - 40KM] V%C3%81RIOS") -> ADV - [IG] [FB] [30%2B] [PIEDADE - 40KM] V%C3%81RIOS | H47: =IFERROR(__xludf.DUMMYFUNCTION("""COMPUTED_VALUE"""),"Facebook_Mobile_Feed") -> Facebook_Mobile_Feed | I47: =IFERROR(__xludf.DUMMYFUNCTION("""COMPUTED_VALUE"""),"07.04 [IMG] [AD04] Pedidos abertos") -> 07.04 [IMG] [AD04] Pedidos abertos | J47: =IFERROR(__xludf.DUMMYFUNCTION("""COMPUTED_VALUE"""),"07.04.2026 [V4] [WB] [LEADS-GRUPO-WHATS] 01") -> 07.04.2026 [V4] [WB] [LEADS-GRUPO-WHATS] 01 | K47: =LEFT(A47,10) -> 2026-04-12 | L47: =DATE(YEAR(SUBSTITUTE(SUBSTITUTE(K47,"-","/",1),"-","/",1)),MONTH(SUBSTITUTE(SUBSTITUTE(K47,"-","/",1),"-","/",1)),DAY(SUBSTITUTE(SUBSTITUTE(K47,"-","/",1),"-","/",1))) -> 46124 | M47: =RIGHT(C47,8) -> 96897606 | N47: =IFERROR(IF(VLOOKUP(M47,'Leads no grupo Saibai'!C:C,1,FALSE)=M47,"Sim"),"Não") -> Sim
A48: 2026-04-12T22:25:22.005Z | B48: Antônia Maria Rodrigues | C48: 15997855858 | D48: toninhaleite12@gmail.com | E48: https://lp.saibai.com.br/?utm_source=MetaAds&utm_medium=ADV+-+%5BIG%5D+%5BFB%5D+%5B30%2B%5D+%5BPIEDADE+-+40KM%5D+V%C3%81RIOS&utm_campaign=07.04.2026+%5BV4%5D+%5BWB%5D+%5BLEADS-GRUPO-WHATS%5D+01&utm_content=07.04+%5BIMG%5D+%5BAD04%5D+Pedidos+abertos&utm_term=Facebook_Mobile_Feed&fbclid=IwZXh0bgNhZW0BMABhZGlkAas0bAfOj7tzcnRjBmFwcF9pZAo2NjI4NTY4Mzc5AAEeOAltH3x8o5K0HJRl4AsF5PjaoKUZ7MLgypQlEMM60h5NyZBxNVowCHUOEkw_aem_dleLWiOyWFRW7dQxU7T9bQ&campaign_id=120247452154580155&ad_id=120247452938090155&utm_id=120247452154580155 | F48: =IFERROR(__xludf.DUMMYFUNCTION("""COMPUTED_VALUE"""),"MetaAds") -> MetaAds | G48: =IFERROR(__xludf.DUMMYFUNCTION("""COMPUTED_VALUE"""),"ADV - [IG] [FB] [30%2B] [PIEDADE - 40KM] V%C3%81RIOS") -> ADV - [IG] [FB] [30%2B] [PIEDADE - 40KM] V%C3%81RIOS | H48: =IFERROR(__xludf.DUMMYFUNCTION("""COMPUTED_VALUE"""),"Facebook_Mobile_Feed") -> Facebook_Mobile_Feed | I48: =IFERROR(__xludf.DUMMYFUNCTION("""COMPUTED_VALUE"""),"07.04 [IMG] [AD04] Pedidos abertos") -> 07.04 [IMG] [AD04] Pedidos abertos | J48: =IFERROR(__xludf.DUMMYFUNCTION("""COMPUTED_VALUE"""),"07.04.2026 [V4] [WB] [LEADS-GRUPO-WHATS] 01") -> 07.04.2026 [V4] [WB] [LEADS-GRUPO-WHATS] 01 | K48: =LEFT(A48,10) -> 2026-04-12 | L48: =DATE(YEAR(SUBSTITUTE(SUBSTITUTE(K48,"-","/",1),"-","/",1)),MONTH(SUBSTITUTE(SUBSTITUTE(K48,"-","/",1),"-","/",1)),DAY(SUBSTITUTE(SUBSTITUTE(K48,"-","/",1),"-","/",1))) -> 46124 | M48: =RIGHT(C48,8) -> 97855858 | N48: =IFERROR(IF(VLOOKUP(M48,'Leads no grupo Saibai'!C:C,1,FALSE)=M48,"Sim"),"Não") -> Sim
A49: 2026-04-12T23:24:47.514Z | B49: Carlos Costa | C49: 15991012121 | D49: costasara2012@gmail.com | E49: https://lp.saibai.com.br/?utm_source=MetaAds&utm_medium=ADV+-+%5BIG%5D+%5BFB%5D+%5B30%2B%5D+%5BPIEDADE+-+40KM%5D+V%C3%81RIOS&utm_campaign=07.04.2026+%5BV4%5D+%5BWB%5D+%5BLEADS-GRUPO-WHATS%5D+01&utm_content=07.04+%5BIMG%5D+%5BAD04%5D+Pedidos+abertos&utm_term=Facebook_Mobile_Feed&fbclid=IwZXh0bgNhZW0BMABhZGlkAas0bAfOj7tzcnRjBmFwcF9pZAwzNTA2ODU1MzE3MjgAAR6f4bBcAdayEksxARLoxgu7ZCmhkWGp-G3FTIZl2-TJeTGFarRIHTX3G8GfAQ_aem_5cmN3J-Arn1T5VTyt3oMVw&campaign_id=120247452154580155&ad_id=120247452938090155&utm_id=120247452154580155 | F49: =IFERROR(__xludf.DUMMYFUNCTION("""COMPUTED_VALUE"""),"MetaAds") -> MetaAds | G49: =IFERROR(__xludf.DUMMYFUNCTION("""COMPUTED_VALUE"""),"ADV - [IG] [FB] [30%2B] [PIEDADE - 40KM] V%C3%81RIOS") -> ADV - [IG] [FB] [30%2B] [PIEDADE - 40KM] V%C3%81RIOS | H49: =IFERROR(__xludf.DUMMYFUNCTION("""COMPUTED_VALUE"""),"Facebook_Mobile_Feed") -> Facebook_Mobile_Feed | I49: =IFERROR(__xludf.DUMMYFUNCTION("""COMPUTED_VALUE"""),"07.04 [IMG] [AD04] Pedidos abertos") -> 07.04 [IMG] [AD04] Pedidos abertos | J49: =IFERROR(__xludf.DUMMYFUNCTION("""COMPUTED_VALUE"""),"07.04.2026 [V4] [WB] [LEADS-GRUPO-WHATS] 01") -> 07.04.2026 [V4] [WB] [LEADS-GRUPO-WHATS] 01 | K49: =LEFT(A49,10) -> 2026-04-12 | L49: =DATE(YEAR(SUBSTITUTE(SUBSTITUTE(K49,"-","/",1),"-","/",1)),MONTH(SUBSTITUTE(SUBSTITUTE(K49,"-","/",1),"-","/",1)),DAY(SUBSTITUTE(SUBSTITUTE(K49,"-","/",1),"-","/",1))) -> 46124 | M49: =RIGHT(C49,8) -> 91012121 | N49: =IFERROR(IF(VLOOKUP(M49,'Leads no grupo Saibai'!C:C,1,FALSE)=M49,"Sim"),"Não") -> Sim
A50: 2026-04-13T01:12:28.362Z | B50: Marcia Croccia | C50: 15991268656 | D50: marciacroccia@gmail.com | E50: https://lp.saibai.com.br/?utm_source=MetaAds&utm_medium=ADV+-+%5BIG%5D+%5BFB%5D+%5B30%2B%5D+%5BPIEDADE+-+40KM%5D+V%C3%81RIOS&utm_campaign=07.04.2026+%5BV4%5D+%5BWB%5D+%5BLEADS-GRUPO-WHATS%5D+01&utm_content=07.04+%5BIMG%5D+%5BAD04%5D+Pedidos+abertos&utm_term=Instagram_Feed&utm_id=120247452154580155&fbclid=PAZXh0bgNhZW0BMABhZGlkAas0bAfOj7tzcnRjBmFwcF9pZA81NjcwNjczNDMzNTI0MjcAAaeDKx8ianBdfbgN3bviJFG3Ge66jee2cOL3hPy_z54EoNYnQxvLEFD0f1YzwQ_aem_tYKWwtiFeRNe_gXHGGal5g&campaign_id=120247452154580155&ad_id=120247452938090155 | F50: =IFERROR(__xludf.DUMMYFUNCTION("""COMPUTED_VALUE"""),"MetaAds") -> MetaAds | G50: =IFERROR(__xludf.DUMMYFUNCTION("""COMPUTED_VALUE"""),"ADV - [IG] [FB] [30%2B] [PIEDADE - 40KM] V%C3%81RIOS") -> ADV - [IG] [FB] [30%2B] [PIEDADE - 40KM] V%C3%81RIOS | H50: =IFERROR(__xludf.DUMMYFUNCTION("""COMPUTED_VALUE"""),"Instagram_Feed") -> Instagram_Feed | I50: =IFERROR(__xludf.DUMMYFUNCTION("""COMPUTED_VALUE"""),"07.04 [IMG] [AD04] Pedidos abertos") -> 07.04 [IMG] [AD04] Pedidos abertos | J50: =IFERROR(__xludf.DUMMYFUNCTION("""COMPUTED_VALUE"""),"07.04.2026 [V4] [WB] [LEADS-GRUPO-WHATS] 01") -> 07.04.2026 [V4] [WB] [LEADS-GRUPO-WHATS] 01 | K50: =LEFT(A50,10) -> 2026-04-13 | L50: =DATE(YEAR(SUBSTITUTE(SUBSTITUTE(K50,"-","/",1),"-","/",1)),MONTH(SUBSTITUTE(SUBSTITUTE(K50,"-","/",1),"-","/",1)),DAY(SUBSTITUTE(SUBSTITUTE(K50,"-","/",1),"-","/",1))) -> 46125 | M50: =RIGHT(C50,8) -> 91268656 | N50: =IFERROR(IF(VLOOKUP(M50,'Leads no grupo Saibai'!C:C,1,FALSE)=M50,"Sim"),"Não") -> Sim
A51: 2026-04-13T06:11:53.711Z | B51: Vivian Santos | C51: 15981773711 | D51: vifirmino@gmail.com | E51: https://lp.saibai.com.br/?utm_source=MetaAds&utm_medium=ADV+-+%5BIG%5D+%5BFB%5D+%5B30%2B%5D+%5BPIEDADE+-+40KM%5D+V%C3%81RIOS&utm_campaign=07.04.2026+%5BV4%5D+%5BWB%5D+%5BLEADS-GRUPO-WHATS%5D+01&utm_content=07.04+%5BIMG%5D+%5BAD01%5D+A+safra+come%C3%A7ou&utm_term=Facebook_Mobile_Feed&fbclid=IwZXh0bgNhZW0BMABhZGlkAas0a_chJvtzcnRjBmFwcF9pZAwzNTA2ODU1MzE3MjgAAR4hHVEou0lg63dwm-4Lg7D2KiycFUKhhW7Dn7fhTCE0Tb5RigYJP787YAKAcg_aem_HbBu4Se0oSmxwQ7cuqRibA&campaign_id=120247452154580155&ad_id=120247452154590155&utm_id=120247452154580155 | F51: =IFERROR(__xludf.DUMMYFUNCTION("""COMPUTED_VALUE"""),"MetaAds") -> MetaAds | G51: =IFERROR(__xludf.DUMMYFUNCTION("""COMPUTED_VALUE"""),"ADV - [IG] [FB] [30%2B] [PIEDADE - 40KM] V%C3%81RIOS") -> ADV - [IG] [FB] [30%2B] [PIEDADE - 40KM] V%C3%81RIOS | H51: =IFERROR(__xludf.DUMMYFUNCTION("""COMPUTED_VALUE"""),"Facebook_Mobile_Feed") -> Facebook_Mobile_Feed | I51: =IFERROR(__xludf.DUMMYFUNCTION("""COMPUTED_VALUE"""),"07.04 [IMG] [AD01] A safra come%C3%A7ou") -> 07.04 [IMG] [AD01] A safra come%C3%A7ou | J51: =IFERROR(__xludf.DUMMYFUNCTION("""COMPUTED_VALUE"""),"07.04.2026 [V4] [WB] [LEADS-GRUPO-WHATS] 01") -> 07.04.2026 [V4] [WB] [LEADS-GRUPO-WHATS] 01 | K51: =LEFT(A51,10) -> 2026-04-13 | L51: =DATE(YEAR(SUBSTITUTE(SUBSTITUTE(K51,"-","/",1),"-","/",1)),MONTH(SUBSTITUTE(SUBSTITUTE(K51,"-","/",1),"-","/",1)),DAY(SUBSTITUTE(SUBSTITUTE(K51,"-","/",1),"-","/",1))) -> 46125 | M51: =RIGHT(C51,8) -> 81773711 | N51: =IFERROR(IF(VLOOKUP(M51,'Leads no grupo Saibai'!C:C,1,FALSE)=M51,"Sim"),"Não") -> Sim
A52: 2026-04-13T09:40:45.773Z | B52: Márcia Toyoda | C52: 15998386011 | D52: marciatoyoda5@gmail.com | E52: https://lp.saibai.com.br/?utm_source=MetaAds&utm_medium=ADV+-+%5BIG%5D+%5BFB%5D+%5B30%2B%5D+%5BPIEDADE+-+40KM%5D+V%C3%81RIOS&utm_campaign=07.04.2026+%5BV4%5D+%5BWB%5D+%5BLEADS-GRUPO-WHATS%5D+01&utm_content=07.04+%5BIMG%5D+%5BAD04%5D+Pedidos+abertos&utm_term=Instagram_Stories&utm_id=120247452154580155&fbclid=PAZXh0bgNhZW0BMABhZGlkAas0bAW7ZytzcnRjBmFwcF9pZA81NjcwNjczNDMzNTI0MjcAAacwO8J97U7cU9mk7zwoFFD0gyp4veL9C8LIAx6OE96bsTegkNBEtkYuqKw5Jw_aem_9o28ChwMB9uqwI6sv_YzBg&campaign_id=120247452154580155&ad_id=120247452938090155 | F52: =IFERROR(__xludf.DUMMYFUNCTION("""COMPUTED_VALUE"""),"MetaAds") -> MetaAds | G52: =IFERROR(__xludf.DUMMYFUNCTION("""COMPUTED_VALUE"""),"ADV - [IG] [FB] [30%2B] [PIEDADE - 40KM] V%C3%81RIOS") -> ADV - [IG] [FB] [30%2B] [PIEDADE - 40KM] V%C3%81RIOS | H52: =IFERROR(__xludf.DUMMYFUNCTION("""COMPUTED_VALUE"""),"Instagram_Stories") -> Instagram_Stories | I52: =IFERROR(__xludf.DUMMYFUNCTION("""COMPUTED_VALUE"""),"07.04 [IMG] [AD04] Pedidos abertos") -> 07.04 [IMG] [AD04] Pedidos abertos | J52: =IFERROR(__xludf.DUMMYFUNCTION("""COMPUTED_VALUE"""),"07.04.2026 [V4] [WB] [LEADS-GRUPO-WHATS] 01") -> 07.04.2026 [V4] [WB] [LEADS-GRUPO-WHATS] 01 | K52: =LEFT(A52,10) -> 2026-04-13 | L52: =DATE(YEAR(SUBSTITUTE(SUBSTITUTE(K52,"-","/",1),"-","/",1)),MONTH(SUBSTITUTE(SUBSTITUTE(K52,"-","/",1),"-","/",1)),DAY(SUBSTITUTE(SUBSTITUTE(K52,"-","/",1),"-","/",1))) -> 46125 | M52: =RIGHT(C52,8) -> 98386011 | N52: =IFERROR(IF(VLOOKUP(M52,'Leads no grupo Saibai'!C:C,1,FALSE)=M52,"Sim"),"Não") -> Sim
A53: 2026-04-13T10:34:51.949Z | B53: Lilian | C53: 11992506864 | D53: likatoyokawa@gmail.com | E53: https://lp.saibai.com.br/?utm_source=MetaAds&utm_medium=ADV+-+%5BIG%5D+%5BFB%5D+%5B30%2B%5D+%5BPIEDADE+-+40KM%5D+V%C3%81RIOS&utm_campaign=07.04.2026+%5BV4%5D+%5BWB%5D+%5BLEADS-GRUPO-WHATS%5D+01&utm_content=07.04+%5BIMG%5D+%5BAD01%5D+A+safra+come%C3%A7ou&utm_term=Instagram_Stories&utm_id=120247452154580155&fbclid=PAZXh0bgNhZW0BMABhZGlkAas0a_chJvtzcnRjBmFwcF9pZA81NjcwNjczNDMzNTI0MjcAAae2rBIaSNdCwQDAdyykNlbz550iIN12GNeZJlQ9ABfVZ592MPcG_LsnsoTsEg_aem__ypSRh2tzy_BkfWwpmqWqw&campaign_id=120247452154580155&ad_id=120247452154590155 | F53: =IFERROR(__xludf.DUMMYFUNCTION("""COMPUTED_VALUE"""),"MetaAds") -> MetaAds | G53: =IFERROR(__xludf.DUMMYFUNCTION("""COMPUTED_VALUE"""),"ADV - [IG] [FB] [30%2B] [PIEDADE - 40KM] V%C3%81RIOS") -> ADV - [IG] [FB] [30%2B] [PIEDADE - 40KM] V%C3%81RIOS | H53: =IFERROR(__xludf.DUMMYFUNCTION("""COMPUTED_VALUE"""),"Instagram_Stories") -> Instagram_Stories | I53: =IFERROR(__xludf.DUMMYFUNCTION("""COMPUTED_VALUE"""),"07.04 [IMG] [AD01] A safra come%C3%A7ou") -> 07.04 [IMG] [AD01] A safra come%C3%A7ou | J53: =IFERROR(__xludf.DUMMYFUNCTION("""COMPUTED_VALUE"""),"07.04.2026 [V4] [WB] [LEADS-GRUPO-WHATS] 01") -> 07.04.2026 [V4] [WB] [LEADS-GRUPO-WHATS] 01 | K53: =LEFT(A53,10) -> 2026-04-13 | L53: =DATE(YEAR(SUBSTITUTE(SUBSTITUTE(K53,"-","/",1),"-","/",1)),MONTH(SUBSTITUTE(SUBSTITUTE(K53,"-","/",1),"-","/",1)),DAY(SUBSTITUTE(SUBSTITUTE(K53,"-","/",1),"-","/",1))) -> 46125 | M53: =RIGHT(C53,8) -> 92506864 | N53: =IFERROR(IF(VLOOKUP(M53,'Leads no grupo Saibai'!C:C,1,FALSE)=M53,"Sim"),"Não") -> Sim
A54: 2026-04-13T13:26:08.320Z | B54: Jane Scarpa | C54: 15981118262 | D54: jane_scarpa@hotmail.com | E54: https://lp.saibai.com.br/?utm_source=MetaAds&utm_medium=ADV+-+%5BIG%5D+%5BFB%5D+%5B30%2B%5D+%5BPIEDADE+-+40KM%5D+V%C3%81RIOS&utm_campaign=07.04.2026+%5BV4%5D+%5BWB%5D+%5BLEADS-GRUPO-WHATS%5D+01&utm_content=07.04+%5BIMG%5D+%5BAD04%5D+Pedidos+abertos&utm_term=Facebook_Mobile_Feed&fbclid=IwZXh0bgNhZW0BMABhZGlkAas0bAfOj7tzcnRjBmFwcF9pZAo2NjI4NTY4Mzc5AAEePI0L28IEBFobUPYjjKBqFiUXPij0W1Nudmg_wiXeH6LfMlicqV3sR9sAPZ0_aem_c56HwmHO7gpr96ZOghZx3A&campaign_id=120247452154580155&ad_id=120247452938090155&utm_id=120247452154580155 | F54: =IFERROR(__xludf.DUMMYFUNCTION("""COMPUTED_VALUE"""),"MetaAds") -> MetaAds | G54: =IFERROR(__xludf.DUMMYFUNCTION("""COMPUTED_VALUE"""),"ADV - [IG] [FB] [30%2B] [PIEDADE - 40KM] V%C3%81RIOS") -> ADV - [IG] [FB] [30%2B] [PIEDADE - 40KM] V%C3%81RIOS | H54: =IFERROR(__xludf.DUMMYFUNCTION("""COMPUTED_VALUE"""),"Facebook_Mobile_Feed") -> Facebook_Mobile_Feed | I54: =IFERROR(__xludf.DUMMYFUNCTION("""COMPUTED_VALUE"""),"07.04 [IMG] [AD04] Pedidos abertos") -> 07.04 [IMG] [AD04] Pedidos abertos | J54: =IFERROR(__xludf.DUMMYFUNCTION("""COMPUTED_VALUE"""),"07.04.2026 [V4] [WB] [LEADS-GRUPO-WHATS] 01") -> 07.04.2026 [V4] [WB] [LEADS-GRUPO-WHATS] 01 | K54: =LEFT(A54,10) -> 2026-04-13 | L54: =DATE(YEAR(SUBSTITUTE(SUBSTITUTE(K54,"-","/",1),"-","/",1)),MONTH(SUBSTITUTE(SUBSTITUTE(K54,"-","/",1),"-","/",1)),DAY(SUBSTITUTE(SUBSTITUTE(K54,"-","/",1),"-","/",1))) -> 46125 | M54: =RIGHT(C54,8) -> 81118262 | N54: =IFERROR(IF(VLOOKUP(M54,'Leads no grupo Saibai'!C:C,1,FALSE)=M54,"Sim"),"Não") -> Sim
A55: 2026-04-13T16:03:53.379Z | B55: Ana Paula | C55: 15991097562 | D55: paulateich@icloud.com | E55: https://lp.saibai.com.br/?utm_source=MetaAds&utm_medium=ADV+-+%5BIG%5D+%5BFB%5D+%5B30%2B%5D+%5BPIEDADE+-+40KM%5D+V%C3%81RIOS&utm_campaign=07.04.2026+%5BV4%5D+%5BWB%5D+%5BLEADS-GRUPO-WHATS%5D+01&utm_content=07.04+%5BIMG%5D+%5BAD04%5D+Pedidos+abertos&utm_term=Facebook_Mobile_Feed&fbclid=IwZXh0bgNhZW0BMABhZGlkAas0bAW7ZytzcnRjBmFwcF9pZAo2NjI4NTY4Mzc5AAEe_Hiac9Mlo4bjmbifeG5sysMBn8TAoTZx3KZfjc0p13NmxyzwnYY5NxqQVzw_aem_ysr9Insn4d2lo-0imWUuAQ&campaign_id=120247452154580155&ad_id=120247452938090155&utm_id=120247452154580155 | F55: =IFERROR(__xludf.DUMMYFUNCTION("""COMPUTED_VALUE"""),"MetaAds") -> MetaAds | G55: =IFERROR(__xludf.DUMMYFUNCTION("""COMPUTED_VALUE"""),"ADV - [IG] [FB] [30%2B] [PIEDADE - 40KM] V%C3%81RIOS") -> ADV - [IG] [FB] [30%2B] [PIEDADE - 40KM] V%C3%81RIOS | H55: =IFERROR(__xludf.DUMMYFUNCTION("""COMPUTED_VALUE"""),"Facebook_Mobile_Feed") -> Facebook_Mobile_Feed | I55: =IFERROR(__xludf.DUMMYFUNCTION("""COMPUTED_VALUE"""),"07.04 [IMG] [AD04] Pedidos abertos") -> 07.04 [IMG] [AD04] Pedidos abertos | J55: =IFERROR(__xludf.DUMMYFUNCTION("""COMPUTED_VALUE"""),"07.04.2026 [V4] [WB] [LEADS-GRUPO-WHATS] 01") -> 07.04.2026 [V4] [WB] [LEADS-GRUPO-WHATS] 01 | K55: =LEFT(A55,10) -> 2026-04-13 | L55: =DATE(YEAR(SUBSTITUTE(SUBSTITUTE(K55,"-","/",1),"-","/",1)),MONTH(SUBSTITUTE(SUBSTITUTE(K55,"-","/",1),"-","/",1)),DAY(SUBSTITUTE(SUBSTITUTE(K55,"-","/",1),"-","/",1))) -> 46125 | M55: =RIGHT(C55,8) -> 91097562 | N55: =IFERROR(IF(VLOOKUP(M55,'Leads no grupo Saibai'!C:C,1,FALSE)=M55,"Sim"),"Não") -> Sim
A56: 2026-04-13T16:33:25.954Z | B56: Geny jabra malke stigliani | C56: 15997034757 | D56: gemalke@gmail.com | E56: https://lp.saibai.com.br/?utm_source=MetaAds&utm_medium=ADV+-+%5BIG%5D+%5BFB%5D+%5B30%2B%5D+%5BPIEDADE+-+40KM%5D+V%C3%81RIOS&utm_campaign=07.04.2026+%5BV4%5D+%5BWB%5D+%5BLEADS-GRUPO-WHATS%5D+01&utm_content=07.04+%5BIMG%5D+%5BAD04%5D+Pedidos+abertos&utm_term=Facebook_Mobile_Feed&fbclid=IwZXh0bgNhZW0BMABhZGlkAas0bAW7ZytzcnRjBmFwcF9pZAwzNTA2ODU1MzE3MjgAAR719o09HNfA9Mh94YVyghG7Nu870FlEkzKuWrj_7rGZk8lYGzPANRLpkDWAXA_aem_nGWl5qwp3kRgR-jub1wzew&campaign_id=120247452154580155&ad_id=120247452938090155&utm_id=120247452154580155 | F56: =IFERROR(__xludf.DUMMYFUNCTION("""COMPUTED_VALUE"""),"MetaAds") -> MetaAds | G56: =IFERROR(__xludf.DUMMYFUNCTION("""COMPUTED_VALUE"""),"ADV - [IG] [FB] [30%2B] [PIEDADE - 40KM] V%C3%81RIOS") -> ADV - [IG] [FB] [30%2B] [PIEDADE - 40KM] V%C3%81RIOS | H56: =IFERROR(__xludf.DUMMYFUNCTION("""COMPUTED_VALUE"""),"Facebook_Mobile_Feed") -> Facebook_Mobile_Feed | I56: =IFERROR(__xludf.DUMMYFUNCTION("""COMPUTED_VALUE"""),"07.04 [IMG] [AD04] Pedidos abertos") -> 07.04 [IMG] [AD04] Pedidos abertos | J56: =IFERROR(__xludf.DUMMYFUNCTION("""COMPUTED_VALUE"""),"07.04.2026 [V4] [WB] [LEADS-GRUPO-WHATS] 01") -> 07.04.2026 [V4] [WB] [LEADS-GRUPO-WHATS] 01 | K56: =LEFT(A56,10) -> 2026-04-13 | L56: =DATE(YEAR(SUBSTITUTE(SUBSTITUTE(K56,"-","/",1),"-","/",1)),MONTH(SUBSTITUTE(SUBSTITUTE(K56,"-","/",1),"-","/",1)),DAY(SUBSTITUTE(SUBSTITUTE(K56,"-","/",1),"-","/",1))) -> 46125 | M56: =RIGHT(C56,8) -> 97034757 | N56: =IFERROR(IF(VLOOKUP(M56,'Leads no grupo Saibai'!C:C,1,FALSE)=M56,"Sim"),"Não") -> Sim
A57: 2026-04-13T17:55:21.685Z | B57: Maria Suracchio | C57: 16999934108 | D57: rescuracchio@uol.com.br | E57: https://lp.saibai.com.br/?utm_source=MetaAds&utm_medium=ADV+-+%5BIG%5D+%5BFB%5D+%5B30%2B%5D+%5BPIEDADE+-+40KM%5D+V%C3%81RIOS&utm_campaign=07.04.2026+%5BV4%5D+%5BWB%5D+%5BLEADS-GRUPO-WHATS%5D+01&utm_content=07.04+%5BIMG%5D+%5BAD04%5D+Pedidos+abertos&utm_term=Instagram_Feed&utm_id=120247452154580155&fbclid=PAZXh0bgNhZW0BMABhZGlkAas0bAW7ZytzcnRjBmFwcF9pZA8xMjQwMjQ1NzQyODc0MTQAAafTjFGdkF_OzJjMrS_oLmLgOJSaFyPseWs_l2R7HNZJOrO4TNFLUMlZ_XwwBQ_aem_d2uQTqih9gmiIz08BxlQBA&campaign_id=120247452154580155&ad_id=120247452938090155 | F57: =IFERROR(__xludf.DUMMYFUNCTION("""COMPUTED_VALUE"""),"MetaAds") -> MetaAds | G57: =IFERROR(__xludf.DUMMYFUNCTION("""COMPUTED_VALUE"""),"ADV - [IG] [FB] [30%2B] [PIEDADE - 40KM] V%C3%81RIOS") -> ADV - [IG] [FB] [30%2B] [PIEDADE - 40KM] V%C3%81RIOS | H57: =IFERROR(__xludf.DUMMYFUNCTION("""COMPUTED_VALUE"""),"Instagram_Feed") -> Instagram_Feed | I57: =IFERROR(__xludf.DUMMYFUNCTION("""COMPUTED_VALUE"""),"07.04 [IMG] [AD04] Pedidos abertos") -> 07.04 [IMG] [AD04] Pedidos abertos | J57: =IFERROR(__xludf.DUMMYFUNCTION("""COMPUTED_VALUE"""),"07.04.2026 [V4] [WB] [LEADS-GRUPO-WHATS] 01") -> 07.04.2026 [V4] [WB] [LEADS-GRUPO-WHATS] 01 | K57: =LEFT(A57,10) -> 2026-04-13 | L57: =DATE(YEAR(SUBSTITUTE(SUBSTITUTE(K57,"-","/",1),"-","/",1)),MONTH(SUBSTITUTE(SUBSTITUTE(K57,"-","/",1),"-","/",1)),DAY(SUBSTITUTE(SUBSTITUTE(K57,"-","/",1),"-","/",1))) -> 46125 | M57: =RIGHT(C57,8) -> 99934108 | N57: =IFERROR(IF(VLOOKUP(M57,'Leads no grupo Saibai'!C:C,1,FALSE)=M57,"Sim"),"Não") -> Sim
A58: 2026-04-13T17:58:22.537Z | B58: Angela Maria Biazotto de Paula | C58: 15997086431 | D58: angelabiazotto@gmail.com | E58: https://lp.saibai.com.br/?utm_source=MetaAds&utm_medium=ADV+-+%5BIG%5D+%5BFB%5D+%5B30%2B%5D+%5BPIEDADE+-+40KM%5D+V%C3%81RIOS&utm_campaign=07.04.2026+%5BV4%5D+%5BWB%5D+%5BLEADS-GRUPO-WHATS%5D+01&utm_content=07.04+%5BIMG%5D+%5BAD04%5D+Pedidos+abertos&utm_term=Facebook_Mobile_Feed&fbclid=IwZXh0bgNhZW0BMABhZGlkAas0bAW7ZytzcnRjBmFwcF9pZAwzNTA2ODU1MzE3MjgAAR76C-mhHNrO4bCs5Mu6Ek-Pqtx_Ff9aKIWR6rIfUngxrVS_Qi6EtnsVfNrtNA_aem_BXz2nXf21c2IfAxkmmoDyg&campaign_id=120247452154580155&ad_id=120247452938090155&utm_id=120247452154580155 | F58: =IFERROR(__xludf.DUMMYFUNCTION("""COMPUTED_VALUE"""),"MetaAds") -> MetaAds | G58: =IFERROR(__xludf.DUMMYFUNCTION("""COMPUTED_VALUE"""),"ADV - [IG] [FB] [30%2B] [PIEDADE - 40KM] V%C3%81RIOS") -> ADV - [IG] [FB] [30%2B] [PIEDADE - 40KM] V%C3%81RIOS | H58: =IFERROR(__xludf.DUMMYFUNCTION("""COMPUTED_VALUE"""),"Facebook_Mobile_Feed") -> Facebook_Mobile_Feed | I58: =IFERROR(__xludf.DUMMYFUNCTION("""COMPUTED_VALUE"""),"07.04 [IMG] [AD04] Pedidos abertos") -> 07.04 [IMG] [AD04] Pedidos abertos | J58: =IFERROR(__xludf.DUMMYFUNCTION("""COMPUTED_VALUE"""),"07.04.2026 [V4] [WB] [LEADS-GRUPO-WHATS] 01") -> 07.04.2026 [V4] [WB] [LEADS-GRUPO-WHATS] 01 | K58: =LEFT(A58,10) -> 2026-04-13 | L58: =DATE(YEAR(SUBSTITUTE(SUBSTITUTE(K58,"-","/",1),"-","/",1)),MONTH(SUBSTITUTE(SUBSTITUTE(K58,"-","/",1),"-","/",1)),DAY(SUBSTITUTE(SUBSTITUTE(K58,"-","/",1),"-","/",1))) -> 46125 | M58: =RIGHT(C58,8) -> 97086431 | N58: =IFERROR(IF(VLOOKUP(M58,'Leads no grupo Saibai'!C:C,1,FALSE)=M58,"Sim"),"Não") -> Sim
A59: 2026-04-13T18:03:16.627Z | B59: Jane Scarpa | C59: 15981118262 | D59: jane_scarpa@hotmail.com | E59: https://lp.saibai.com.br/?utm_source=MetaAds&utm_medium=ADV+-+%5BIG%5D+%5BFB%5D+%5B30%2B%5D+%5BPIEDADE+-+40KM%5D+V%C3%81RIOS&utm_campaign=07.04.2026+%5BV4%5D+%5BWB%5D+%5BLEADS-GRUPO-WHATS%5D+01&utm_content=07.04+%5BIMG%5D+%5BAD04%5D+Pedidos+abertos&utm_term=Facebook_Mobile_Feed&fbclid=IwZXh0bgNhZW0BMABhZGlkAas0bAfOj7tzcnRjBmFwcF9pZAo2NjI4NTY4Mzc5AAEewbj_O5LTKXyh38wzpxT7K2EsRhsfxjY0AaRO73aS-ywlZxNbFRsezUyQNuU_aem_wfRirr_jwAfTvnNgi9rewA&campaign_id=120247452154580155&ad_id=120247452938090155&utm_id=120247452154580155 | F59: =IFERROR(__xludf.DUMMYFUNCTION("""COMPUTED_VALUE"""),"MetaAds") -> MetaAds | G59: =IFERROR(__xludf.DUMMYFUNCTION("""COMPUTED_VALUE"""),"ADV - [IG] [FB] [30%2B] [PIEDADE - 40KM] V%C3%81RIOS") -> ADV - [IG] [FB] [30%2B] [PIEDADE - 40KM] V%C3%81RIOS | H59: =IFERROR(__xludf.DUMMYFUNCTION("""COMPUTED_VALUE"""),"Facebook_Mobile_Feed") -> Facebook_Mobile_Feed | I59: =IFERROR(__xludf.DUMMYFUNCTION("""COMPUTED_VALUE"""),"07.04 [IMG] [AD04] Pedidos abertos") -> 07.04 [IMG] [AD04] Pedidos abertos | J59: =IFERROR(__xludf.DUMMYFUNCTION("""COMPUTED_VALUE"""),"07.04.2026 [V4] [WB] [LEADS-GRUPO-WHATS] 01") -> 07.04.2026 [V4] [WB] [LEADS-GRUPO-WHATS] 01 | K59: =LEFT(A59,10) -> 2026-04-13 | L59: =DATE(YEAR(SUBSTITUTE(SUBSTITUTE(K59,"-","/",1),"-","/",1)),MONTH(SUBSTITUTE(SUBSTITUTE(K59,"-","/",1),"-","/",1)),DAY(SUBSTITUTE(SUBSTITUTE(K59,"-","/",1),"-","/",1))) -> 46125 | M59: =RIGHT(C59,8) -> 81118262 | N59: =IFERROR(IF(VLOOKUP(M59,'Leads no grupo Saibai'!C:C,1,FALSE)=M59,"Sim"),"Não") -> Sim
A60: 2026-04-13T21:49:32.223Z | B60: CLEMENTINA SIVIERO | C60: 19996015972 | D60: tina@supercromo.com.br | E60: https://lp.saibai.com.br/?utm_source=MetaAds&utm_medium=%7B%7Badset.name%7D%7D&utm_campaign=%7B%7Bcampaign.name%7D%7D&utm_content=%7B%7Bad.name%7D%7D&utm_term=%7B%7Bplacement%7D%7D | F60: =IFERROR(__xludf.DUMMYFUNCTION("""COMPUTED_VALUE"""),"MetaAds") -> MetaAds | G60: =IFERROR(__xludf.DUMMYFUNCTION("""COMPUTED_VALUE"""),"%7B%7Badset.name%7D%7D") -> %7B%7Badset.name%7D%7D | H60: =IFERROR(__xludf.DUMMYFUNCTION("""COMPUTED_VALUE"""),"%7B%7Bplacement%7D%7D") -> %7B%7Bplacement%7D%7D | I60: =IFERROR(__xludf.DUMMYFUNCTION("""COMPUTED_VALUE"""),"%7B%7Bad.name%7D%7D") -> %7B%7Bad.name%7D%7D | J60: =IFERROR(__xludf.DUMMYFUNCTION("""COMPUTED_VALUE"""),"%7B%7Bcampaign.name%7D%7D") -> %7B%7Bcampaign.name%7D%7D | K60: =LEFT(A60,10) -> 2026-04-13 | L60: =DATE(YEAR(SUBSTITUTE(SUBSTITUTE(K60,"-","/",1),"-","/",1)),MONTH(SUBSTITUTE(SUBSTITUTE(K60,"-","/",1),"-","/",1)),DAY(SUBSTITUTE(SUBSTITUTE(K60,"-","/",1),"-","/",1))) -> 46125 | M60: =RIGHT(C60,8) -> 96015972 | N60: =IFERROR(IF(VLOOKUP(M60,'Leads no grupo Saibai'!C:C,1,FALSE)=M60,"Sim"),"Não") -> Sim
A61: 2026-04-13T22:45:17.907Z | B61: Laura Lima | C61: 15998337833 | D61: lauralima5094@gmail.com | E61: https://lp.saibai.com.br/?utm_source=MetaAds&utm_medium=ADV+-+%5BIG%5D+%5BFB%5D+%5B30%2B%5D+%5BPIEDADE+-+40KM%5D+V%C3%81RIOS&utm_campaign=07.04.2026+%5BV4%5D+%5BWB%5D+%5BLEADS-GRUPO-WHATS%5D+01&utm_content=07.04+%5BIMG%5D+%5BAD04%5D+Pedidos+abertos&utm_term=Facebook_Mobile_Reels&fbclid=IwZXh0bgNhZW0BMABhZGlkAas0bAW7ZytzcnRjBmFwcF9pZAo2NjI4NTY4Mzc5AAEeXWApn53DGPWAZUXZ7PInXIO8NvwN8ghnB-lpg7KjhbDCcEw9S8iVB6WOl68_aem_melm75ihQlVu4C46UVVzgw&campaign_id=120247452154580155&ad_id=120247452938090155&utm_id=120247452154580155 | F61: =IFERROR(__xludf.DUMMYFUNCTION("""COMPUTED_VALUE"""),"MetaAds") -> MetaAds | G61: =IFERROR(__xludf.DUMMYFUNCTION("""COMPUTED_VALUE"""),"ADV - [IG] [FB] [30%2B] [PIEDADE - 40KM] V%C3%81RIOS") -> ADV - [IG] [FB] [30%2B] [PIEDADE - 40KM] V%C3%81RIOS | H61: =IFERROR(__xludf.DUMMYFUNCTION("""COMPUTED_VALUE"""),"Facebook_Mobile_Reels") -> Facebook_Mobile_Reels | I61: =IFERROR(__xludf.DUMMYFUNCTION("""COMPUTED_VALUE"""),"07.04 [IMG] [AD04] Pedidos abertos") -> 07.04 [IMG] [AD04] Pedidos abertos | J61: =IFERROR(__xludf.DUMMYFUNCTION("""COMPUTED_VALUE"""),"07.04.2026 [V4] [WB] [LEADS-GRUPO-WHATS] 01") -> 07.04.2026 [V4] [WB] [LEADS-GRUPO-WHATS] 01 | K61: =LEFT(A61,10) -> 2026-04-13 | L61: =DATE(YEAR(SUBSTITUTE(SUBSTITUTE(K61,"-","/",1),"-","/",1)),MONTH(SUBSTITUTE(SUBSTITUTE(K61,"-","/",1),"-","/",1)),DAY(SUBSTITUTE(SUBSTITUTE(K61,"-","/",1),"-","/",1))) -> 46125 | M61: =RIGHT(C61,8) -> 98337833 | N61: =IFERROR(IF(VLOOKUP(M61,'Leads no grupo Saibai'!C:C,1,FALSE)=M61,"Sim"),"Não") -> Sim
A62: 2026-04-14T00:44:47.256Z | B62: Arianna S. | C62: 55159977742 | D62: ariannasassaroli@gmail.com | E62: https://lp.saibai.com.br/?utm_source=MetaAds&utm_medium=ADV+-+%5BIG%5D+%5BFB%5D+%5B30%2B%5D+%5BPIEDADE+-+40KM%5D+V%C3%81RIOS&utm_campaign=07.04.2026+%5BV4%5D+%5BWB%5D+%5BLEADS-GRUPO-WHATS%5D+01&utm_content=07.04+%5BIMG%5D+%5BAD04%5D+Pedidos+abertos&utm_term=Instagram_Feed&utm_id=120247452154580155&fbclid=PAZXh0bgNhZW0BMABhZGlkAas0bAW7ZytzcnRjBmFwcF9pZA8xMjQwMjQ1NzQyODc0MTQAAadwq1OGwfFlArwQdq8u5QBB1yGFQ22GDMk61MJ9Qz42jmYePZi7tgpsxRKsTw_aem_0a5XqFCOmKe651v3yV0tsA&campaign_id=120247452154580155&ad_id=120247452938090155 | F62: =IFERROR(__xludf.DUMMYFUNCTION("""COMPUTED_VALUE"""),"MetaAds") -> MetaAds | G62: =IFERROR(__xludf.DUMMYFUNCTION("""COMPUTED_VALUE"""),"ADV - [IG] [FB] [30%2B] [PIEDADE - 40KM] V%C3%81RIOS") -> ADV - [IG] [FB] [30%2B] [PIEDADE - 40KM] V%C3%81RIOS | H62: =IFERROR(__xludf.DUMMYFUNCTION("""COMPUTED_VALUE"""),"Instagram_Feed") -> Instagram_Feed | I62: =IFERROR(__xludf.DUMMYFUNCTION("""COMPUTED_VALUE"""),"07.04 [IMG] [AD04] Pedidos abertos") -> 07.04 [IMG] [AD04] Pedidos abertos | J62: =IFERROR(__xludf.DUMMYFUNCTION("""COMPUTED_VALUE"""),"07.04.2026 [V4] [WB] [LEADS-GRUPO-WHATS] 01") -> 07.04.2026 [V4] [WB] [LEADS-GRUPO-WHATS] 01 | K62: =LEFT(A62,10) -> 2026-04-14 | L62: =DATE(YEAR(SUBSTITUTE(SUBSTITUTE(K62,"-","/",1),"-","/",1)),MONTH(SUBSTITUTE(SUBSTITUTE(K62,"-","/",1),"-","/",1)),DAY(SUBSTITUTE(SUBSTITUTE(K62,"-","/",1),"-","/",1))) -> 46126 | M62: =RIGHT(C62,8) -> 59977742 | N62: =IFERROR(IF(VLOOKUP(M62,'Leads no grupo Saibai'!C:C,1,FALSE)=M62,"Sim"),"Não") -> Não
A63: 2026-04-14T01:20:53.491Z | B63: Jeane Marie | C63: 15981131732 | D63: jmpeter@uol.com.br | E63: https://lp.saibai.com.br/?utm_source=MetaAds&utm_medium=ADV+-+%5BIG%5D+%5BFB%5D+%5B30%2B%5D+%5BPIEDADE+-+40KM%5D+V%C3%81RIOS&utm_campaign=07.04.2026+%5BV4%5D+%5BWB%5D+%5BLEADS-GRUPO-WHATS%5D+01&utm_content=07.04+%5BIMG%5D+%5BAD01%5D+A+safra+come%C3%A7ou&utm_term=Instagram_Feed&utm_id=120247452154580155&fbclid=PAZXh0bgNhZW0BMABhZGlkAas0a_chJvtzcnRjBmFwcF9pZA81NjcwNjczNDMzNTI0MjcAAaejFV20wgIV9EOqARug0sbVNGgLrYzf88TZtesUPZe5iAJgqfJ7TMfISbuJlA_aem_AKV61uG53jXpm90dRiKndg&campaign_id=120247452154580155&ad_id=120247452154590155 | F63: =IFERROR(__xludf.DUMMYFUNCTION("""COMPUTED_VALUE"""),"MetaAds") -> MetaAds | G63: =IFERROR(__xludf.DUMMYFUNCTION("""COMPUTED_VALUE"""),"ADV - [IG] [FB] [30%2B] [PIEDADE - 40KM] V%C3%81RIOS") -> ADV - [IG] [FB] [30%2B] [PIEDADE - 40KM] V%C3%81RIOS | H63: =IFERROR(__xludf.DUMMYFUNCTION("""COMPUTED_VALUE"""),"Instagram_Feed") -> Instagram_Feed | I63: =IFERROR(__xludf.DUMMYFUNCTION("""COMPUTED_VALUE"""),"07.04 [IMG] [AD01] A safra come%C3%A7ou") -> 07.04 [IMG] [AD01] A safra come%C3%A7ou | J63: =IFERROR(__xludf.DUMMYFUNCTION("""COMPUTED_VALUE"""),"07.04.2026 [V4] [WB] [LEADS-GRUPO-WHATS] 01") -> 07.04.2026 [V4] [WB] [LEADS-GRUPO-WHATS] 01 | K63: =LEFT(A63,10) -> 2026-04-14 | L63: =DATE(YEAR(SUBSTITUTE(SUBSTITUTE(K63,"-","/",1),"-","/",1)),MONTH(SUBSTITUTE(SUBSTITUTE(K63,"-","/",1),"-","/",1)),DAY(SUBSTITUTE(SUBSTITUTE(K63,"-","/",1),"-","/",1))) -> 46126 | M63: =RIGHT(C63,8) -> 81131732 | N63: =IFERROR(IF(VLOOKUP(M63,'Leads no grupo Saibai'!C:C,1,FALSE)=M63,"Sim"),"Não") -> Não
A64: 2026-04-14T07:16:40.264Z | B64: Vivian firmino | C64: 55159817737 | D64: vifirmino@gmail.com | E64: https://lp.saibai.com.br/?utm_source=MetaAds&utm_medium=ADV+-+%5BIG%5D+%5BFB%5D+%5B30%2B%5D+%5BPIEDADE+-+40KM%5D+V%C3%81RIOS&utm_campaign=07.04.2026+%5BV4%5D+%5BWB%5D+%5BLEADS-GRUPO-WHATS%5D+01&utm_content=07.04+%5BIMG%5D+%5BAD01%5D+A+safra+come%C3%A7ou&utm_term=Instagram_Feed&utm_id=120247452154580155&fbclid=PAZXh0bgNhZW0BMABhZGlkAas0a_chJvtzcnRjBmFwcF9pZA81NjcwNjczNDMzNTI0MjcAAac4qHYEvhRrTvYOm4mGDkdpQtYnH4x7UZWXDgBoZHT2x8DH4OySE-nV3VwiuQ_aem_PtYsFw1aU2ZOHfYd0PpCVA&campaign_id=120247452154580155&ad_id=120247452154590155 | F64: =IFERROR(__xludf.DUMMYFUNCTION("""COMPUTED_VALUE"""),"MetaAds") -> MetaAds | G64: =IFERROR(__xludf.DUMMYFUNCTION("""COMPUTED_VALUE"""),"ADV - [IG] [FB] [30%2B] [PIEDADE - 40KM] V%C3%81RIOS") -> ADV - [IG] [FB] [30%2B] [PIEDADE - 40KM] V%C3%81RIOS | H64: =IFERROR(__xludf.DUMMYFUNCTION("""COMPUTED_VALUE"""),"Instagram_Feed") -> Instagram_Feed | I64: =IFERROR(__xludf.DUMMYFUNCTION("""COMPUTED_VALUE"""),"07.04 [IMG] [AD01] A safra come%C3%A7ou") -> 07.04 [IMG] [AD01] A safra come%C3%A7ou | J64: =IFERROR(__xludf.DUMMYFUNCTION("""COMPUTED_VALUE"""),"07.04.2026 [V4] [WB] [LEADS-GRUPO-WHATS] 01") -> 07.04.2026 [V4] [WB] [LEADS-GRUPO-WHATS] 01 | K64: =LEFT(A64,10) -> 2026-04-14 | L64: =DATE(YEAR(SUBSTITUTE(SUBSTITUTE(K64,"-","/",1),"-","/",1)),MONTH(SUBSTITUTE(SUBSTITUTE(K64,"-","/",1),"-","/",1)),DAY(SUBSTITUTE(SUBSTITUTE(K64,"-","/",1),"-","/",1))) -> 46126 | M64: =RIGHT(C64,8) -> 59817737 | N64: =IFERROR(IF(VLOOKUP(M64,'Leads no grupo Saibai'!C:C,1,FALSE)=M64,"Sim"),"Não") -> Não
A65: 2026-04-14T10:09:57.295Z | B65: Caroline Huada | C65: 15998302019 | D65: carol.huada@uol.com.br | E65: https://lp.saibai.com.br/?utm_source=MetaAds&utm_medium=ADV+-+%5BIG%5D+%5BFB%5D+%5B30%2B%5D+%5BPIEDADE+-+40KM%5D+V%C3%81RIOS&utm_campaign=07.04.2026+%5BV4%5D+%5BWB%5D+%5BLEADS-GRUPO-WHATS%5D+01&utm_content=07.04+%5BIMG%5D+%5BAD04%5D+Pedidos+abertos&utm_term=Facebook_Mobile_Feed&fbclid=IwZXh0bgNhZW0BMABhZGlkAas0bAW7ZytzcnRjBmFwcF9pZAo2NjI4NTY4Mzc5AAEerQJNGaBJ23JQimVZRbE3GlpLIlMPPAHGgb6jVUrVhtOt5ymhJjJGnpVTQlQ_aem_wrcpE4iZ3Ii9Dfe5hc6olg&campaign_id=120247452154580155&ad_id=120247452938090155&utm_id=120247452154580155 | F65: =IFERROR(__xludf.DUMMYFUNCTION("""COMPUTED_VALUE"""),"MetaAds") -> MetaAds | G65: =IFERROR(__xludf.DUMMYFUNCTION("""COMPUTED_VALUE"""),"ADV - [IG] [FB] [30%2B] [PIEDADE - 40KM] V%C3%81RIOS") -> ADV - [IG] [FB] [30%2B] [PIEDADE - 40KM] V%C3%81RIOS | H65: =IFERROR(__xludf.DUMMYFUNCTION("""COMPUTED_VALUE"""),"Facebook_Mobile_Feed") -> Facebook_Mobile_Feed | I65: =IFERROR(__xludf.DUMMYFUNCTION("""COMPUTED_VALUE"""),"07.04 [IMG] [AD04] Pedidos abertos") -> 07.04 [IMG] [AD04] Pedidos abertos | J65: =IFERROR(__xludf.DUMMYFUNCTION("""COMPUTED_VALUE"""),"07.04.2026 [V4] [WB] [LEADS-GRUPO-WHATS] 01") -> 07.04.2026 [V4] [WB] [LEADS-GRUPO-WHATS] 01 | K65: =LEFT(A65,10) -> 2026-04-14 | L65: =DATE(YEAR(SUBSTITUTE(SUBSTITUTE(K65,"-","/",1),"-","/",1)),MONTH(SUBSTITUTE(SUBSTITUTE(K65,"-","/",1),"-","/",1)),DAY(SUBSTITUTE(SUBSTITUTE(K65,"-","/",1),"-","/",1))) -> 46126 | M65: =RIGHT(C65,8) -> 98302019 | N65: =IFERROR(IF(VLOOKUP(M65,'Leads no grupo Saibai'!C:C,1,FALSE)=M65,"Sim"),"Não") -> Sim
A66: 2026-04-14T11:01:28.917Z | B66: Miriam Capelin | C66: 15988215521 | D66: miriam.capelin@gmail.com | E66: https://lp.saibai.com.br/?utm_source=MetaAds&utm_medium=ADV+-+%5BIG%5D+%5BFB%5D+%5B30%2B%5D+%5BPIEDADE+-+40KM%5D+V%C3%81RIOS&utm_campaign=07.04.2026+%5BV4%5D+%5BWB%5D+%5BLEADS-GRUPO-WHATS%5D+01&utm_content=07.04+%5BIMG%5D+%5BAD01%5D+A+safra+come%C3%A7ou&utm_term=Facebook_Mobile_Feed&fbclid=IwZXh0bgNhZW0BMABhZGlkAas0a_chJvtzcnRjBmFwcF9pZAwzNTA2ODU1MzE3MjgAAR4u1jOOOTrZom4SWN0mGr2llfBbfkZ1epcQ3X_gdyrtfwhpquvKx264XH93sA_aem_O5nqCdaRDsb1AMqhlHRUcA&campaign_id=120247452154580155&ad_id=120247452154590155&utm_id=120247452154580155 | F66: =IFERROR(__xludf.DUMMYFUNCTION("""COMPUTED_VALUE"""),"MetaAds") -> MetaAds | G66: =IFERROR(__xludf.DUMMYFUNCTION("""COMPUTED_VALUE"""),"ADV - [IG] [FB] [30%2B] [PIEDADE - 40KM] V%C3%81RIOS") -> ADV - [IG] [FB] [30%2B] [PIEDADE - 40KM] V%C3%81RIOS | H66: =IFERROR(__xludf.DUMMYFUNCTION("""COMPUTED_VALUE"""),"Facebook_Mobile_Feed") -> Facebook_Mobile_Feed | I66: =IFERROR(__xludf.DUMMYFUNCTION("""COMPUTED_VALUE"""),"07.04 [IMG] [AD01] A safra come%C3%A7ou") -> 07.04 [IMG] [AD01] A safra come%C3%A7ou | J66: =IFERROR(__xludf.DUMMYFUNCTION("""COMPUTED_VALUE"""),"07.04.2026 [V4] [WB] [LEADS-GRUPO-WHATS] 01") -> 07.04.2026 [V4] [WB] [LEADS-GRUPO-WHATS] 01 | K66: =LEFT(A66,10) -> 2026-04-14 | L66: =DATE(YEAR(SUBSTITUTE(SUBSTITUTE(K66,"-","/",1),"-","/",1)),MONTH(SUBSTITUTE(SUBSTITUTE(K66,"-","/",1),"-","/",1)),DAY(SUBSTITUTE(SUBSTITUTE(K66,"-","/",1),"-","/",1))) -> 46126 | M66: =RIGHT(C66,8) -> 88215521 | N66: =IFERROR(IF(VLOOKUP(M66,'Leads no grupo Saibai'!C:C,1,FALSE)=M66,"Sim"),"Não") -> Não
A67: 2026-04-14T13:03:39.873Z | B67: JOSE NIVALDO WALTER | C67: 15997425400 | D67: jowalter1967@gmail.com | E67: https://lp.saibai.com.br/?utm_source=google-ads&utm_medium=branding-terms&utm_campaign=venda-direta&utm_term=saibai&utm_content=786538028159&gad_source=1&gad_campaignid=23319194144&gbraid=0AAAAArClr9HvST-AAT2q2FVedMNVp0cW7&gclid=Cj0KCQjwy_fOBhC6ARIsAHKFB7-eTOgvuaDzCme5t4_KANOxAXasL-u4hOgfjLY57DG-eq6nXKWeRXEaAuXvEALw_wcB | F67: =IFERROR(__xludf.DUMMYFUNCTION("""COMPUTED_VALUE"""),"google-ads") -> google-ads | G67: =IFERROR(__xludf.DUMMYFUNCTION("""COMPUTED_VALUE"""),"branding-terms") -> branding-terms | H67: =IFERROR(__xludf.DUMMYFUNCTION("""COMPUTED_VALUE"""),"saibai") -> saibai | I67: =IFERROR(__xludf.DUMMYFUNCTION("""COMPUTED_VALUE"""),"786538028159") -> 786538028159 | J67: =IFERROR(__xludf.DUMMYFUNCTION("""COMPUTED_VALUE"""),"venda-direta") -> venda-direta | K67: =LEFT(A67,10) -> 2026-04-14 | L67: =DATE(YEAR(SUBSTITUTE(SUBSTITUTE(K67,"-","/",1),"-","/",1)),MONTH(SUBSTITUTE(SUBSTITUTE(K67,"-","/",1),"-","/",1)),DAY(SUBSTITUTE(SUBSTITUTE(K67,"-","/",1),"-","/",1))) -> 46126 | M67: =RIGHT(C67,8) -> 97425400 | N67: =IFERROR(IF(VLOOKUP(M67,'Leads no grupo Saibai'!C:C,1,FALSE)=M67,"Sim"),"Não") -> Não
A68: 2026-04-14T14:34:10.508Z | B68: José Rubens Ambrosio | C68: 11964273383 | D68: jr.ambrosio51@terra.com.br | E68: https://lp.saibai.com.br/?utm_source=MetaAds&utm_medium=ADV+-+%5BIG%5D+%5BFB%5D+%5B30%2B%5D+%5BPIEDADE+-+40KM%5D+V%C3%81RIOS&utm_campaign=07.04.2026+%5BV4%5D+%5BWB%5D+%5BLEADS-GRUPO-WHATS%5D+01&utm_content=07.04+%5BIMG%5D+%5BAD04%5D+Pedidos+abertos&utm_term=Facebook_Mobile_Reels&fbclid=IwZXh0bgNhZW0BMABhZGlkAas0bAW7ZytzcnRjBmFwcF9pZAo2NjI4NTY4Mzc5AAEeXWApn53DGPWAZUXZ7PInXIO8NvwN8ghnB-lpg7KjhbDCcEw9S8iVB6WOl68_aem_melm75ihQlVu4C46UVVzgw&campaign_id=120247452154580155&ad_id=120247452938090155&utm_id=120247452154580155 | F68: =IFERROR(__xludf.DUMMYFUNCTION("""COMPUTED_VALUE"""),"MetaAds") -> MetaAds | G68: =IFERROR(__xludf.DUMMYFUNCTION("""COMPUTED_VALUE"""),"ADV - [IG] [FB] [30%2B] [PIEDADE - 40KM] V%C3%81RIOS") -> ADV - [IG] [FB] [30%2B] [PIEDADE - 40KM] V%C3%81RIOS | H68: =IFERROR(__xludf.DUMMYFUNCTION("""COMPUTED_VALUE"""),"Facebook_Mobile_Reels") -> Facebook_Mobile_Reels | I68: =IFERROR(__xludf.DUMMYFUNCTION("""COMPUTED_VALUE"""),"07.04 [IMG] [AD04] Pedidos abertos") -> 07.04 [IMG] [AD04] Pedidos abertos | J68: =IFERROR(__xludf.DUMMYFUNCTION("""COMPUTED_VALUE"""),"07.04.2026 [V4] [WB] [LEADS-GRUPO-WHATS] 01") -> 07.04.2026 [V4] [WB] [LEADS-GRUPO-WHATS] 01 | K68: =LEFT(A68,10) -> 2026-04-14 | L68: =DATE(YEAR(SUBSTITUTE(SUBSTITUTE(K68,"-","/",1),"-","/",1)),MONTH(SUBSTITUTE(SUBSTITUTE(K68,"-","/",1),"-","/",1)),DAY(SUBSTITUTE(SUBSTITUTE(K68,"-","/",1),"-","/",1))) -> 46126 | M68: =RIGHT(C68,8) -> 64273383 | N68: =IFERROR(IF(VLOOKUP(M68,'Leads no grupo Saibai'!C:C,1,FALSE)=M68,"Sim"),"Não") -> Não
A69: 2026-04-14T16:06:30.201Z | B69: Mara Mikami | C69: 15997089265 | D69: maramikami@yahoo.com.br | E69: https://lp.saibai.com.br/?utm_source=MetaAds&utm_medium=ADV+-+%5BIG%5D+%5BFB%5D+%5B30%2B%5D+%5BPIEDADE+-+40KM%5D+V%C3%81RIOS&utm_campaign=07.04.2026+%5BV4%5D+%5BWB%5D+%5BLEADS-GRUPO-WHATS%5D+01&utm_content=07.04+%5BIMG%5D+%5BAD04%5D+Pedidos+abertos&utm_term=Instagram_Stories&utm_id=120247452154580155&fbclid=PAZXh0bgNhZW0BMABhZGlkAas0bAfOj7tzcnRjBmFwcF9pZA81NjcwNjczNDMzNTI0MjcAAaf0wmcdHYgPRGHy8lZaiV-EJdLrIIkSv56drEVhekIfAC3YGaNAzInhtYGtBQ_aem_DLsmoAgXedfkNRdS1HPGfg&campaign_id=120247452154580155&ad_id=120247452938090155 | F69: =IFERROR(__xludf.DUMMYFUNCTION("""COMPUTED_VALUE"""),"MetaAds") -> MetaAds | G69: =IFERROR(__xludf.DUMMYFUNCTION("""COMPUTED_VALUE"""),"ADV - [IG] [FB] [30%2B] [PIEDADE - 40KM] V%C3%81RIOS") -> ADV - [IG] [FB] [30%2B] [PIEDADE - 40KM] V%C3%81RIOS | H69: =IFERROR(__xludf.DUMMYFUNCTION("""COMPUTED_VALUE"""),"Instagram_Stories") -> Instagram_Stories | I69: =IFERROR(__xludf.DUMMYFUNCTION("""COMPUTED_VALUE"""),"07.04 [IMG] [AD04] Pedidos abertos") -> 07.04 [IMG] [AD04] Pedidos abertos | J69: =IFERROR(__xludf.DUMMYFUNCTION("""COMPUTED_VALUE"""),"07.04.2026 [V4] [WB] [LEADS-GRUPO-WHATS] 01") -> 07.04.2026 [V4] [WB] [LEADS-GRUPO-WHATS] 01 | K69: =LEFT(A69,10) -> 2026-04-14 | L69: =DATE(YEAR(SUBSTITUTE(SUBSTITUTE(K69,"-","/",1),"-","/",1)),MONTH(SUBSTITUTE(SUBSTITUTE(K69,"-","/",1),"-","/",1)),DAY(SUBSTITUTE(SUBSTITUTE(K69,"-","/",1),"-","/",1))) -> 46126 | M69: =RIGHT(C69,8) -> 97089265 | N69: =IFERROR(IF(VLOOKUP(M69,'Leads no grupo Saibai'!C:C,1,FALSE)=M69,"Sim"),"Não") -> Sim
A70: 2026-04-14T16:37:53.895Z | B70: Marina Hess | C70: 15997811443 | D70: marina@hugohess.com.br | E70: https://lp.saibai.com.br/?utm_source=MetaAds&utm_medium=ADV+-+%5BIG%5D+%5BFB%5D+%5B30%2B%5D+%5BPIEDADE+-+40KM%5D+V%C3%81RIOS&utm_campaign=07.04.2026+%5BV4%5D+%5BWB%5D+%5BLEADS-GRUPO-WHATS%5D+01&utm_content=07.04+%5BIMG%5D+%5BAD04%5D+Pedidos+abertos&utm_term=Facebook_Mobile_Feed&fbclid=IwZXh0bgNhZW0BMABhZGlkAas0bAW7ZytzcnRjBmFwcF9pZAo2NjI4NTY4Mzc5AAEewHyAxJK4lz5CquXJWPVOibe4ZQiMiq4WgD6vTqhqzJc5dcffjUiAtJC8V3o_aem_nKbdQrcM-dc3ySx3i08AhQ&campaign_id=120247452154580155&ad_id=120247452938090155&utm_id=120247452154580155 | F70: =IFERROR(__xludf.DUMMYFUNCTION("""COMPUTED_VALUE"""),"MetaAds") -> MetaAds | G70: =IFERROR(__xludf.DUMMYFUNCTION("""COMPUTED_VALUE"""),"ADV - [IG] [FB] [30%2B] [PIEDADE - 40KM] V%C3%81RIOS") -> ADV - [IG] [FB] [30%2B] [PIEDADE - 40KM] V%C3%81RIOS | H70: =IFERROR(__xludf.DUMMYFUNCTION("""COMPUTED_VALUE"""),"Facebook_Mobile_Feed") -> Facebook_Mobile_Feed | I70: =IFERROR(__xludf.DUMMYFUNCTION("""COMPUTED_VALUE"""),"07.04 [IMG] [AD04] Pedidos abertos") -> 07.04 [IMG] [AD04] Pedidos abertos | J70: =IFERROR(__xludf.DUMMYFUNCTION("""COMPUTED_VALUE"""),"07.04.2026 [V4] [WB] [LEADS-GRUPO-WHATS] 01") -> 07.04.2026 [V4] [WB] [LEADS-GRUPO-WHATS] 01 | K70: =LEFT(A70,10) -> 2026-04-14 | L70: =DATE(YEAR(SUBSTITUTE(SUBSTITUTE(K70,"-","/",1),"-","/",1)),MONTH(SUBSTITUTE(SUBSTITUTE(K70,"-","/",1),"-","/",1)),DAY(SUBSTITUTE(SUBSTITUTE(K70,"-","/",1),"-","/",1))) -> 46126 | M70: =RIGHT(C70,8) -> 97811443 | N70: =IFERROR(IF(VLOOKUP(M70,'Leads no grupo Saibai'!C:C,1,FALSE)=M70,"Sim"),"Não") -> Sim
A71: 2026-04-14T18:20:46.246Z | B71: Jandaia Nunes | C71: 15991428680 | D71: jandaiamartinsnunes@gmail.com | E71: https://lp.saibai.com.br/?utm_source=MetaAds&utm_medium=ADV+-+%5BIG%5D+%5BFB%5D+%5B30%2B%5D+%5BPIEDADE+-+40KM%5D+V%C3%81RIOS&utm_campaign=07.04.2026+%5BV4%5D+%5BWB%5D+%5BLEADS-GRUPO-WHATS%5D+01&utm_content=07.04+%5BIMG%5D+%5BAD04%5D+Pedidos+abertos&utm_term=Instagram_Feed&utm_id=120247452154580155&fbclid=PAZXh0bgNhZW0BMABhZGlkAas0bAW7ZytzcnRjBmFwcF9pZA8xMjQwMjQ1NzQyODc0MTQAAafnwzYTTRzJ1rO6r3Je1BQQxLaPCqMhyoBYjJ6KUhXTGsRCuYWrTgsrbJJOtg_aem_DGZgdM3R0u7igh1TaRXL9A&campaign_id=120247452154580155&ad_id=120247452938090155 | F71: =IFERROR(__xludf.DUMMYFUNCTION("""COMPUTED_VALUE"""),"MetaAds") -> MetaAds | G71: =IFERROR(__xludf.DUMMYFUNCTION("""COMPUTED_VALUE"""),"ADV - [IG] [FB] [30%2B] [PIEDADE - 40KM] V%C3%81RIOS") -> ADV - [IG] [FB] [30%2B] [PIEDADE - 40KM] V%C3%81RIOS | H71: =IFERROR(__xludf.DUMMYFUNCTION("""COMPUTED_VALUE"""),"Instagram_Feed") -> Instagram_Feed | I71: =IFERROR(__xludf.DUMMYFUNCTION("""COMPUTED_VALUE"""),"07.04 [IMG] [AD04] Pedidos abertos") -> 07.04 [IMG] [AD04] Pedidos abertos | J71: =IFERROR(__xludf.DUMMYFUNCTION("""COMPUTED_VALUE"""),"07.04.2026 [V4] [WB] [LEADS-GRUPO-WHATS] 01") -> 07.04.2026 [V4] [WB] [LEADS-GRUPO-WHATS] 01 | K71: =LEFT(A71,10) -> 2026-04-14 | L71: =DATE(YEAR(SUBSTITUTE(SUBSTITUTE(K71,"-","/",1),"-","/",1)),MONTH(SUBSTITUTE(SUBSTITUTE(K71,"-","/",1),"-","/",1)),DAY(SUBSTITUTE(SUBSTITUTE(K71,"-","/",1),"-","/",1))) -> 46126 | M71: =RIGHT(C71,8) -> 91428680 | N71: =IFERROR(IF(VLOOKUP(M71,'Leads no grupo Saibai'!C:C,1,FALSE)=M71,"Sim"),"Não") -> Sim
A72: 2026-04-14T20:46:24.731Z | B72: Laura Lima | C72: 15998337833 | D72: lauralima5094@gmail.com | E72: https://lp.saibai.com.br/?utm_source=MetaAds&utm_medium=ADV+-+%5BIG%5D+%5BFB%5D+%5B30%2B%5D+%5BPIEDADE+-+40KM%5D+V%C3%81RIOS&utm_campaign=07.04.2026+%5BV4%5D+%5BWB%5D+%5BLEADS-GRUPO-WHATS%5D+01&utm_content=07.04+%5BIMG%5D+%5BAD04%5D+Pedidos+abertos&utm_term=Instagram_Stories&utm_id=120247452154580155&fbclid=PAZXh0bgNhZW0BMABhZGlkAas0bAW7ZytzcnRjBmFwcF9pZA81NjcwNjczNDMzNTI0MjcAAacwFz6Y0xDip9ywb1DobT-HIr8TTOtkLB4wh4KLRzaiV0bKWMoWO5hcUlju_A_aem_QTtv4D7Qs1nTfhLjVbDt-g&campaign_id=120247452154580155&ad_id=120247452938090155 | F72: =IFERROR(__xludf.DUMMYFUNCTION("""COMPUTED_VALUE"""),"MetaAds") -> MetaAds | G72: =IFERROR(__xludf.DUMMYFUNCTION("""COMPUTED_VALUE"""),"ADV - [IG] [FB] [30%2B] [PIEDADE - 40KM] V%C3%81RIOS") -> ADV - [IG] [FB] [30%2B] [PIEDADE - 40KM] V%C3%81RIOS | H72: =IFERROR(__xludf.DUMMYFUNCTION("""COMPUTED_VALUE"""),"Instagram_Stories") -> Instagram_Stories | I72: =IFERROR(__xludf.DUMMYFUNCTION("""COMPUTED_VALUE"""),"07.04 [IMG] [AD04] Pedidos abertos") -> 07.04 [IMG] [AD04] Pedidos abertos | J72: =IFERROR(__xludf.DUMMYFUNCTION("""COMPUTED_VALUE"""),"07.04.2026 [V4] [WB] [LEADS-GRUPO-WHATS] 01") -> 07.04.2026 [V4] [WB] [LEADS-GRUPO-WHATS] 01 | K72: =LEFT(A72,10) -> 2026-04-14 | L72: =DATE(YEAR(SUBSTITUTE(SUBSTITUTE(K72,"-","/",1),"-","/",1)),MONTH(SUBSTITUTE(SUBSTITUTE(K72,"-","/",1),"-","/",1)),DAY(SUBSTITUTE(SUBSTITUTE(K72,"-","/",1),"-","/",1))) -> 46126 | M72: =RIGHT(C72,8) -> 98337833 | N72: =IFERROR(IF(VLOOKUP(M72,'Leads no grupo Saibai'!C:C,1,FALSE)=M72,"Sim"),"Não") -> Sim
A73: 2026-04-14T21:23:59.338Z | B73: Ednea Matiuci | C73: 15997710142 | D73: ednea.iacono@terra.com.br | E73: https://lp.saibai.com.br/?utm_source=MetaAds&utm_medium=ADV+-+%5BIG%5D+%5BFB%5D+%5B30%2B%5D+%5BPIEDADE+-+40KM%5D+V%C3%81RIOS&utm_campaign=07.04.2026+%5BV4%5D+%5BWB%5D+%5BLEADS-GRUPO-WHATS%5D+01&utm_content=07.04+%5BIMG%5D+%5BAD04%5D+Pedidos+abertos&utm_term=Instagram_Feed&utm_id=120247452154580155&fbclid=PAZXh0bgNhZW0BMABhZGlkAas0bAfOj7tzcnRjBmFwcF9pZA81NjcwNjczNDMzNTI0MjcAAafgofO-gOElnf6EG9-HTbB-88BJzDhUG8afcCpCTZAfVz878Cdl9oKFew-_3Q_aem_CP6-y1xzTRniRge5aIs4OA&campaign_id=120247452154580155&ad_id=120247452938090155 | F73: =IFERROR(__xludf.DUMMYFUNCTION("""COMPUTED_VALUE"""),"MetaAds") -> MetaAds | G73: =IFERROR(__xludf.DUMMYFUNCTION("""COMPUTED_VALUE"""),"ADV - [IG] [FB] [30%2B] [PIEDADE - 40KM] V%C3%81RIOS") -> ADV - [IG] [FB] [30%2B] [PIEDADE - 40KM] V%C3%81RIOS | H73: =IFERROR(__xludf.DUMMYFUNCTION("""COMPUTED_VALUE"""),"Instagram_Feed") -> Instagram_Feed | I73: =IFERROR(__xludf.DUMMYFUNCTION("""COMPUTED_VALUE"""),"07.04 [IMG] [AD04] Pedidos abertos") -> 07.04 [IMG] [AD04] Pedidos abertos | J73: =IFERROR(__xludf.DUMMYFUNCTION("""COMPUTED_VALUE"""),"07.04.2026 [V4] [WB] [LEADS-GRUPO-WHATS] 01") -> 07.04.2026 [V4] [WB] [LEADS-GRUPO-WHATS] 01 | K73: =LEFT(A73,10) -> 2026-04-14 | L73: =DATE(YEAR(SUBSTITUTE(SUBSTITUTE(K73,"-","/",1),"-","/",1)),MONTH(SUBSTITUTE(SUBSTITUTE(K73,"-","/",1),"-","/",1)),DAY(SUBSTITUTE(SUBSTITUTE(K73,"-","/",1),"-","/",1))) -> 46126 | M73: =RIGHT(C73,8) -> 97710142 | N73: =IFERROR(IF(VLOOKUP(M73,'Leads no grupo Saibai'!C:C,1,FALSE)=M73,"Sim"),"Não") -> Sim
A74: 2026-04-14T21:54:29.116Z | B74: Vera Aparecida | C74: 15991351222 | D74: veraggonzalez@gmail.com | E74: https://lp.saibai.com.br/?utm_source=MetaAds&utm_medium=ADV+-+%5BIG%5D+%5BFB%5D+%5B30%2B%5D+%5BPIEDADE+-+40KM%5D+V%C3%81RIOS&utm_campaign=07.04.2026+%5BV4%5D+%5BWB%5D+%5BLEADS-GRUPO-WHATS%5D+01&utm_content=07.04+%5BIMG%5D+%5BAD04%5D+Pedidos+abertos&utm_term=Facebook_Mobile_Feed&fbclid=IwZXh0bgNhZW0BMABhZGlkAas0bAfOj7tzcnRjBmFwcF9pZAwzNTA2ODU1MzE3MjgAAR55cjfGr0QRByccS94IpGJk689izEU6Yaxb-s3nUy-gRp7nEHwZN9d7sdxBYg_aem_kTc55bjAhIaltCaAZWfmmg&campaign_id=120247452154580155&ad_id=120247452938090155&utm_id=120247452154580155 | F74: =IFERROR(__xludf.DUMMYFUNCTION("""COMPUTED_VALUE"""),"MetaAds") -> MetaAds | G74: =IFERROR(__xludf.DUMMYFUNCTION("""COMPUTED_VALUE"""),"ADV - [IG] [FB] [30%2B] [PIEDADE - 40KM] V%C3%81RIOS") -> ADV - [IG] [FB] [30%2B] [PIEDADE - 40KM] V%C3%81RIOS | H74: =IFERROR(__xludf.DUMMYFUNCTION("""COMPUTED_VALUE"""),"Facebook_Mobile_Feed") -> Facebook_Mobile_Feed | I74: =IFERROR(__xludf.DUMMYFUNCTION("""COMPUTED_VALUE"""),"07.04 [IMG] [AD04] Pedidos abertos") -> 07.04 [IMG] [AD04] Pedidos abertos | J74: =IFERROR(__xludf.DUMMYFUNCTION("""COMPUTED_VALUE"""),"07.04.2026 [V4] [WB] [LEADS-GRUPO-WHATS] 01") -> 07.04.2026 [V4] [WB] [LEADS-GRUPO-WHATS] 01 | K74: =LEFT(A74,10) -> 2026-04-14 | L74: =DATE(YEAR(SUBSTITUTE(SUBSTITUTE(K74,"-","/",1),"-","/",1)),MONTH(SUBSTITUTE(SUBSTITUTE(K74,"-","/",1),"-","/",1)),DAY(SUBSTITUTE(SUBSTITUTE(K74,"-","/",1),"-","/",1))) -> 46126 | M74: =RIGHT(C74,8) -> 91351222 | N74: =IFERROR(IF(VLOOKUP(M74,'Leads no grupo Saibai'!C:C,1,FALSE)=M74,"Sim"),"Não") -> Sim
A75: 2026-04-14T23:59:09.522Z | B75: Douglas Pereira | C75: 11983402086 | D75: douglas_2304@hotmail.com | E75: https://lp.saibai.com.br/?utm_source=MetaAds&utm_medium=ADV+-+%5BIG%5D+%5BFB%5D+%5B30%2B%5D+%5BPIEDADE+-+40KM%5D+V%C3%81RIOS&utm_campaign=07.04.2026+%5BV4%5D+%5BWB%5D+%5BLEADS-GRUPO-WHATS%5D+01&utm_content=07.04+%5BIMG%5D+%5BAD04%5D+Pedidos+abertos&utm_term=Instagram_Feed&utm_id=120247452154580155&fbclid=PAZXh0bgNhZW0BMABhZGlkAas0bAW7ZytzcnRjBmFwcF9pZA81NjcwNjczNDMzNTI0MjcAAacYEfUQ8yrgI5i2AdpEIiZJJTy7ixWHZMMxMZ2hBlaUg_EX_xo7KGHPD--iOA_aem_ac6IWjUJWVN4nxMrqNXuMA&campaign_id=120247452154580155&ad_id=120247452938090155 | F75: =IFERROR(__xludf.DUMMYFUNCTION("""COMPUTED_VALUE"""),"MetaAds") -> MetaAds | G75: =IFERROR(__xludf.DUMMYFUNCTION("""COMPUTED_VALUE"""),"ADV - [IG] [FB] [30%2B] [PIEDADE - 40KM] V%C3%81RIOS") -> ADV - [IG] [FB] [30%2B] [PIEDADE - 40KM] V%C3%81RIOS | H75: =IFERROR(__xludf.DUMMYFUNCTION("""COMPUTED_VALUE"""),"Instagram_Feed") -> Instagram_Feed | I75: =IFERROR(__xludf.DUMMYFUNCTION("""COMPUTED_VALUE"""),"07.04 [IMG] [AD04] Pedidos abertos") -> 07.04 [IMG] [AD04] Pedidos abertos | J75: =IFERROR(__xludf.DUMMYFUNCTION("""COMPUTED_VALUE"""),"07.04.2026 [V4] [WB] [LEADS-GRUPO-WHATS] 01") -> 07.04.2026 [V4] [WB] [LEADS-GRUPO-WHATS] 01 | K75: =LEFT(A75,10) -> 2026-04-14 | L75: =DATE(YEAR(SUBSTITUTE(SUBSTITUTE(K75,"-","/",1),"-","/",1)),MONTH(SUBSTITUTE(SUBSTITUTE(K75,"-","/",1),"-","/",1)),DAY(SUBSTITUTE(SUBSTITUTE(K75,"-","/",1),"-","/",1))) -> 46126 | M75: =RIGHT(C75,8) -> 83402086 | N75: =IFERROR(IF(VLOOKUP(M75,'Leads no grupo Saibai'!C:C,1,FALSE)=M75,"Sim"),"Não") -> Sim
A76: 2026-04-15T01:34:45.638Z | B76: Lucilene Schleetz | C76: 15998047496 | D76: lschleetz@hotmail.com | E76: https://lp.saibai.com.br/?utm_source=MetaAds&utm_medium=ADV+-+%5BIG%5D+%5BFB%5D+%5B30%2B%5D+%5BPIEDADE+-+40KM%5D+V%C3%81RIOS&utm_campaign=07.04.2026+%5BV4%5D+%5BWB%5D+%5BLEADS-GRUPO-WHATS%5D+01&utm_content=07.04+%5BIMG%5D+%5BAD04%5D+Pedidos+abertos&utm_term=Facebook_Mobile_Feed&fbclid=IwZXh0bgNhZW0BMABhZGlkAas0bAW7ZytzcnRjBmFwcF9pZAo2NjI4NTY4Mzc5AAEeyCr_7Fy4HPsUjad5nVN3IZvkX0iFDb--fntI2zeSHuSneN6Q7l4KPcM4Ed0_aem_EehaTSCd3kY_8rZ3CN5PGw&campaign_id=120247452154580155&ad_id=120247452938090155&utm_id=120247452154580155 | F76: =IFERROR(__xludf.DUMMYFUNCTION("""COMPUTED_VALUE"""),"MetaAds") -> MetaAds | G76: =IFERROR(__xludf.DUMMYFUNCTION("""COMPUTED_VALUE"""),"ADV - [IG] [FB] [30%2B] [PIEDADE - 40KM] V%C3%81RIOS") -> ADV - [IG] [FB] [30%2B] [PIEDADE - 40KM] V%C3%81RIOS | H76: =IFERROR(__xludf.DUMMYFUNCTION("""COMPUTED_VALUE"""),"Facebook_Mobile_Feed") -> Facebook_Mobile_Feed | I76: =IFERROR(__xludf.DUMMYFUNCTION("""COMPUTED_VALUE"""),"07.04 [IMG] [AD04] Pedidos abertos") -> 07.04 [IMG] [AD04] Pedidos abertos | J76: =IFERROR(__xludf.DUMMYFUNCTION("""COMPUTED_VALUE"""),"07.04.2026 [V4] [WB] [LEADS-GRUPO-WHATS] 01") -> 07.04.2026 [V4] [WB] [LEADS-GRUPO-WHATS] 01 | K76: =LEFT(A76,10) -> 2026-04-15 | L76: =DATE(YEAR(SUBSTITUTE(SUBSTITUTE(K76,"-","/",1),"-","/",1)),MONTH(SUBSTITUTE(SUBSTITUTE(K76,"-","/",1),"-","/",1)),DAY(SUBSTITUTE(SUBSTITUTE(K76,"-","/",1),"-","/",1))) -> 46127 | M76: =RIGHT(C76,8) -> 98047496 | N76: =IFERROR(IF(VLOOKUP(M76,'Leads no grupo Saibai'!C:C,1,FALSE)=M76,"Sim"),"Não") -> Sim
A77: 2026-04-15T01:46:29.038Z | B77: Marisol Masedo | C77: 15997474704 | D77: marisol.masedo13@gmail.com | E77: https://lp.saibai.com.br/?utm_source=MetaAds&utm_medium=ADV+-+%5BIG%5D+%5BFB%5D+%5B30%2B%5D+%5BPIEDADE+-+40KM%5D+V%C3%81RIOS&utm_campaign=07.04.2026+%5BV4%5D+%5BWB%5D+%5BLEADS-GRUPO-WHATS%5D+01&utm_content=07.04+%5BIMG%5D+%5BAD04%5D+Pedidos+abertos&utm_term=Instagram_Stories&utm_id=120247452154580155&fbclid=PAZXh0bgNhZW0BMABhZGlkAas0bAW7ZytzcnRjBmFwcF9pZA81NjcwNjczNDMzNTI0MjcAAadMv9p9gh3dewyfMy3V81zcWJqDbkRmrIc4n9UNgehO3PqEs7mrLdsgoZnpXw_aem_HyECITGkIk5dPdULEMC68g&campaign_id=120247452154580155&ad_id=120247452938090155 | F77: =IFERROR(__xludf.DUMMYFUNCTION("""COMPUTED_VALUE"""),"MetaAds") -> MetaAds | G77: =IFERROR(__xludf.DUMMYFUNCTION("""COMPUTED_VALUE"""),"ADV - [IG] [FB] [30%2B] [PIEDADE - 40KM] V%C3%81RIOS") -> ADV - [IG] [FB] [30%2B] [PIEDADE - 40KM] V%C3%81RIOS | H77: =IFERROR(__xludf.DUMMYFUNCTION("""COMPUTED_VALUE"""),"Instagram_Stories") -> Instagram_Stories | I77: =IFERROR(__xludf.DUMMYFUNCTION("""COMPUTED_VALUE"""),"07.04 [IMG] [AD04] Pedidos abertos") -> 07.04 [IMG] [AD04] Pedidos abertos | J77: =IFERROR(__xludf.DUMMYFUNCTION("""COMPUTED_VALUE"""),"07.04.2026 [V4] [WB] [LEADS-GRUPO-WHATS] 01") -> 07.04.2026 [V4] [WB] [LEADS-GRUPO-WHATS] 01 | K77: =LEFT(A77,10) -> 2026-04-15 | L77: =DATE(YEAR(SUBSTITUTE(SUBSTITUTE(K77,"-","/",1),"-","/",1)),MONTH(SUBSTITUTE(SUBSTITUTE(K77,"-","/",1),"-","/",1)),DAY(SUBSTITUTE(SUBSTITUTE(K77,"-","/",1),"-","/",1))) -> 46127 | M77: =RIGHT(C77,8) -> 97474704 | N77: =IFERROR(IF(VLOOKUP(M77,'Leads no grupo Saibai'!C:C,1,FALSE)=M77,"Sim"),"Não") -> Sim
A78: 2026-04-15T02:36:02.604Z | B78: Cintia Souza Massucatto | C78: 11950501768 | D78: cintiasouzamassucatto@gmail.com | E78: https://lp.saibai.com.br/?utm_source=MetaAds&utm_medium=ADV+-+%5BIG%5D+%5BFB%5D+%5B30%2B%5D+%5BPIEDADE+-+40KM%5D+V%C3%81RIOS&utm_campaign=07.04.2026+%5BV4%5D+%5BWB%5D+%5BLEADS-GRUPO-WHATS%5D+01&utm_content=07.04+%5BIMG%5D+%5BAD01%5D+A+safra+come%C3%A7ou&utm_term=Instagram_Feed&utm_id=120247452154580155&fbclid=PAZXh0bgNhZW0BMABhZGlkAas0a_chJvtzcnRjBmFwcF9pZA81NjcwNjczNDMzNTI0MjcAAad7h9cmEyMPPcKDt4bMofwuhNETFoIci_-U5p_5GCZZOCDvuWtpY1MJk__Stg_aem_ACtlyqU0Ds6QV7TpXlPv_Q&campaign_id=120247452154580155&ad_id=120247452154590155 | F78: =IFERROR(__xludf.DUMMYFUNCTION("""COMPUTED_VALUE"""),"MetaAds") -> MetaAds | G78: =IFERROR(__xludf.DUMMYFUNCTION("""COMPUTED_VALUE"""),"ADV - [IG] [FB] [30%2B] [PIEDADE - 40KM] V%C3%81RIOS") -> ADV - [IG] [FB] [30%2B] [PIEDADE - 40KM] V%C3%81RIOS | H78: =IFERROR(__xludf.DUMMYFUNCTION("""COMPUTED_VALUE"""),"Instagram_Feed") -> Instagram_Feed | I78: =IFERROR(__xludf.DUMMYFUNCTION("""COMPUTED_VALUE"""),"07.04 [IMG] [AD01] A safra come%C3%A7ou") -> 07.04 [IMG] [AD01] A safra come%C3%A7ou | J78: =IFERROR(__xludf.DUMMYFUNCTION("""COMPUTED_VALUE"""),"07.04.2026 [V4] [WB] [LEADS-GRUPO-WHATS] 01") -> 07.04.2026 [V4] [WB] [LEADS-GRUPO-WHATS] 01 | K78: =LEFT(A78,10) -> 2026-04-15 | L78: =DATE(YEAR(SUBSTITUTE(SUBSTITUTE(K78,"-","/",1),"-","/",1)),MONTH(SUBSTITUTE(SUBSTITUTE(K78,"-","/",1),"-","/",1)),DAY(SUBSTITUTE(SUBSTITUTE(K78,"-","/",1),"-","/",1))) -> 46127 | M78: =RIGHT(C78,8) -> 50501768 | N78: =IFERROR(IF(VLOOKUP(M78,'Leads no grupo Saibai'!C:C,1,FALSE)=M78,"Sim"),"Não") -> Sim
A79: 2026-04-15T03:57:19.247Z | B79: Vera Sorrentino | C79: 15991079288 | D79: verasorrentino@yahoo.com.br | E79: https://lp.saibai.com.br/?utm_source=MetaAds&utm_medium=ADV+-+%5BIG%5D+%5BFB%5D+%5B30%2B%5D+%5BPIEDADE+-+40KM%5D+V%C3%81RIOS&utm_campaign=07.04.2026+%5BV4%5D+%5BWB%5D+%5BLEADS-GRUPO-WHATS%5D+01&utm_content=07.04+%5BIMG%5D+%5BAD01%5D+A+safra+come%C3%A7ou&utm_term=Instagram_Feed&utm_id=120247452154580155&fbclid=PAZXh0bgNhZW0BMABhZGlkAas0a_chJvtzcnRjBmFwcF9pZA8xMjQwMjQ1NzQyODc0MTQAAadkwZfgLBTf27aueBE-Q3dSkUyYqjjBU_0_FEV1uE1QsQYIxjvUEJ_f8UknNw_aem_fBr295wtdPb0KlV9xXcjMQ&campaign_id=120247452154580155&ad_id=120247452154590155 | F79: =IFERROR(__xludf.DUMMYFUNCTION("""COMPUTED_VALUE"""),"MetaAds") -> MetaAds | G79: =IFERROR(__xludf.DUMMYFUNCTION("""COMPUTED_VALUE"""),"ADV - [IG] [FB] [30%2B] [PIEDADE - 40KM] V%C3%81RIOS") -> ADV - [IG] [FB] [30%2B] [PIEDADE - 40KM] V%C3%81RIOS | H79: =IFERROR(__xludf.DUMMYFUNCTION("""COMPUTED_VALUE"""),"Instagram_Feed") -> Instagram_Feed | I79: =IFERROR(__xludf.DUMMYFUNCTION("""COMPUTED_VALUE"""),"07.04 [IMG] [AD01] A safra come%C3%A7ou") -> 07.04 [IMG] [AD01] A safra come%C3%A7ou | J79: =IFERROR(__xludf.DUMMYFUNCTION("""COMPUTED_VALUE"""),"07.04.2026 [V4] [WB] [LEADS-GRUPO-WHATS] 01") -> 07.04.2026 [V4] [WB] [LEADS-GRUPO-WHATS] 01 | K79: =LEFT(A79,10) -> 2026-04-15 | L79: =DATE(YEAR(SUBSTITUTE(SUBSTITUTE(K79,"-","/",1),"-","/",1)),MONTH(SUBSTITUTE(SUBSTITUTE(K79,"-","/",1),"-","/",1)),DAY(SUBSTITUTE(SUBSTITUTE(K79,"-","/",1),"-","/",1))) -> 46127 | M79: =RIGHT(C79,8) -> 91079288 | N79: =IFERROR(IF(VLOOKUP(M79,'Leads no grupo Saibai'!C:C,1,FALSE)=M79,"Sim"),"Não") -> Sim
A80: 2026-04-15T09:19:11.653Z | B80: Eduardo Mariucci | C80: 11991517194 | D80: dumariucci@gmail.com | E80: https://lp.saibai.com.br/?utm_source=MetaAds&utm_medium=ADV+-+%5BIG%5D+%5BFB%5D+%5B30%2B%5D+%5BPIEDADE+-+40KM%5D+V%C3%81RIOS&utm_campaign=07.04.2026+%5BV4%5D+%5BWB%5D+%5BLEADS-GRUPO-WHATS%5D+01&utm_content=07.04+%5BIMG%5D+%5BAD01%5D+A+safra+come%C3%A7ou&utm_term=Instagram_Reels&utm_id=120247452154580155&fbclid=PAZXh0bgNhZW0BMABhZGlkAas0a_chJvtzcnRjBmFwcF9pZA81NjcwNjczNDMzNTI0MjcAAacwvg1L2mHdSlpDRiNa_eT3N3g1z3feccGVxqqSqmLKsWJNE4KBADkmjNHTaw_aem_2mqxEC6gZsasyNI1zlecqA&campaign_id=120247452154580155&ad_id=120247452154590155 | F80: =IFERROR(__xludf.DUMMYFUNCTION("""COMPUTED_VALUE"""),"MetaAds") -> MetaAds | G80: =IFERROR(__xludf.DUMMYFUNCTION("""COMPUTED_VALUE"""),"ADV - [IG] [FB] [30%2B] [PIEDADE - 40KM] V%C3%81RIOS") -> ADV - [IG] [FB] [30%2B] [PIEDADE - 40KM] V%C3%81RIOS | H80: =IFERROR(__xludf.DUMMYFUNCTION("""COMPUTED_VALUE"""),"Instagram_Reels") -> Instagram_Reels | I80: =IFERROR(__xludf.DUMMYFUNCTION("""COMPUTED_VALUE"""),"07.04 [IMG] [AD01] A safra come%C3%A7ou") -> 07.04 [IMG] [AD01] A safra come%C3%A7ou | J80: =IFERROR(__xludf.DUMMYFUNCTION("""COMPUTED_VALUE"""),"07.04.2026 [V4] [WB] [LEADS-GRUPO-WHATS] 01") -> 07.04.2026 [V4] [WB] [LEADS-GRUPO-WHATS] 01 | K80: =LEFT(A80,10) -> 2026-04-15 | L80: =DATE(YEAR(SUBSTITUTE(SUBSTITUTE(K80,"-","/",1),"-","/",1)),MONTH(SUBSTITUTE(SUBSTITUTE(K80,"-","/",1),"-","/",1)),DAY(SUBSTITUTE(SUBSTITUTE(K80,"-","/",1),"-","/",1))) -> 46127 | M80: =RIGHT(C80,8) -> 91517194 | N80: =IFERROR(IF(VLOOKUP(M80,'Leads no grupo Saibai'!C:C,1,FALSE)=M80,"Sim"),"Não") -> Sim
A81: 2026-04-15T09:38:54.361Z | B81: Mariangela Botelho | C81: 11981274041 | D81: marianforte@gmail.com | E81: https://lp.saibai.com.br/?utm_source=MetaAds&utm_medium=ADV+-+%5BIG%5D+%5BFB%5D+%5B30%2B%5D+%5BPIEDADE+-+40KM%5D+V%C3%81RIOS&utm_campaign=07.04.2026+%5BV4%5D+%5BWB%5D+%5BLEADS-GRUPO-WHATS%5D+01&utm_content=07.04+%5BIMG%5D+%5BAD01%5D+A+safra+come%C3%A7ou&utm_term=Instagram_Stories&utm_id=120247452154580155&fbclid=PAZXh0bgNhZW0BMABhZGlkAas0a_chJvtzcnRjBmFwcF9pZA81NjcwNjczNDMzNTI0MjcAAaeZTbBtI_OZFij3b6bMqRAGfcOXq57RHCQ0X84AbvJjsH6iJm-kBKsZPSZ7YA_aem_8IRldGXI_ZjmFS1k0pSyLg&campaign_id=120247452154580155&ad_id=120247452154590155 | F81: =IFERROR(__xludf.DUMMYFUNCTION("""COMPUTED_VALUE"""),"MetaAds") -> MetaAds | G81: =IFERROR(__xludf.DUMMYFUNCTION("""COMPUTED_VALUE"""),"ADV - [IG] [FB] [30%2B] [PIEDADE - 40KM] V%C3%81RIOS") -> ADV - [IG] [FB] [30%2B] [PIEDADE - 40KM] V%C3%81RIOS | H81: =IFERROR(__xludf.DUMMYFUNCTION("""COMPUTED_VALUE"""),"Instagram_Stories") -> Instagram_Stories | I81: =IFERROR(__xludf.DUMMYFUNCTION("""COMPUTED_VALUE"""),"07.04 [IMG] [AD01] A safra come%C3%A7ou") -> 07.04 [IMG] [AD01] A safra come%C3%A7ou | J81: =IFERROR(__xludf.DUMMYFUNCTION("""COMPUTED_VALUE"""),"07.04.2026 [V4] [WB] [LEADS-GRUPO-WHATS] 01") -> 07.04.2026 [V4] [WB] [LEADS-GRUPO-WHATS] 01 | K81: =LEFT(A81,10) -> 2026-04-15 | L81: =DATE(YEAR(SUBSTITUTE(SUBSTITUTE(K81,"-","/",1),"-","/",1)),MONTH(SUBSTITUTE(SUBSTITUTE(K81,"-","/",1),"-","/",1)),DAY(SUBSTITUTE(SUBSTITUTE(K81,"-","/",1),"-","/",1))) -> 46127 | M81: =RIGHT(C81,8) -> 81274041 | N81: =IFERROR(IF(VLOOKUP(M81,'Leads no grupo Saibai'!C:C,1,FALSE)=M81,"Sim"),"Não") -> Sim
A82: 2026-04-15T09:58:32.294Z | B82: Valdir Calió Rolino | C82: 15981298820 | D82: valdirrolino@gmail.com | E82: https://lp.saibai.com.br/?utm_source=MetaAds&utm_medium=ADV+-+%5BIG%5D+%5BFB%5D+%5B30%2B%5D+%5BPIEDADE+-+40KM%5D+V%C3%81RIOS&utm_campaign=07.04.2026+%5BV4%5D+%5BWB%5D+%5BLEADS-GRUPO-WHATS%5D+01&utm_content=07.04+%5BIMG%5D+%5BAD01%5D+A+safra+come%C3%A7ou&utm_term=Instagram_Reels&utm_id=120247452154580155&fbclid=PAZXh0bgNhZW0BMABhZGlkAas0a_chJvtzcnRjBmFwcF9pZA81NjcwNjczNDMzNTI0MjcAAacbr7KsffG4OHO2l5m7wFRif-LUSHbM5mg_T4wS0PMabj4CedkVLQ-i1NUpPw_aem_yzwjfrurTfLgWCn-YsQOsw&campaign_id=120247452154580155&ad_id=120247452154590155 | F82: =IFERROR(__xludf.DUMMYFUNCTION("""COMPUTED_VALUE"""),"MetaAds") -> MetaAds | G82: =IFERROR(__xludf.DUMMYFUNCTION("""COMPUTED_VALUE"""),"ADV - [IG] [FB] [30%2B] [PIEDADE - 40KM] V%C3%81RIOS") -> ADV - [IG] [FB] [30%2B] [PIEDADE - 40KM] V%C3%81RIOS | H82: =IFERROR(__xludf.DUMMYFUNCTION("""COMPUTED_VALUE"""),"Instagram_Reels") -> Instagram_Reels | I82: =IFERROR(__xludf.DUMMYFUNCTION("""COMPUTED_VALUE"""),"07.04 [IMG] [AD01] A safra come%C3%A7ou") -> 07.04 [IMG] [AD01] A safra come%C3%A7ou | J82: =IFERROR(__xludf.DUMMYFUNCTION("""COMPUTED_VALUE"""),"07.04.2026 [V4] [WB] [LEADS-GRUPO-WHATS] 01") -> 07.04.2026 [V4] [WB] [LEADS-GRUPO-WHATS] 01 | K82: =LEFT(A82,10) -> 2026-04-15 | L82: =DATE(YEAR(SUBSTITUTE(SUBSTITUTE(K82,"-","/",1),"-","/",1)),MONTH(SUBSTITUTE(SUBSTITUTE(K82,"-","/",1),"-","/",1)),DAY(SUBSTITUTE(SUBSTITUTE(K82,"-","/",1),"-","/",1))) -> 46127 | M82: =RIGHT(C82,8) -> 81298820 | N82: =IFERROR(IF(VLOOKUP(M82,'Leads no grupo Saibai'!C:C,1,FALSE)=M82,"Sim"),"Não") -> Sim
A83: 2026-04-15T10:41:26.206Z | B83: Leny Ruocco Ruocco | C83: 11999495893 | D83: lenyruocco@hotmail.com | E83: https://lp.saibai.com.br/?utm_source=MetaAds&utm_medium=ADV+-+%5BIG%5D+%5BFB%5D+%5B30%2B%5D+%5BPIEDADE+-+40KM%5D+V%C3%81RIOS&utm_campaign=07.04.2026+%5BV4%5D+%5BWB%5D+%5BLEADS-GRUPO-WHATS%5D+01&utm_content=07.04+%5BIMG%5D+%5BAD01%5D+A+safra+come%C3%A7ou&utm_term=Facebook_Stories&fbclid=IwZXh0bgNhZW0BMABhZGlkAas0a_chJvtzcnRjBmFwcF9pZAo2NjI4NTY4Mzc5AAEeRkl772lZ3QbAI8VhHR4Yv8e99IMtHsPvfZVapiW_Vjsjv57SPLANDpCx530_aem_O-vwG9kHcY7D3zOBCtgf_A&campaign_id=120247452154580155&ad_id=120247452154590155&utm_id=120247452154580155 | F83: =IFERROR(__xludf.DUMMYFUNCTION("""COMPUTED_VALUE"""),"MetaAds") -> MetaAds | G83: =IFERROR(__xludf.DUMMYFUNCTION("""COMPUTED_VALUE"""),"ADV - [IG] [FB] [30%2B] [PIEDADE - 40KM] V%C3%81RIOS") -> ADV - [IG] [FB] [30%2B] [PIEDADE - 40KM] V%C3%81RIOS | H83: =IFERROR(__xludf.DUMMYFUNCTION("""COMPUTED_VALUE"""),"Facebook_Stories") -> Facebook_Stories | I83: =IFERROR(__xludf.DUMMYFUNCTION("""COMPUTED_VALUE"""),"07.04 [IMG] [AD01] A safra come%C3%A7ou") -> 07.04 [IMG] [AD01] A safra come%C3%A7ou | J83: =IFERROR(__xludf.DUMMYFUNCTION("""COMPUTED_VALUE"""),"07.04.2026 [V4] [WB] [LEADS-GRUPO-WHATS] 01") -> 07.04.2026 [V4] [WB] [LEADS-GRUPO-WHATS] 01 | K83: =LEFT(A83,10) -> 2026-04-15 | L83: =DATE(YEAR(SUBSTITUTE(SUBSTITUTE(K83,"-","/",1),"-","/",1)),MONTH(SUBSTITUTE(SUBSTITUTE(K83,"-","/",1),"-","/",1)),DAY(SUBSTITUTE(SUBSTITUTE(K83,"-","/",1),"-","/",1))) -> 46127 | M83: =RIGHT(C83,8) -> 99495893 | N83: =IFERROR(IF(VLOOKUP(M83,'Leads no grupo Saibai'!C:C,1,FALSE)=M83,"Sim"),"Não") -> Sim
A84: 2026-04-15T11:16:40.972Z | B84: Rosemeire Mazitelli | C84: 11975424567 | D84: rosemazitelli1956@gmail.com | E84: https://lp.saibai.com.br/?utm_source=MetaAds&utm_medium=ADV+-+%5BIG%5D+%5BFB%5D+%5B30%2B%5D+%5BPIEDADE+-+40KM%5D+V%C3%81RIOS&utm_campaign=07.04.2026+%5BV4%5D+%5BWB%5D+%5BLEADS-GRUPO-WHATS%5D+01&utm_content=07.04+%5BIMG%5D+%5BAD01%5D+A+safra+come%C3%A7ou&utm_term=Instagram_Feed&utm_id=120247452154580155&fbclid=PAZXh0bgNhZW0BMABhZGlkAas0a_chJvtzcnRjBmFwcF9pZA8xMjQwMjQ1NzQyODc0MTQAAadPzH6ltltSWldvAoin0S6Rc6acxjN2nsrxSyUHfKSQoE71GJriOj2GzED5xw_aem_IcP1Ibzh8BDpyWAtvYR0CA&campaign_id=120247452154580155&ad_id=120247452154590155 | F84: =IFERROR(__xludf.DUMMYFUNCTION("""COMPUTED_VALUE"""),"MetaAds") -> MetaAds | G84: =IFERROR(__xludf.DUMMYFUNCTION("""COMPUTED_VALUE"""),"ADV - [IG] [FB] [30%2B] [PIEDADE - 40KM] V%C3%81RIOS") -> ADV - [IG] [FB] [30%2B] [PIEDADE - 40KM] V%C3%81RIOS | H84: =IFERROR(__xludf.DUMMYFUNCTION("""COMPUTED_VALUE"""),"Instagram_Feed") -> Instagram_Feed | I84: =IFERROR(__xludf.DUMMYFUNCTION("""COMPUTED_VALUE"""),"07.04 [IMG] [AD01] A safra come%C3%A7ou") -> 07.04 [IMG] [AD01] A safra come%C3%A7ou | J84: =IFERROR(__xludf.DUMMYFUNCTION("""COMPUTED_VALUE"""),"07.04.2026 [V4] [WB] [LEADS-GRUPO-WHATS] 01") -> 07.04.2026 [V4] [WB] [LEADS-GRUPO-WHATS] 01 | K84: =LEFT(A84,10) -> 2026-04-15 | L84: =DATE(YEAR(SUBSTITUTE(SUBSTITUTE(K84,"-","/",1),"-","/",1)),MONTH(SUBSTITUTE(SUBSTITUTE(K84,"-","/",1),"-","/",1)),DAY(SUBSTITUTE(SUBSTITUTE(K84,"-","/",1),"-","/",1))) -> 46127 | M84: =RIGHT(C84,8) -> 75424567 | N84: =IFERROR(IF(VLOOKUP(M84,'Leads no grupo Saibai'!C:C,1,FALSE)=M84,"Sim"),"Não") -> Sim
A85: 2026-04-15T11:43:29.527Z | B85: Paula Mason Mason | C85: 11982941210 | D85: paulacristiney@gmail.com | E85: https://lp.saibai.com.br/?utm_source=MetaAds&utm_medium=ADV+-+%5BIG%5D+%5BFB%5D+%5B30%2B%5D+%5BPIEDADE+-+40KM%5D+V%C3%81RIOS&utm_campaign=07.04.2026+%5BV4%5D+%5BWB%5D+%5BLEADS-GRUPO-WHATS%5D+01&utm_content=07.04+%5BIMG%5D+%5BAD01%5D+A+safra+come%C3%A7ou&utm_term=Instagram_Feed&utm_id=120247452154580155&fbclid=PAZXh0bgNhZW0BMABhZGlkAas0a_chJvtzcnRjBmFwcF9pZA8xMjQwMjQ1NzQyODc0MTQAAacETyTRKNyJBz6meccYZ2ZlgmYPH1USnsFerEM8QWvDkfXvQTuuBzB6FI_ZnA_aem_kzjzUSzwegZlk7Uq0_RdSQ&campaign_id=120247452154580155&ad_id=120247452154590155 | F85: =IFERROR(__xludf.DUMMYFUNCTION("""COMPUTED_VALUE"""),"MetaAds") -> MetaAds | G85: =IFERROR(__xludf.DUMMYFUNCTION("""COMPUTED_VALUE"""),"ADV - [IG] [FB] [30%2B] [PIEDADE - 40KM] V%C3%81RIOS") -> ADV - [IG] [FB] [30%2B] [PIEDADE - 40KM] V%C3%81RIOS | H85: =IFERROR(__xludf.DUMMYFUNCTION("""COMPUTED_VALUE"""),"Instagram_Feed") -> Instagram_Feed | I85: =IFERROR(__xludf.DUMMYFUNCTION("""COMPUTED_VALUE"""),"07.04 [IMG] [AD01] A safra come%C3%A7ou") -> 07.04 [IMG] [AD01] A safra come%C3%A7ou | J85: =IFERROR(__xludf.DUMMYFUNCTION("""COMPUTED_VALUE"""),"07.04.2026 [V4] [WB] [LEADS-GRUPO-WHATS] 01") -> 07.04.2026 [V4] [WB] [LEADS-GRUPO-WHATS] 01 | K85: =LEFT(A85,10) -> 2026-04-15 | L85: =DATE(YEAR(SUBSTITUTE(SUBSTITUTE(K85,"-","/",1),"-","/",1)),MONTH(SUBSTITUTE(SUBSTITUTE(K85,"-","/",1),"-","/",1)),DAY(SUBSTITUTE(SUBSTITUTE(K85,"-","/",1),"-","/",1))) -> 46127 | M85: =RIGHT(C85,8) -> 82941210 | N85: =IFERROR(IF(VLOOKUP(M85,'Leads no grupo Saibai'!C:C,1,FALSE)=M85,"Sim"),"Não") -> Sim
A86: 2026-04-15T15:15:30.779Z | B86: Magali Zampieri | C86: 15997717274 | D86: mzampieri@pucsp.br | E86: https://lp.saibai.com.br/?utm_source=MetaAds&utm_medium=ADV+-+%5BIG%5D+%5BFB%5D+%5B30%2B%5D+%5BPIEDADE+-+40KM%5D+V%C3%81RIOS&utm_campaign=07.04.2026+%5BV4%5D+%5BWB%5D+%5BLEADS-GRUPO-WHATS%5D+01&utm_content=07.04+%5BIMG%5D+%5BAD04%5D+Pedidos+abertos&utm_term=Instagram_Feed&utm_id=120247452154580155&fbclid=PAZXh0bgNhZW0BMABhZGlkAas0a_lii3tzcnRjBmFwcF9pZA81NjcwNjczNDMzNTI0MjcAAadfiusuYMKofOgpz9KrPGQs2I-dczM2o_t6fAqbYu44Rss7i1Gy_ssD-eBpoA_aem_8FNCdPn_RrwlzmXtJzlm-Q&campaign_id=120247452154580155&ad_id=120247452938090155 | F86: =IFERROR(__xludf.DUMMYFUNCTION("""COMPUTED_VALUE"""),"MetaAds") -> MetaAds | G86: =IFERROR(__xludf.DUMMYFUNCTION("""COMPUTED_VALUE"""),"ADV - [IG] [FB] [30%2B] [PIEDADE - 40KM] V%C3%81RIOS") -> ADV - [IG] [FB] [30%2B] [PIEDADE - 40KM] V%C3%81RIOS | H86: =IFERROR(__xludf.DUMMYFUNCTION("""COMPUTED_VALUE"""),"Instagram_Feed") -> Instagram_Feed | I86: =IFERROR(__xludf.DUMMYFUNCTION("""COMPUTED_VALUE"""),"07.04 [IMG] [AD04] Pedidos abertos") -> 07.04 [IMG] [AD04] Pedidos abertos | J86: =IFERROR(__xludf.DUMMYFUNCTION("""COMPUTED_VALUE"""),"07.04.2026 [V4] [WB] [LEADS-GRUPO-WHATS] 01") -> 07.04.2026 [V4] [WB] [LEADS-GRUPO-WHATS] 01 | K86: =LEFT(A86,10) -> 2026-04-15 | L86: =DATE(YEAR(SUBSTITUTE(SUBSTITUTE(K86,"-","/",1),"-","/",1)),MONTH(SUBSTITUTE(SUBSTITUTE(K86,"-","/",1),"-","/",1)),DAY(SUBSTITUTE(SUBSTITUTE(K86,"-","/",1),"-","/",1))) -> 46127 | M86: =RIGHT(C86,8) -> 97717274 | N86: =IFERROR(IF(VLOOKUP(M86,'Leads no grupo Saibai'!C:C,1,FALSE)=M86,"Sim"),"Não") -> Sim
A87: 2026-04-15T15:18:25.489Z | B87: Magali Zampieri | C87: 15997717274 | D87: mzampieri@pucsp.br | E87: https://lp.saibai.com.br/?utm_source=MetaAds&utm_medium=ADV+-+%5BIG%5D+%5BFB%5D+%5B30%2B%5D+%5BPIEDADE+-+40KM%5D+V%C3%81RIOS&utm_campaign=07.04.2026+%5BV4%5D+%5BWB%5D+%5BLEADS-GRUPO-WHATS%5D+01&utm_content=07.04+%5BIMG%5D+%5BAD04%5D+Pedidos+abertos&utm_term=Instagram_Feed&utm_id=120247452154580155&fbclid=PAZXh0bgNhZW0BMABhZGlkAas0a_lii3tzcnRjBmFwcF9pZA81NjcwNjczNDMzNTI0MjcAAadfiusuYMKofOgpz9KrPGQs2I-dczM2o_t6fAqbYu44Rss7i1Gy_ssD-eBpoA_aem_8FNCdPn_RrwlzmXtJzlm-Q&campaign_id=120247452154580155&ad_id=120247452938090155 | F87: =IFERROR(__xludf.DUMMYFUNCTION("""COMPUTED_VALUE"""),"MetaAds") -> MetaAds | G87: =IFERROR(__xludf.DUMMYFUNCTION("""COMPUTED_VALUE"""),"ADV - [IG] [FB] [30%2B] [PIEDADE - 40KM] V%C3%81RIOS") -> ADV - [IG] [FB] [30%2B] [PIEDADE - 40KM] V%C3%81RIOS | H87: =IFERROR(__xludf.DUMMYFUNCTION("""COMPUTED_VALUE"""),"Instagram_Feed") -> Instagram_Feed | I87: =IFERROR(__xludf.DUMMYFUNCTION("""COMPUTED_VALUE"""),"07.04 [IMG] [AD04] Pedidos abertos") -> 07.04 [IMG] [AD04] Pedidos abertos | J87: =IFERROR(__xludf.DUMMYFUNCTION("""COMPUTED_VALUE"""),"07.04.2026 [V4] [WB] [LEADS-GRUPO-WHATS] 01") -> 07.04.2026 [V4] [WB] [LEADS-GRUPO-WHATS] 01 | K87: =LEFT(A87,10) -> 2026-04-15 | L87: =DATE(YEAR(SUBSTITUTE(SUBSTITUTE(K87,"-","/",1),"-","/",1)),MONTH(SUBSTITUTE(SUBSTITUTE(K87,"-","/",1),"-","/",1)),DAY(SUBSTITUTE(SUBSTITUTE(K87,"-","/",1),"-","/",1))) -> 46127 | M87: =RIGHT(C87,8) -> 97717274 | N87: =IFERROR(IF(VLOOKUP(M87,'Leads no grupo Saibai'!C:C,1,FALSE)=M87,"Sim"),"Não") -> Sim
A88: 2026-04-15T22:39:16.593Z | B88: Márcia Toyoda | C88: 15998386011 | D88: marciatoyoda5@gmail.com | E88: https://lp.saibai.com.br/?utm_source=MetaAds&utm_medium=ADV+-+%5BIG%5D+%5BFB%5D+%5B30%2B%5D+%5BPIEDADE+-+40KM%5D+V%C3%81RIOS&utm_campaign=07.04.2026+%5BV4%5D+%5BWB%5D+%5BLEADS-GRUPO-WHATS%5D+01&utm_content=07.04+%5BIMG%5D+%5BAD04%5D+Pedidos+abertos&utm_term=Instagram_Stories&utm_id=120247452154580155&fbclid=PAZXh0bgNhZW0BMABhZGlkAas0bAW7ZytzcnRjBmFwcF9pZA81NjcwNjczNDMzNTI0MjcAAaenu_avnSZbwr-CO2z5uY1TJEXGvIkHOeBGKGe4tLq0uP7Dm6cupeC__BnqEA_aem_TCEQ99JmQr6ZKbkyDITarA&campaign_id=120247452154580155&ad_id=120247452938090155 | F88: =IFERROR(__xludf.DUMMYFUNCTION("""COMPUTED_VALUE"""),"MetaAds") -> MetaAds | G88: =IFERROR(__xludf.DUMMYFUNCTION("""COMPUTED_VALUE"""),"ADV - [IG] [FB] [30%2B] [PIEDADE - 40KM] V%C3%81RIOS") -> ADV - [IG] [FB] [30%2B] [PIEDADE - 40KM] V%C3%81RIOS | H88: =IFERROR(__xludf.DUMMYFUNCTION("""COMPUTED_VALUE"""),"Instagram_Stories") -> Instagram_Stories | I88: =IFERROR(__xludf.DUMMYFUNCTION("""COMPUTED_VALUE"""),"07.04 [IMG] [AD04] Pedidos abertos") -> 07.04 [IMG] [AD04] Pedidos abertos | J88: =IFERROR(__xludf.DUMMYFUNCTION("""COMPUTED_VALUE"""),"07.04.2026 [V4] [WB] [LEADS-GRUPO-WHATS] 01") -> 07.04.2026 [V4] [WB] [LEADS-GRUPO-WHATS] 01 | K88: =LEFT(A88,10) -> 2026-04-15 | L88: =DATE(YEAR(SUBSTITUTE(SUBSTITUTE(K88,"-","/",1),"-","/",1)),MONTH(SUBSTITUTE(SUBSTITUTE(K88,"-","/",1),"-","/",1)),DAY(SUBSTITUTE(SUBSTITUTE(K88,"-","/",1),"-","/",1))) -> 46127 | M88: =RIGHT(C88,8) -> 98386011 | N88: =IFERROR(IF(VLOOKUP(M88,'Leads no grupo Saibai'!C:C,1,FALSE)=M88,"Sim"),"Não") -> Sim
A89: 2026-04-15T22:41:31.631Z | B89: Máira Cristina | C89: 55159812780 | D89: mc_lua@yahoo.com.br | E89: https://lp.saibai.com.br/?utm_source=MetaAds&utm_medium=ADV+-+%5BIG%5D+%5BFB%5D+%5B30%2B%5D+%5BPIEDADE+-+40KM%5D+V%C3%81RIOS&utm_campaign=07.04.2026+%5BV4%5D+%5BWB%5D+%5BLEADS-GRUPO-WHATS%5D+01&utm_content=07.04+%5BIMG%5D+%5BAD04%5D+Pedidos+abertos&utm_term=Instagram_Stories&utm_id=120247452154580155&fbclid=PAZXh0bgNhZW0BMABhZGlkAas0bAW7ZytzcnRjBmFwcF9pZA81NjcwNjczNDMzNTI0MjcAAac-Qqpp4K1JiSQbIiHvkXKlMkg3fEfU7g0YyAqmmf1quN1Ei2Wf9rtkRWukhg_aem_QIrAAgJetpVQQzVf4pgWcQ&campaign_id=120247452154580155&ad_id=120247452938090155 | F89: =IFERROR(__xludf.DUMMYFUNCTION("""COMPUTED_VALUE"""),"MetaAds") -> MetaAds | G89: =IFERROR(__xludf.DUMMYFUNCTION("""COMPUTED_VALUE"""),"ADV - [IG] [FB] [30%2B] [PIEDADE - 40KM] V%C3%81RIOS") -> ADV - [IG] [FB] [30%2B] [PIEDADE - 40KM] V%C3%81RIOS | H89: =IFERROR(__xludf.DUMMYFUNCTION("""COMPUTED_VALUE"""),"Instagram_Stories") -> Instagram_Stories | I89: =IFERROR(__xludf.DUMMYFUNCTION("""COMPUTED_VALUE"""),"07.04 [IMG] [AD04] Pedidos abertos") -> 07.04 [IMG] [AD04] Pedidos abertos | J89: =IFERROR(__xludf.DUMMYFUNCTION("""COMPUTED_VALUE"""),"07.04.2026 [V4] [WB] [LEADS-GRUPO-WHATS] 01") -> 07.04.2026 [V4] [WB] [LEADS-GRUPO-WHATS] 01 | K89: =LEFT(A89,10) -> 2026-04-15 | L89: =DATE(YEAR(SUBSTITUTE(SUBSTITUTE(K89,"-","/",1),"-","/",1)),MONTH(SUBSTITUTE(SUBSTITUTE(K89,"-","/",1),"-","/",1)),DAY(SUBSTITUTE(SUBSTITUTE(K89,"-","/",1),"-","/",1))) -> 46127 | M89: =RIGHT(C89,8) -> 59812780 | N89: =IFERROR(IF(VLOOKUP(M89,'Leads no grupo Saibai'!C:C,1,FALSE)=M89,"Sim"),"Não") -> Não
A90: 2026-04-16T00:11:03.530Z | B90: Elizabeth Campos Pecchiae | C90: 11998288819 | D90: bpecchiae@hotmail.com | E90: https://lp.saibai.com.br/?utm_source=MetaAds&utm_medium=ADV+-+%5BIG%5D+%5BFB%5D+%5B30%2B%5D+%5BPIEDADE+-+40KM%5D+V%C3%81RIOS&utm_campaign=07.04.2026+%5BV4%5D+%5BWB%5D+%5BLEADS-GRUPO-WHATS%5D+01&utm_content=07.04+%5BIMG%5D+%5BAD04%5D+Pedidos+abertos&utm_term=Instagram_Reels&utm_id=120247452154580155&fbclid=PAZXh0bgNhZW0BMABhZGlkAas0bAW7ZytzcnRjBmFwcF9pZA8xMjQwMjQ1NzQyODc0MTQAAacAdPYFn3jnrtBOZZpzTJGFhA3WJAGZ_PMriiE0b7Zpx7If4ZeM4nr1CUxWBA_aem_p2Kq_Hl3AqoU4IRpb7N60Q&campaign_id=120247452154580155&ad_id=120247452938090155 | F90: =IFERROR(__xludf.DUMMYFUNCTION("""COMPUTED_VALUE"""),"MetaAds") -> MetaAds | G90: =IFERROR(__xludf.DUMMYFUNCTION("""COMPUTED_VALUE"""),"ADV - [IG] [FB] [30%2B] [PIEDADE - 40KM] V%C3%81RIOS") -> ADV - [IG] [FB] [30%2B] [PIEDADE - 40KM] V%C3%81RIOS | H90: =IFERROR(__xludf.DUMMYFUNCTION("""COMPUTED_VALUE"""),"Instagram_Reels") -> Instagram_Reels | I90: =IFERROR(__xludf.DUMMYFUNCTION("""COMPUTED_VALUE"""),"07.04 [IMG] [AD04] Pedidos abertos") -> 07.04 [IMG] [AD04] Pedidos abertos | J90: =IFERROR(__xludf.DUMMYFUNCTION("""COMPUTED_VALUE"""),"07.04.2026 [V4] [WB] [LEADS-GRUPO-WHATS] 01") -> 07.04.2026 [V4] [WB] [LEADS-GRUPO-WHATS] 01 | K90: =LEFT(A90,10) -> 2026-04-16 | L90: =DATE(YEAR(SUBSTITUTE(SUBSTITUTE(K90,"-","/",1),"-","/",1)),MONTH(SUBSTITUTE(SUBSTITUTE(K90,"-","/",1),"-","/",1)),DAY(SUBSTITUTE(SUBSTITUTE(K90,"-","/",1),"-","/",1))) -> 46128 | M90: =RIGHT(C90,8) -> 98288819 | N90: =IFERROR(IF(VLOOKUP(M90,'Leads no grupo Saibai'!C:C,1,FALSE)=M90,"Sim"),"Não") -> Sim
A91: 2026-04-16T02:45:18.261Z | B91: Neuza Maria Ribeiro tuzino | C91: 15991018440 | D91: neuzatuzino@gmail.com | E91: https://lp.saibai.com.br/?utm_source=MetaAds&utm_medium=ADV+-+%5BIG%5D+%5BFB%5D+%5B30%2B%5D+%5BPIEDADE+-+40KM%5D+V%C3%81RIOS&utm_campaign=07.04.2026+%5BV4%5D+%5BWB%5D+%5BLEADS-GRUPO-WHATS%5D+01&utm_content=07.04+%5BIMG%5D+%5BAD01%5D+A+safra+come%C3%A7ou&utm_term=Facebook_Mobile_Reels&fbclid=IwZXh0bgNhZW0BMABhZGlkAas0a_chJvtzcnRjBmFwcF9pZAwzNTA2ODU1MzE3MjgAAR6rzUMO2xRv5Y2ezBg5K1xzpEsdhQKlcCZCE6xApv4T-Ew_dY36-NyVncGnfg_aem_Nk0sg2VsDv6It-V_2WEkSQ&campaign_id=120247452154580155&ad_id=120247452154590155&utm_id=120247452154580155 | F91: =IFERROR(__xludf.DUMMYFUNCTION("""COMPUTED_VALUE"""),"MetaAds") -> MetaAds | G91: =IFERROR(__xludf.DUMMYFUNCTION("""COMPUTED_VALUE"""),"ADV - [IG] [FB] [30%2B] [PIEDADE - 40KM] V%C3%81RIOS") -> ADV - [IG] [FB] [30%2B] [PIEDADE - 40KM] V%C3%81RIOS | H91: =IFERROR(__xludf.DUMMYFUNCTION("""COMPUTED_VALUE"""),"Facebook_Mobile_Reels") -> Facebook_Mobile_Reels | I91: =IFERROR(__xludf.DUMMYFUNCTION("""COMPUTED_VALUE"""),"07.04 [IMG] [AD01] A safra come%C3%A7ou") -> 07.04 [IMG] [AD01] A safra come%C3%A7ou | J91: =IFERROR(__xludf.DUMMYFUNCTION("""COMPUTED_VALUE"""),"07.04.2026 [V4] [WB] [LEADS-GRUPO-WHATS] 01") -> 07.04.2026 [V4] [WB] [LEADS-GRUPO-WHATS] 01 | K91: =LEFT(A91,10) -> 2026-04-16 | L91: =DATE(YEAR(SUBSTITUTE(SUBSTITUTE(K91,"-","/",1),"-","/",1)),MONTH(SUBSTITUTE(SUBSTITUTE(K91,"-","/",1),"-","/",1)),DAY(SUBSTITUTE(SUBSTITUTE(K91,"-","/",1),"-","/",1))) -> 46128 | M91: =RIGHT(C91,8) -> 91018440 | N91: =IFERROR(IF(VLOOKUP(M91,'Leads no grupo Saibai'!C:C,1,FALSE)=M91,"Sim"),"Não") -> Não
A92: 2026-04-16T03:32:42.477Z | B92: Luciana Geraldes | C92: 11964128289 | D92: geraldesluciana@gmail.com | E92: https://lp.saibai.com.br/?utm_source=MetaAds&utm_medium=ADV+-+%5BIG%5D+%5BFB%5D+%5B30%2B%5D+%5BPIEDADE+-+40KM%5D+V%C3%81RIOS&utm_campaign=07.04.2026+%5BV4%5D+%5BWB%5D+%5BLEADS-GRUPO-WHATS%5D+01&utm_content=07.04+%5BIMG%5D+%5BAD01%5D+A+safra+come%C3%A7ou&utm_term=Instagram_Feed&utm_id=120247452154580155&fbclid=PAZXh0bgNhZW0BMABhZGlkAas0a_chJvtzcnRjBmFwcF9pZA81NjcwNjczNDMzNTI0MjcAAaestcpQj5FxfSZbKFJaFdusX1Omcc2zzXHOiSbhElXNwy-jZOAsoLvN4VKOtA_aem_bjs32XhKshPlES1ru45pWA&campaign_id=120247452154580155&ad_id=120247452154590155 | F92: =IFERROR(__xludf.DUMMYFUNCTION("""COMPUTED_VALUE"""),"MetaAds") -> MetaAds | G92: =IFERROR(__xludf.DUMMYFUNCTION("""COMPUTED_VALUE"""),"ADV - [IG] [FB] [30%2B] [PIEDADE - 40KM] V%C3%81RIOS") -> ADV - [IG] [FB] [30%2B] [PIEDADE - 40KM] V%C3%81RIOS | H92: =IFERROR(__xludf.DUMMYFUNCTION("""COMPUTED_VALUE"""),"Instagram_Feed") -> Instagram_Feed | I92: =IFERROR(__xludf.DUMMYFUNCTION("""COMPUTED_VALUE"""),"07.04 [IMG] [AD01] A safra come%C3%A7ou") -> 07.04 [IMG] [AD01] A safra come%C3%A7ou | J92: =IFERROR(__xludf.DUMMYFUNCTION("""COMPUTED_VALUE"""),"07.04.2026 [V4] [WB] [LEADS-GRUPO-WHATS] 01") -> 07.04.2026 [V4] [WB] [LEADS-GRUPO-WHATS] 01 | K92: =LEFT(A92,10) -> 2026-04-16 | L92: =DATE(YEAR(SUBSTITUTE(SUBSTITUTE(K92,"-","/",1),"-","/",1)),MONTH(SUBSTITUTE(SUBSTITUTE(K92,"-","/",1),"-","/",1)),DAY(SUBSTITUTE(SUBSTITUTE(K92,"-","/",1),"-","/",1))) -> 46128 | M92: =RIGHT(C92,8) -> 64128289 | N92: =IFERROR(IF(VLOOKUP(M92,'Leads no grupo Saibai'!C:C,1,FALSE)=M92,"Sim"),"Não") -> Sim
A93: 2026-04-16T06:18:38.589Z | B93: Gilma fabiano Fabiano | C93: 11997021140 | D93: gilma.corretora@gmail.com | E93: https://lp.saibai.com.br/?utm_source=MetaAds&utm_medium=ADV+-+%5BIG%5D+%5BFB%5D+%5B30%2B%5D+%5BPIEDADE+-+40KM%5D+V%C3%81RIOS&utm_campaign=07.04.2026+%5BV4%5D+%5BWB%5D+%5BLEADS-GRUPO-WHATS%5D+01&utm_content=07.04+%5BIMG%5D+%5BAD01%5D+A+safra+come%C3%A7ou&utm_term=Facebook_Mobile_Reels&fbclid=IwZXh0bgNhZW0BMABhZGlkAas0a_chJvtzcnRjBmFwcF9pZAwzNTA2ODU1MzE3MjgAAR41CfyEzV6t0FSydi34NnyIE1cT5duuf2DHuwJEgciSz3527xee804NEvSmGA_aem_-6mhVgLgXAsK7ZiCkiJsSQ&campaign_id=120247452154580155&ad_id=120247452154590155&utm_id=120247452154580155 | F93: =IFERROR(__xludf.DUMMYFUNCTION("""COMPUTED_VALUE"""),"MetaAds") -> MetaAds | G93: =IFERROR(__xludf.DUMMYFUNCTION("""COMPUTED_VALUE"""),"ADV - [IG] [FB] [30%2B] [PIEDADE - 40KM] V%C3%81RIOS") -> ADV - [IG] [FB] [30%2B] [PIEDADE - 40KM] V%C3%81RIOS | H93: =IFERROR(__xludf.DUMMYFUNCTION("""COMPUTED_VALUE"""),"Facebook_Mobile_Reels") -> Facebook_Mobile_Reels | I93: =IFERROR(__xludf.DUMMYFUNCTION("""COMPUTED_VALUE"""),"07.04 [IMG] [AD01] A safra come%C3%A7ou") -> 07.04 [IMG] [AD01] A safra come%C3%A7ou | J93: =IFERROR(__xludf.DUMMYFUNCTION("""COMPUTED_VALUE"""),"07.04.2026 [V4] [WB] [LEADS-GRUPO-WHATS] 01") -> 07.04.2026 [V4] [WB] [LEADS-GRUPO-WHATS] 01 | K93: =LEFT(A93,10) -> 2026-04-16 | L93: =DATE(YEAR(SUBSTITUTE(SUBSTITUTE(K93,"-","/",1),"-","/",1)),MONTH(SUBSTITUTE(SUBSTITUTE(K93,"-","/",1),"-","/",1)),DAY(SUBSTITUTE(SUBSTITUTE(K93,"-","/",1),"-","/",1))) -> 46128 | M93: =RIGHT(C93,8) -> 97021140 | N93: =IFERROR(IF(VLOOKUP(M93,'Leads no grupo Saibai'!C:C,1,FALSE)=M93,"Sim"),"Não") -> Sim
A94: 2026-04-16T06:39:24.018Z | B94: Liliane Townsend | C94: 55119849772 | D94: lilianetownsend@hotmail.com | E94: https://lp.saibai.com.br/?utm_source=MetaAds&utm_medium=ADV+-+%5BIG%5D+%5BFB%5D+%5B30%2B%5D+%5BPIEDADE+-+40KM%5D+V%C3%81RIOS&utm_campaign=07.04.2026+%5BV4%5D+%5BWB%5D+%5BLEADS-GRUPO-WHATS%5D+01&utm_content=07.04+%5BIMG%5D+%5BAD04%5D+Pedidos+abertos&utm_term=Facebook_Mobile_Reels&fbclid=IwZXh0bgNhZW0BMABhZGlkAas0bAW7ZytzcnRjBmFwcF9pZAwzNTA2ODU1MzE3MjgAAR6Qx0-Lwtbb_jayhZZOgRA9eJsyr6GdTXjhaU7xQIxxYPUd8j7Gk8BustDeZg_aem_-T2os2Yny1WSZbDsPt35mw&campaign_id=120247452154580155&ad_id=120247452938090155&utm_id=120247452154580155 | F94: =IFERROR(__xludf.DUMMYFUNCTION("""COMPUTED_VALUE"""),"MetaAds") -> MetaAds | G94: =IFERROR(__xludf.DUMMYFUNCTION("""COMPUTED_VALUE"""),"ADV - [IG] [FB] [30%2B] [PIEDADE - 40KM] V%C3%81RIOS") -> ADV - [IG] [FB] [30%2B] [PIEDADE - 40KM] V%C3%81RIOS | H94: =IFERROR(__xludf.DUMMYFUNCTION("""COMPUTED_VALUE"""),"Facebook_Mobile_Reels") -> Facebook_Mobile_Reels | I94: =IFERROR(__xludf.DUMMYFUNCTION("""COMPUTED_VALUE"""),"07.04 [IMG] [AD04] Pedidos abertos") -> 07.04 [IMG] [AD04] Pedidos abertos | J94: =IFERROR(__xludf.DUMMYFUNCTION("""COMPUTED_VALUE"""),"07.04.2026 [V4] [WB] [LEADS-GRUPO-WHATS] 01") -> 07.04.2026 [V4] [WB] [LEADS-GRUPO-WHATS] 01 | K94: =LEFT(A94,10) -> 2026-04-16 | L94: =DATE(YEAR(SUBSTITUTE(SUBSTITUTE(K94,"-","/",1),"-","/",1)),MONTH(SUBSTITUTE(SUBSTITUTE(K94,"-","/",1),"-","/",1)),DAY(SUBSTITUTE(SUBSTITUTE(K94,"-","/",1),"-","/",1))) -> 46128 | M94: =RIGHT(C94,8) -> 19849772 | N94: =IFERROR(IF(VLOOKUP(M94,'Leads no grupo Saibai'!C:C,1,FALSE)=M94,"Sim"),"Não") -> Não
A95: 2026-04-16T10:05:28.578Z | B95: Sandra Marilda | C95: 55159918200 | D95: sandra.nascimento@ymail.com | E95: https://lp.saibai.com.br/?utm_source=MetaAds&utm_medium=ADV+-+%5BIG%5D+%5BFB%5D+%5B30%2B%5D+%5BPIEDADE+-+40KM%5D+V%C3%81RIOS&utm_campaign=07.04.2026+%5BV4%5D+%5BWB%5D+%5BLEADS-GRUPO-WHATS%5D+01&utm_content=07.04+%5BIMG%5D+%5BAD04%5D+Pedidos+abertos&utm_term=Facebook_Mobile_Reels&fbclid=IwZXh0bgNhZW0BMABhZGlkAas0bAW7ZytzcnRjBmFwcF9pZAwzNTA2ODU1MzE3MjgAAR7Y1qMagdntkYxn1qccooYa7Avr5o2mS0gO8cSc09o5fuv1_3D7G21FHum4qg_aem_7ungyuvQPmk9DSEyTns9hg&campaign_id=120247452154580155&ad_id=120247452938090155&utm_id=120247452154580155 | F95: =IFERROR(__xludf.DUMMYFUNCTION("""COMPUTED_VALUE"""),"MetaAds") -> MetaAds | G95: =IFERROR(__xludf.DUMMYFUNCTION("""COMPUTED_VALUE"""),"ADV - [IG] [FB] [30%2B] [PIEDADE - 40KM] V%C3%81RIOS") -> ADV - [IG] [FB] [30%2B] [PIEDADE - 40KM] V%C3%81RIOS | H95: =IFERROR(__xludf.DUMMYFUNCTION("""COMPUTED_VALUE"""),"Facebook_Mobile_Reels") -> Facebook_Mobile_Reels | I95: =IFERROR(__xludf.DUMMYFUNCTION("""COMPUTED_VALUE"""),"07.04 [IMG] [AD04] Pedidos abertos") -> 07.04 [IMG] [AD04] Pedidos abertos | J95: =IFERROR(__xludf.DUMMYFUNCTION("""COMPUTED_VALUE"""),"07.04.2026 [V4] [WB] [LEADS-GRUPO-WHATS] 01") -> 07.04.2026 [V4] [WB] [LEADS-GRUPO-WHATS] 01 | K95: =LEFT(A95,10) -> 2026-04-16 | L95: =DATE(YEAR(SUBSTITUTE(SUBSTITUTE(K95,"-","/",1),"-","/",1)),MONTH(SUBSTITUTE(SUBSTITUTE(K95,"-","/",1),"-","/",1)),DAY(SUBSTITUTE(SUBSTITUTE(K95,"-","/",1),"-","/",1))) -> 46128 | M95: =RIGHT(C95,8) -> 59918200 | N95: =IFERROR(IF(VLOOKUP(M95,'Leads no grupo Saibai'!C:C,1,FALSE)=M95,"Sim"),"Não") -> Não
A96: 2026-04-16T10:27:50.995Z | B96: Stella | C96: 55159970385 | D96: s.stelasantos@hotmail.com | E96: https://lp.saibai.com.br/?utm_source=MetaAds&utm_medium=ADV+-+%5BIG%5D+%5BFB%5D+%5B30%2B%5D+%5BPIEDADE+-+40KM%5D+V%C3%81RIOS&utm_campaign=07.04.2026+%5BV4%5D+%5BWB%5D+%5BLEADS-GRUPO-WHATS%5D+01&utm_content=07.04+%5BIMG%5D+%5BAD04%5D+Pedidos+abertos&utm_term=Facebook_Mobile_Reels&fbclid=IwZXh0bgNhZW0BMABhZGlkAas0bAW7ZytzcnRjBmFwcF9pZAwzNTA2ODU1MzE3MjgAAR4pXK_wpl_wZmGzjIw1CcgFabKIoq99_jBORlyBYm33WRpFkPZoy-wIsCkmYg_aem_agdXasLjJZ2CACGp3Y-0JQ&campaign_id=120247452154580155&ad_id=120247452938090155&utm_id=120247452154580155 | F96: =IFERROR(__xludf.DUMMYFUNCTION("""COMPUTED_VALUE"""),"MetaAds") -> MetaAds | G96: =IFERROR(__xludf.DUMMYFUNCTION("""COMPUTED_VALUE"""),"ADV - [IG] [FB] [30%2B] [PIEDADE - 40KM] V%C3%81RIOS") -> ADV - [IG] [FB] [30%2B] [PIEDADE - 40KM] V%C3%81RIOS | H96: =IFERROR(__xludf.DUMMYFUNCTION("""COMPUTED_VALUE"""),"Facebook_Mobile_Reels") -> Facebook_Mobile_Reels | I96: =IFERROR(__xludf.DUMMYFUNCTION("""COMPUTED_VALUE"""),"07.04 [IMG] [AD04] Pedidos abertos") -> 07.04 [IMG] [AD04] Pedidos abertos | J96: =IFERROR(__xludf.DUMMYFUNCTION("""COMPUTED_VALUE"""),"07.04.2026 [V4] [WB] [LEADS-GRUPO-WHATS] 01") -> 07.04.2026 [V4] [WB] [LEADS-GRUPO-WHATS] 01 | K96: =LEFT(A96,10) -> 2026-04-16 | L96: =DATE(YEAR(SUBSTITUTE(SUBSTITUTE(K96,"-","/",1),"-","/",1)),MONTH(SUBSTITUTE(SUBSTITUTE(K96,"-","/",1),"-","/",1)),DAY(SUBSTITUTE(SUBSTITUTE(K96,"-","/",1),"-","/",1))) -> 46128 | M96: =RIGHT(C96,8) -> 59970385 | N96: =IFERROR(IF(VLOOKUP(M96,'Leads no grupo Saibai'!C:C,1,FALSE)=M96,"Sim"),"Não") -> Não
A97: 2026-04-16T11:09:34.534Z | B97: Eliane mi | C97: 55119765303 | D97: changmi1004@gmail.com | E97: https://lp.saibai.com.br/?utm_source=MetaAds&utm_medium=ADV+-+%5BIG%5D+%5BFB%5D+%5B30%2B%5D+%5BPIEDADE+-+40KM%5D+V%C3%81RIOS&utm_campaign=07.04.2026+%5BV4%5D+%5BWB%5D+%5BLEADS-GRUPO-WHATS%5D+01&utm_content=07.04+%5BIMG%5D+%5BAD01%5D+A+safra+come%C3%A7ou&utm_term=Instagram_Feed&utm_id=120247452154580155&fbclid=PAZXh0bgNhZW0BMABhZGlkAas0a_chJvtzcnRjBmFwcF9pZA8xMjQwMjQ1NzQyODc0MTQAAacxflx8UTX0yURjF5suut4ZPyHFrd9JfiojdcZcAkPjaN0ZH2jJNUcvaxky6A_aem_5YrGyrdeglwS28MvyqswdQ&campaign_id=120247452154580155&ad_id=120247452154590155 | F97: =IFERROR(__xludf.DUMMYFUNCTION("""COMPUTED_VALUE"""),"MetaAds") -> MetaAds | G97: =IFERROR(__xludf.DUMMYFUNCTION("""COMPUTED_VALUE"""),"ADV - [IG] [FB] [30%2B] [PIEDADE - 40KM] V%C3%81RIOS") -> ADV - [IG] [FB] [30%2B] [PIEDADE - 40KM] V%C3%81RIOS | H97: =IFERROR(__xludf.DUMMYFUNCTION("""COMPUTED_VALUE"""),"Instagram_Feed") -> Instagram_Feed | I97: =IFERROR(__xludf.DUMMYFUNCTION("""COMPUTED_VALUE"""),"07.04 [IMG] [AD01] A safra come%C3%A7ou") -> 07.04 [IMG] [AD01] A safra come%C3%A7ou | J97: =IFERROR(__xludf.DUMMYFUNCTION("""COMPUTED_VALUE"""),"07.04.2026 [V4] [WB] [LEADS-GRUPO-WHATS] 01") -> 07.04.2026 [V4] [WB] [LEADS-GRUPO-WHATS] 01 | K97: =LEFT(A97,10) -> 2026-04-16 | L97: =DATE(YEAR(SUBSTITUTE(SUBSTITUTE(K97,"-","/",1),"-","/",1)),MONTH(SUBSTITUTE(SUBSTITUTE(K97,"-","/",1),"-","/",1)),DAY(SUBSTITUTE(SUBSTITUTE(K97,"-","/",1),"-","/",1))) -> 46128 | M97: =RIGHT(C97,8) -> 19765303 | N97: =IFERROR(IF(VLOOKUP(M97,'Leads no grupo Saibai'!C:C,1,FALSE)=M97,"Sim"),"Não") -> Não
A98: 2026-04-16T13:37:23.837Z | B98: Débora Alves | C98: 15996739689 | D98: deboraalvesrocha91@hotmail.com | E98: https://lp.saibai.com.br/?utm_source=MetaAds&utm_medium=ADV+-+%5BIG%5D+%5BFB%5D+%5B30%2B%5D+%5BPIEDADE+-+40KM%5D+V%C3%81RIOS&utm_campaign=07.04.2026+%5BV4%5D+%5BWB%5D+%5BLEADS-GRUPO-WHATS%5D+01&utm_content=07.04+%5BIMG%5D+%5BAD04%5D+Pedidos+abertos&utm_term=Instagram_Stories&utm_id=120247452154580155&fbclid=PAZXh0bgNhZW0BMABhZGlkAas0bAW7ZytzcnRjBmFwcF9pZA81NjcwNjczNDMzNTI0MjcAAaeN7WFLBRVudwOreyz19iL2fAIlSvZrZskZMi6te5aSyle9KIv7hnpRcNepWQ_aem_IAHL2XCDr53yRQClOXOXFg&campaign_id=120247452154580155&ad_id=120247452938090155 | F98: =IFERROR(__xludf.DUMMYFUNCTION("""COMPUTED_VALUE"""),"MetaAds") -> MetaAds | G98: =IFERROR(__xludf.DUMMYFUNCTION("""COMPUTED_VALUE"""),"ADV - [IG] [FB] [30%2B] [PIEDADE - 40KM] V%C3%81RIOS") -> ADV - [IG] [FB] [30%2B] [PIEDADE - 40KM] V%C3%81RIOS | H98: =IFERROR(__xludf.DUMMYFUNCTION("""COMPUTED_VALUE"""),"Instagram_Stories") -> Instagram_Stories | I98: =IFERROR(__xludf.DUMMYFUNCTION("""COMPUTED_VALUE"""),"07.04 [IMG] [AD04] Pedidos abertos") -> 07.04 [IMG] [AD04] Pedidos abertos | J98: =IFERROR(__xludf.DUMMYFUNCTION("""COMPUTED_VALUE"""),"07.04.2026 [V4] [WB] [LEADS-GRUPO-WHATS] 01") -> 07.04.2026 [V4] [WB] [LEADS-GRUPO-WHATS] 01 | K98: =LEFT(A98,10) -> 2026-04-16 | L98: =DATE(YEAR(SUBSTITUTE(SUBSTITUTE(K98,"-","/",1),"-","/",1)),MONTH(SUBSTITUTE(SUBSTITUTE(K98,"-","/",1),"-","/",1)),DAY(SUBSTITUTE(SUBSTITUTE(K98,"-","/",1),"-","/",1))) -> 46128 | M98: =RIGHT(C98,8) -> 96739689 | N98: =IFERROR(IF(VLOOKUP(M98,'Leads no grupo Saibai'!C:C,1,FALSE)=M98,"Sim"),"Não") -> Sim
A99: 2026-04-16T18:05:33.883Z | B99: Rita Cássia Vieira de Oliveira | C99: 15981220521 | D99: rivol1504@gmail.com | E99: https://lp.saibai.com.br/?utm_source=MetaAds&utm_medium=ADV+-+%5BIG%5D+%5BFB%5D+%5B30%2B%5D+%5BPIEDADE+-+40KM%5D+V%C3%81RIOS&utm_campaign=07.04.2026+%5BV4%5D+%5BWB%5D+%5BLEADS-GRUPO-WHATS%5D+01&utm_content=07.04+%5BIMG%5D+%5BAD04%5D+Pedidos+abertos&utm_term=Facebook_Stories&fbclid=IwZXh0bgNhZW0BMABhZGlkAas0bAW7ZytzcnRjBmFwcF9pZAo2NjI4NTY4Mzc5AAEewHCBCHDQnnVlB4LyT1brSOwMECLxDLxiqr2_Va44T5uXnDMI9c228DC0gKM_aem_3KCZW6zR3T62J3POWfLR4Q&campaign_id=120247452154580155&ad_id=120247452938090155&utm_id=120247452154580155 | F99: =IFERROR(__xludf.DUMMYFUNCTION("""COMPUTED_VALUE"""),"MetaAds") -> MetaAds | G99: =IFERROR(__xludf.DUMMYFUNCTION("""COMPUTED_VALUE"""),"ADV - [IG] [FB] [30%2B] [PIEDADE - 40KM] V%C3%81RIOS") -> ADV - [IG] [FB] [30%2B] [PIEDADE - 40KM] V%C3%81RIOS | H99: =IFERROR(__xludf.DUMMYFUNCTION("""COMPUTED_VALUE"""),"Facebook_Stories") -> Facebook_Stories | I99: =IFERROR(__xludf.DUMMYFUNCTION("""COMPUTED_VALUE"""),"07.04 [IMG] [AD04] Pedidos abertos") -> 07.04 [IMG] [AD04] Pedidos abertos | J99: =IFERROR(__xludf.DUMMYFUNCTION("""COMPUTED_VALUE"""),"07.04.2026 [V4] [WB] [LEADS-GRUPO-WHATS] 01") -> 07.04.2026 [V4] [WB] [LEADS-GRUPO-WHATS] 01 | K99: =LEFT(A99,10) -> 2026-04-16 | L99: =DATE(YEAR(SUBSTITUTE(SUBSTITUTE(K99,"-","/",1),"-","/",1)),MONTH(SUBSTITUTE(SUBSTITUTE(K99,"-","/",1),"-","/",1)),DAY(SUBSTITUTE(SUBSTITUTE(K99,"-","/",1),"-","/",1))) -> 46128 | M99: =RIGHT(C99,8) -> 81220521 | N99: =IFERROR(IF(VLOOKUP(M99,'Leads no grupo Saibai'!C:C,1,FALSE)=M99,"Sim"),"Não") -> Sim
A100: 2026-04-16T22:36:18.455Z | B100: Patricia Amparo Lauria | C100: 11957713604 | D100: patylauria@gmail.com | E100: https://lp.saibai.com.br/?utm_source=MetaAds&utm_medium=ADV+-+%5BIG%5D+%5BFB%5D+%5B30%2B%5D+%5BPIEDADE+-+40KM%5D+V%C3%81RIOS&utm_campaign=07.04.2026+%5BV4%5D+%5BWB%5D+%5BLEADS-GRUPO-WHATS%5D+01&utm_content=07.04+%5BIMG%5D+%5BAD04%5D+Pedidos+abertos&utm_term=Facebook_Mobile_Feed&fbclid=IwZXh0bgNhZW0BMABhZGlkAas0bAW7ZytzcnRjBmFwcF9pZAwzNTA2ODU1MzE3MjgAAR7IPJ4XcKocLSZ5uX6fjcP_9GUN6d8zeoO9BkPiPknEUMBT26QH65dwuZoqyw_aem_4YtSSaKCDPosCg_gkAew2w&campaign_id=120247452154580155&ad_id=120247452938090155&utm_id=120247452154580155 | F100: =IFERROR(__xludf.DUMMYFUNCTION("""COMPUTED_VALUE"""),"MetaAds") -> MetaAds | G100: =IFERROR(__xludf.DUMMYFUNCTION("""COMPUTED_VALUE"""),"ADV - [IG] [FB] [30%2B] [PIEDADE - 40KM] V%C3%81RIOS") -> ADV - [IG] [FB] [30%2B] [PIEDADE - 40KM] V%C3%81RIOS | H100: =IFERROR(__xludf.DUMMYFUNCTION("""COMPUTED_VALUE"""),"Facebook_Mobile_Feed") -> Facebook_Mobile_Feed | I100: =IFERROR(__xludf.DUMMYFUNCTION("""COMPUTED_VALUE"""),"07.04 [IMG] [AD04] Pedidos abertos") -> 07.04 [IMG] [AD04] Pedidos abertos | J100: =IFERROR(__xludf.DUMMYFUNCTION("""COMPUTED_VALUE"""),"07.04.2026 [V4] [WB] [LEADS-GRUPO-WHATS] 01") -> 07.04.2026 [V4] [WB] [LEADS-GRUPO-WHATS] 01 | K100: =LEFT(A100,10) -> 2026-04-16 | L100: =DATE(YEAR(SUBSTITUTE(SUBSTITUTE(K100,"-","/",1),"-","/",1)),MONTH(SUBSTITUTE(SUBSTITUTE(K100,"-","/",1),"-","/",1)),DAY(SUBSTITUTE(SUBSTITUTE(K100,"-","/",1),"-","/",1))) -> 46128 | M100: =RIGHT(C100,8) -> 57713604 | N100: =IFERROR(IF(VLOOKUP(M100,'Leads no grupo Saibai'!C:C,1,FALSE)=M100,"Sim"),"Não") -> Sim
...

Sheet Leads no grupo Saibai
A1: Data | B1: Numero | C1: Telefone 8 Digitos
A2: 2026-06-03T06:30:09.449+02:00 | B2: 5511992398632 | C2: =RIGHT(B2,8) -> 92398632
A3: 2026-06-03T06:30:09.449+02:00 | B3: 5511984977222 | C3: =RIGHT(B3,8) -> 84977222
A4: 2026-06-03T06:30:09.462+02:00 | B4: 5515997827051 | C4: =RIGHT(B4,8) -> 97827051
A5: 2026-04-13T19:42:21.214+02:00 | B5: 5515996897606 | C5: =RIGHT(B5,8) -> 96897606
A6: 2026-06-03T06:30:09.465+02:00 | B6: 5515991729665 | C6: =RIGHT(B6,8) -> 91729665
A7: 2026-04-25T06:31:00.222+02:00 | B7: 5515998141671 | C7: =RIGHT(B7,8) -> 98141671
A8: 2026-06-03T06:30:09.473+02:00 | B8: 5515991152300 | C8: =RIGHT(B8,8) -> 91152300
A9: 2026-04-25T06:31:00.236+02:00 | B9: 5515991956401 | C9: =RIGHT(B9,8) -> 91956401
A10: 2026-06-03T06:30:09.480+02:00 | B10: 5515998386011 | C10: =RIGHT(B10,8) -> 98386011
A11: 2026-06-03T06:30:09.481+02:00 | B11: 5515981509778 | C11: =RIGHT(B11,8) -> 81509778
A12: 2026-06-03T06:30:09.483+02:00 | B12: 5511917539658 | C12: =RIGHT(B12,8) -> 17539658
A13: 2026-06-03T06:30:09.484+02:00 | B13: 5515981118262 | C13: =RIGHT(B13,8) -> 81118262
... A284: 2026-06-03T06:30:03.716+02:00 | B284: 5511991080095 | C284: =RIGHT(B284,8) -> 91080095

Sheet 1. Sprint Growth
A1: Data do Sprint | B1: Pilar | C1: Categoria | D1: Ação 🎯 | E1: NSM | F1: Ekyte | G1: Responsável 👮 | H1: Confiança | I1: Impacto | J1: Facilidade | K1: Prioridade | L1: Prazo 📆 | M1: Status | N1: Nota Ja Faco | O1: Nota Impacto | P1: Nota Facilidade | Q1: Facilidade + Impacto | R1: Nota Prioridade
A2: 46090 | B2: Tráfego | C2: Promoção | D2: Colocar rodar ads no Meta e Google Ads. (rodando search) | F2: TRUE | G2: William Rodrigues | H2: Média | I2: Alto | J2: Fácil | K2: =IF(M2=TRUE,"Feito ✅",IF(H2="Faço bem","Já faço bem ✔",IF(R2=27,"🟩🟩🟩🟩🟩🟩🟩🟩🟩",IF(R2=18,"⬛⬛⬛⬛⬛⬛⬛⬛⬜",IF(R2=12,"⬛⬛⬛⬛⬛⬛⬛⬜⬜",IF(R2=9,"⬛⬛⬛⬛⬛⬛⬜⬜⬜",IF(R2=8,"⬛⬛⬛⬛⬛⬜⬜⬜⬜",IF(R2=6,"⬛⬛⬛⬛⬜⬜⬜⬜⬜",IF(R2=4,"⬛⬛⬛⬜⬜⬜⬜⬜⬜",IF(R2=3,"⬛⬛⬜⬜⬜⬜⬜⬜⬜",IF(R2=2,"⬛⬜⬜⬜⬜⬜⬜⬜⬜",""))))))))))) -> Feito ✅ | L2: 46091 | M2: TRUE | N2: =IF(H2="Alta",3,IF(H2="Média",2,IF(H2="Baixa",1))) -> 2 | O2: =IF(I2="Baixo",1,IF(I2="Médio",2,IF(I2="Alto",3,0))) -> 3 | P2: =IF(J2="Fácil",3,IF(J2="Médio",2,IF(J2="Difícil",1,0))) -> 3 | Q2: =IF(P2=0,"",(N2*O2)) -> 6 | R2: =IF(H2="Faço bem",0,(N2*Q2)) -> 12
A3: 46097 | B3: Tráfego | D3: Precisamos destravar campanha de engajamento. | E3: Start do projeto. | F3: FALSE | G3: William Rodrigues | K3: =IF(M3=TRUE,"Feito ✅",IF(H3="Faço bem","Já faço bem ✔",IF(R3=27,"🟩🟩🟩🟩🟩🟩🟩🟩🟩",IF(R3=18,"⬛⬛⬛⬛⬛⬛⬛⬛⬜",IF(R3=12,"⬛⬛⬛⬛⬛⬛⬛⬜⬜",IF(R3=9,"⬛⬛⬛⬛⬛⬛⬜⬜⬜",IF(R3=8,"⬛⬛⬛⬛⬛⬜⬜⬜⬜",IF(R3=6,"⬛⬛⬛⬛⬜⬜⬜⬜⬜",IF(R3=4,"⬛⬛⬛⬜⬜⬜⬜⬜⬜",IF(R3=3,"⬛⬛⬜⬜⬜⬜⬜⬜⬜",IF(R3=2,"⬛⬜⬜⬜⬜⬜⬜⬜⬜",""))))))))))) -> Feito ✅ | L3: 46098 | M3: TRUE | N3: =IF(H3="Alta",3,IF(H3="Média",2,IF(H3="Baixa",1))) -> FALSE | O3: =IF(I3="Baixo",1,IF(I3="Médio",2,IF(I3="Alto",3,0))) -> 0 | P3: =IF(J3="Fácil",3,IF(J3="Médio",2,IF(J3="Difícil",1,0))) -> 0 | Q3: =IF(P3=0,"",(N3*O3)) | R3: =IF(H3="Faço bem",0,(N3*Q3)) -> 0
A4: 46097 | B4: Tráfego | D4: Domínio da LP | E4: Start do projeto. | F4: FALSE | G4: Carlos Williame | K4: =IF(M4=TRUE,"Feito ✅",IF(H4="Faço bem","Já faço bem ✔",IF(R4=27,"🟩🟩🟩🟩🟩🟩🟩🟩🟩",IF(R4=18,"⬛⬛⬛⬛⬛⬛⬛⬛⬜",IF(R4=12,"⬛⬛⬛⬛⬛⬛⬛⬜⬜",IF(R4=9,"⬛⬛⬛⬛⬛⬛⬜⬜⬜",IF(R4=8,"⬛⬛⬛⬛⬛⬜⬜⬜⬜",IF(R4=6,"⬛⬛⬛⬛⬜⬜⬜⬜⬜",IF(R4=4,"⬛⬛⬛⬜⬜⬜⬜⬜⬜",IF(R4=3,"⬛⬛⬜⬜⬜⬜⬜⬜⬜",IF(R4=2,"⬛⬜⬜⬜⬜⬜⬜⬜⬜",""))))))))))) -> Feito ✅ | L4: 46098 | M4: TRUE | N4: =IF(H4="Alta",3,IF(H4="Média",2,IF(H4="Baixa",1))) -> FALSE | O4: =IF(I4="Baixo",1,IF(I4="Médio",2,IF(I4="Alto",3,0))) -> 0 | P4: =IF(J4="Fácil",3,IF(J4="Médio",2,IF(J4="Difícil",1,0))) -> 0 | Q4: =IF(P4=0,"",(N4*O4)) | R4: =IF(H4="Faço bem",0,(N4*Q4)) -> 0
A5: 46153 | B5: Tráfego | D5: criar campanha e grupo para SP capital | E5: Start do projeto. | F5: FALSE | G5: William Rodrigues | H5: Alta | I5: Médio | J5: Médio | K5: =IF(M5=TRUE,"Feito ✅",IF(H5="Faço bem","Já faço bem ✔",IF(R5=27,"🟩🟩🟩🟩🟩🟩🟩🟩🟩",IF(R5=18,"⬛⬛⬛⬛⬛⬛⬛⬛⬜",IF(R5=12,"⬛⬛⬛⬛⬛⬛⬛⬜⬜",IF(R5=9,"⬛⬛⬛⬛⬛⬛⬜⬜⬜",IF(R5=8,"⬛⬛⬛⬛⬛⬜⬜⬜⬜",IF(R5=6,"⬛⬛⬛⬛⬜⬜⬜⬜⬜",IF(R5=4,"⬛⬛⬛⬜⬜⬜⬜⬜⬜",IF(R5=3,"⬛⬛⬜⬜⬜⬜⬜⬜⬜",IF(R5=2,"⬛⬜⬜⬜⬜⬜⬜⬜⬜",""))))))))))) -> Feito ✅ | L5: 46101 | M5: TRUE | N5: =IF(H5="Alta",3,IF(H5="Média",2,IF(H5="Baixa",1))) -> 3 | O5: =IF(I5="Baixo",1,IF(I5="Médio",2,IF(I5="Alto",3,0))) -> 2 | P5: =IF(J5="Fácil",3,IF(J5="Médio",2,IF(J5="Difícil",1,0))) -> 2 | Q5: =IF(P5=0,"",(N5*O5)) -> 6 | R5: =IF(H5="Faço bem",0,(N5*Q5)) -> 18
A6: 46134 | B6: Tráfego | D6: Fazer alimentação do grupo vip whatsapp | E6: Start do projeto. | F6: FALSE | G6: William Rodrigues | H6: Alta | I6: Médio | J6: Médio | K6: =IF(M6=TRUE,"Feito ✅",IF(H6="Faço bem","Já faço bem ✔",IF(R6=27,"🟩🟩🟩🟩🟩🟩🟩🟩🟩",IF(R6=18,"⬛⬛⬛⬛⬛⬛⬛⬛⬜",IF(R6=12,"⬛⬛⬛⬛⬛⬛⬛⬜⬜",IF(R6=9,"⬛⬛⬛⬛⬛⬛⬜⬜⬜",IF(R6=8,"⬛⬛⬛⬛⬛⬜⬜⬜⬜",IF(R6=6,"⬛⬛⬛⬛⬜⬜⬜⬜⬜",IF(R6=4,"⬛⬛⬛⬜⬜⬜⬜⬜⬜",IF(R6=3,"⬛⬛⬜⬜⬜⬜⬜⬜⬜",IF(R6=2,"⬛⬜⬜⬜⬜⬜⬜⬜⬜",""))))))))))) -> Feito ✅ | L6: 46101 | M6: TRUE | N6: =IF(H6="Alta",3,IF(H6="Média",2,IF(H6="Baixa",1))) -> 3 | O6: =IF(I6="Baixo",1,IF(I6="Médio",2,IF(I6="Alto",3,0))) -> 2 | P6: =IF(J6="Fácil",3,IF(J6="Médio",2,IF(J6="Difícil",1,0))) -> 2 | Q6: =IF(P6=0,"",(N6*O6)) -> 6 | R6: =IF(H6="Faço bem",0,(N6*Q6)) -> 18
A7: 46153 | B7: Tráfego | D7: criar campanha e grupo para SP capital | E7: Start do projeto. | F7: FALSE | G7: William Rodrigues | H7: Alta | I7: Médio | J7: Médio | K7: =IF(M7=TRUE,"Feito ✅",IF(H7="Faço bem","Já faço bem ✔",IF(R7=27,"🟩🟩🟩🟩🟩🟩🟩🟩🟩",IF(R7=18,"⬛⬛⬛⬛⬛⬛⬛⬛⬜",IF(R7=12,"⬛⬛⬛⬛⬛⬛⬛⬜⬜",IF(R7=9,"⬛⬛⬛⬛⬛⬛⬜⬜⬜",IF(R7=8,"⬛⬛⬛⬛⬛⬜⬜⬜⬜",IF(R7=6,"⬛⬛⬛⬛⬜⬜⬜⬜⬜",IF(R7=4,"⬛⬛⬛⬜⬜⬜⬜⬜⬜",IF(R7=3,"⬛⬛⬜⬜⬜⬜⬜⬜⬜",IF(R7=2,"⬛⬜⬜⬜⬜⬜⬜⬜⬜",""))))))))))) -> Feito ✅ | L7: 46156 | M7: TRUE | N7: =IF(H7="Alta",3,IF(H7="Média",2,IF(H7="Baixa",1))) -> 3 | O7: =IF(I7="Baixo",1,IF(I7="Médio",2,IF(I7="Alto",3,0))) -> 2 | P7: =IF(J7="Fácil",3,IF(J7="Médio",2,IF(J7="Difícil",1,0))) -> 2 | Q7: =IF(P7=0,"",(N7*O7)) -> 6 | R7: =IF(H7="Faço bem",0,(N7*Q7)) -> 18
A8: 46153 | B8: Tráfego | D8: Adicionar saldo nas campanhas | E8: Start do projeto. | F8: FALSE | G8: William Rodrigues | H8: Alta | I8: Médio | J8: Médio | K8: =IF(M8=TRUE,"Feito ✅",IF(H8="Faço bem","Já faço bem ✔",IF(R8=27,"🟩🟩🟩🟩🟩🟩🟩🟩🟩",IF(R8=18,"⬛⬛⬛⬛⬛⬛⬛⬛⬜",IF(R8=12,"⬛⬛⬛⬛⬛⬛⬛⬜⬜",IF(R8=9,"⬛⬛⬛⬛⬛⬛⬜⬜⬜",IF(R8=8,"⬛⬛⬛⬛⬛⬜⬜⬜⬜",IF(R8=6,"⬛⬛⬛⬛⬜⬜⬜⬜⬜",IF(R8=4,"⬛⬛⬛⬜⬜⬜⬜⬜⬜",IF(R8=3,"⬛⬛⬜⬜⬜⬜⬜⬜⬜",IF(R8=2,"⬛⬜⬜⬜⬜⬜⬜⬜⬜",""))))))))))) -> Feito ✅ | L8: 46156 | M8: TRUE | N8: =IF(H8="Alta",3,IF(H8="Média",2,IF(H8="Baixa",1))) -> 3 | O8: =IF(I8="Baixo",1,IF(I8="Médio",2,IF(I8="Alto",3,0))) -> 2 | P8: =IF(J8="Fácil",3,IF(J8="Médio",2,IF(J8="Difícil",1,0))) -> 2 | Q8: =IF(P8=0,"",(N8*O8)) -> 6 | R8: =IF(H8="Faço bem",0,(N8*Q8)) -> 18
A9: 46153 | B9: Tráfego | D9: Dar acesso ao everton na conta do meta ads | E9: Start do projeto. | F9: FALSE | G9: William Rodrigues | H9: Alta | I9: Médio | J9: Médio | K9: =IF(M9=TRUE,"Feito ✅",IF(H9="Faço bem","Já faço bem ✔",IF(R9=27,"🟩🟩🟩🟩🟩🟩🟩🟩🟩",IF(R9=18,"⬛⬛⬛⬛⬛⬛⬛⬛⬜",IF(R9=12,"⬛⬛⬛⬛⬛⬛⬛⬜⬜",IF(R9=9,"⬛⬛⬛⬛⬛⬛⬜⬜⬜",IF(R9=8,"⬛⬛⬛⬛⬛⬜⬜⬜⬜",IF(R9=6,"⬛⬛⬛⬛⬜⬜⬜⬜⬜",IF(R9=4,"⬛⬛⬛⬜⬜⬜⬜⬜⬜",IF(R9=3,"⬛⬛⬜⬜⬜⬜⬜⬜⬜",IF(R9=2,"⬛⬜⬜⬜⬜⬜⬜⬜⬜",""))))))))))) -> Feito ✅ | L9: 46156 | M9: TRUE | N9: =IF(H9="Alta",3,IF(H9="Média",2,IF(H9="Baixa",1))) -> 3 | O9: =IF(I9="Baixo",1,IF(I9="Médio",2,IF(I9="Alto",3,0))) -> 2 | P9: =IF(J9="Fácil",3,IF(J9="Médio",2,IF(J9="Difícil",1,0))) -> 2 | Q9: =IF(P9=0,"",(N9*O9)) -> 6 | R9: =IF(H9="Faço bem",0,(N9*Q9)) -> 18
A10: 46153 | B10: Tráfego | D10: Revisar e-com estrutural e copy (Colocar link da planilha de acessos) | E10: Start do projeto. | F10: FALSE | G10: Everton da Silva | H10: Alta | I10: Médio | J10: Médio | K10: =IF(M10=TRUE,"Feito ✅",IF(H10="Faço bem","Já faço bem ✔",IF(R10=27,"🟩🟩🟩🟩🟩🟩🟩🟩🟩",IF(R10=18,"⬛⬛⬛⬛⬛⬛⬛⬛⬜",IF(R10=12,"⬛⬛⬛⬛⬛⬛⬛⬜⬜",IF(R10=9,"⬛⬛⬛⬛⬛⬛⬜⬜⬜",IF(R10=8,"⬛⬛⬛⬛⬛⬜⬜⬜⬜",IF(R10=6,"⬛⬛⬛⬛⬜⬜⬜⬜⬜",IF(R10=4,"⬛⬛⬛⬜⬜⬜⬜⬜⬜",IF(R10=3,"⬛⬛⬜⬜⬜⬜⬜⬜⬜",IF(R10=2,"⬛⬜⬜⬜⬜⬜⬜⬜⬜",""))))))))))) -> Feito ✅ | L10: 46156 | M10: TRUE | N10: =IF(H10="Alta",3,IF(H10="Média",2,IF(H10="Baixa",1))) -> 3 | O10: =IF(I10="Baixo",1,IF(I10="Médio",2,IF(I10="Alto",3,0))) -> 2 | P10: =IF(J10="Fácil",3,IF(J10="Médio",2,IF(J10="Difícil",1,0))) -> 2 | Q10: =IF(P10=0,"",(N10*O10)) -> 6 | R10: =IF(H10="Faço bem",0,(N10*Q10)) -> 18
A11: 46153 | B11: Tráfego | D11: Trocar link do grupa para fazer pedido no whatsapp | E11: Start do projeto. | F11: FALSE | G11: William Rodrigues | H11: Média | I11: Médio | J11: Médio | K11: =IF(M11=TRUE,"Feito ✅",IF(H11="Faço bem","Já faço bem ✔",IF(R11=27,"🟩🟩🟩🟩🟩🟩🟩🟩🟩",IF(R11=18,"⬛⬛⬛⬛⬛⬛⬛⬛⬜",IF(R11=12,"⬛⬛⬛⬛⬛⬛⬛⬜⬜",IF(R11=9,"⬛⬛⬛⬛⬛⬛⬜⬜⬜",IF(R11=8,"⬛⬛⬛⬛⬛⬜⬜⬜⬜",IF(R11=6,"⬛⬛⬛⬛⬜⬜⬜⬜⬜",IF(R11=4,"⬛⬛⬛⬜⬜⬜⬜⬜⬜",IF(R11=3,"⬛⬛⬜⬜⬜⬜⬜⬜⬜",IF(R11=2,"⬛⬜⬜⬜⬜⬜⬜⬜⬜",""))))))))))) -> Feito ✅ | L11: 46162 | M11: TRUE | N11: =IF(H11="Alta",3,IF(H11="Média",2,IF(H11="Baixa",1))) -> 2 | O11: =IF(I11="Baixo",1,IF(I11="Médio",2,IF(I11="Alto",3,0))) -> 2 | P11: =IF(J11="Fácil",3,IF(J11="Médio",2,IF(J11="Difícil",1,0))) -> 2 | Q11: =IF(P11=0,"",(N11*O11)) -> 4 | R11: =IF(H11="Faço bem",0,(N11*Q11)) -> 8
A12: 46167 | B12: Tráfego | D12: Revisão dos textos dos grupos | E12: Start do projeto. | F12: FALSE | G12: William Rodrigues | H12: Média | I12: Médio | J12: Médio | K12: =IF(M12=TRUE,"Feito ✅",IF(H12="Faço bem","Já faço bem ✔",IF(R12=27,"🟩🟩🟩🟩🟩🟩🟩🟩🟩",IF(R12=18,"⬛⬛⬛⬛⬛⬛⬛⬛⬜",IF(R12=12,"⬛⬛⬛⬛⬛⬛⬛⬜⬜",IF(R12=9,"⬛⬛⬛⬛⬛⬛⬜⬜⬜",IF(R12=8,"⬛⬛⬛⬛⬛⬜⬜⬜⬜",IF(R12=6,"⬛⬛⬛⬛⬜⬜⬜⬜⬜",IF(R12=4,"⬛⬛⬛⬜⬜⬜⬜⬜⬜",IF(R12=3,"⬛⬛⬜⬜⬜⬜⬜⬜⬜",IF(R12=2,"⬛⬜⬜⬜⬜⬜⬜⬜⬜",""))))))))))) -> Feito ✅ | L12: 46171 | M12: TRUE | N12: =IF(H12="Alta",3,IF(H12="Média",2,IF(H12="Baixa",1))) -> 2 | O12: =IF(I12="Baixo",1,IF(I12="Médio",2,IF(I12="Alto",3,0))) -> 2 | P12: =IF(J12="Fácil",3,IF(J12="Médio",2,IF(J12="Difícil",1,0))) -> 2 | Q12: =IF(P12=0,"",(N12*O12)) -> 4 | R12: =IF(H12="Faço bem",0,(N12*Q12)) -> 8
A13: 46167 | B13: Tráfego | D13: Revisão da Copy da LP | E13: Start do projeto. | F13: FALSE | G13: William Rodrigues | H13: Média | I13: Médio | J13: Médio | K13: =IF(M13=TRUE,"Feito ✅",IF(H13="Faço bem","Já faço bem ✔",IF(R13=27,"🟩🟩🟩🟩🟩🟩🟩🟩🟩",IF(R13=18,"⬛⬛⬛⬛⬛⬛⬛⬛⬜",IF(R13=12,"⬛⬛⬛⬛⬛⬛⬛⬜⬜",IF(R13=9,"⬛⬛⬛⬛⬛⬛⬜⬜⬜",IF(R13=8,"⬛⬛⬛⬛⬛⬜⬜⬜⬜",IF(R13=6,"⬛⬛⬛⬛⬜⬜⬜⬜⬜",IF(R13=4,"⬛⬛⬛⬜⬜⬜⬜⬜⬜",IF(R13=3,"⬛⬛⬜⬜⬜⬜⬜⬜⬜",IF(R13=2,"⬛⬜⬜⬜⬜⬜⬜⬜⬜",""))))))))))) -> Feito ✅ | L13: 46171 | M13: TRUE | N13: =IF(H13="Alta",3,IF(H13="Média",2,IF(H13="Baixa",1))) -> 2 | O13: =IF(I13="Baixo",1,IF(I13="Médio",2,IF(I13="Alto",3,0))) -> 2 | P13: =IF(J13="Fácil",3,IF(J13="Médio",2,IF(J13="Difícil",1,0))) -> 2 | Q13: =IF(P13=0,"",(N13*O13)) -> 4 | R13: =IF(H13="Faço bem",0,(N13*Q13)) -> 8
A14: 46167 | B14: Tráfego | D14: Ver com Otávio desconto dos grupos VIP'S | E14: Start do projeto. | F14: FALSE | G14: William Rodrigues | H14: Média | I14: Médio | J14: Médio | K14: =IF(M14=TRUE,"Feito ✅",IF(H14="Faço bem","Já faço bem ✔",IF(R14=27,"🟩🟩🟩🟩🟩🟩🟩🟩🟩",IF(R14=18,"⬛⬛⬛⬛⬛⬛⬛⬛⬜",IF(R14=12,"⬛⬛⬛⬛⬛⬛⬛⬜⬜",IF(R14=9,"⬛⬛⬛⬛⬛⬛⬜⬜⬜",IF(R14=8,"⬛⬛⬛⬛⬛⬜⬜⬜⬜",IF(R14=6,"⬛⬛⬛⬛⬜⬜⬜⬜⬜",IF(R14=4,"⬛⬛⬛⬜⬜⬜⬜⬜⬜",IF(R14=3,"⬛⬛⬜⬜⬜⬜⬜⬜⬜",IF(R14=2,"⬛⬜⬜⬜⬜⬜⬜⬜⬜",""))))))))))) -> Feito ✅ | L14: 46169 | M14: TRUE | N14: =IF(H14="Alta",3,IF(H14="Média",2,IF(H14="Baixa",1))) -> 2 | O14: =IF(I14="Baixo",1,IF(I14="Médio",2,IF(I14="Alto",3,0))) -> 2 | P14: =IF(J14="Fácil",3,IF(J14="Médio",2,IF(J14="Difícil",1,0))) -> 2 | Q14: =IF(P14=0,"",(N14*O14)) -> 4 | R14: =IF(H14="Faço bem",0,(N14*Q14)) -> 8
A15: 46167 | B15: Tráfego | D15: Rodar videos da Clara | E15: Start do projeto. | F15: FALSE | G15: William Rodrigues | H15: Média | I15: Médio | J15: Médio | K15: =IF(M15=TRUE,"Feito ✅",IF(H15="Faço bem","Já faço bem ✔",IF(R15=27,"🟩🟩🟩🟩🟩🟩🟩🟩🟩",IF(R15=18,"⬛⬛⬛⬛⬛⬛⬛⬛⬜",IF(R15=12,"⬛⬛⬛⬛⬛⬛⬛⬜⬜",IF(R15=9,"⬛⬛⬛⬛⬛⬛⬜⬜⬜",IF(R15=8,"⬛⬛⬛⬛⬛⬜⬜⬜⬜",IF(R15=6,"⬛⬛⬛⬛⬜⬜⬜⬜⬜",IF(R15=4,"⬛⬛⬛⬜⬜⬜⬜⬜⬜",IF(R15=3,"⬛⬛⬜⬜⬜⬜⬜⬜⬜",IF(R15=2,"⬛⬜⬜⬜⬜⬜⬜⬜⬜",""))))))))))) -> Feito ✅ | L15: 46168 | M15: TRUE | N15: =IF(H15="Alta",3,IF(H15="Média",2,IF(H15="Baixa",1))) -> 2 | O15: =IF(I15="Baixo",1,IF(I15="Médio",2,IF(I15="Alto",3,0))) -> 2 | P15: =IF(J15="Fácil",3,IF(J15="Médio",2,IF(J15="Difícil",1,0))) -> 2 | Q15: =IF(P15=0,"",(N15*O15)) -> 4 | R15: =IF(H15="Faço bem",0,(N15*Q15)) -> 8
A16: 46167 | B16: Tráfego | D16: Ver possibilidade de monetizar outros produtos | E16: Start do projeto. | F16: FALSE | G16: William Rodrigues | H16: Média | I16: Médio | J16: Médio | K16: =IF(M16=TRUE,"Feito ✅",IF(H16="Faço bem","Já faço bem ✔",IF(R16=27,"🟩🟩🟩🟩🟩🟩🟩🟩🟩",IF(R16=18,"⬛⬛⬛⬛⬛⬛⬛⬛⬜",IF(R16=12,"⬛⬛⬛⬛⬛⬛⬛⬜⬜",IF(R16=9,"⬛⬛⬛⬛⬛⬛⬜⬜⬜",IF(R16=8,"⬛⬛⬛⬛⬛⬜⬜⬜⬜",IF(R16=6,"⬛⬛⬛⬛⬜⬜⬜⬜⬜",IF(R16=4,"⬛⬛⬛⬜⬜⬜⬜⬜⬜",IF(R16=3,"⬛⬛⬜⬜⬜⬜⬜⬜⬜",IF(R16=2,"⬛⬜⬜⬜⬜⬜⬜⬜⬜",""))))))))))) -> Feito ✅ | L16: 46169 | M16: TRUE | N16: =IF(H16="Alta",3,IF(H16="Média",2,IF(H16="Baixa",1))) -> 2 | O16: =IF(I16="Baixo",1,IF(I16="Médio",2,IF(I16="Alto",3,0))) -> 2 | P16: =IF(J16="Fácil",3,IF(J16="Médio",2,IF(J16="Difícil",1,0))) -> 2 | Q16: =IF(P16=0,"",(N16*O16)) -> 4 | R16: =IF(H16="Faço bem",0,(N16*Q16)) -> 8
... A18: 46167 | B18: Tráfego | D18: Clara - colocar catalogo no whatsapp | E18: Start do projeto. | F18: FALSE | G18: William Rodrigues | H18: Média | I18: Médio | J18: Médio | K18: =IF(M18=TRUE,"Feito ✅",IF(H18="Faço bem","Já faço bem ✔",IF(R18=27,"🟩🟩🟩🟩🟩🟩🟩🟩🟩",IF(R18=18,"⬛⬛⬛⬛⬛⬛⬛⬛⬜",IF(R18=12,"⬛⬛⬛⬛⬛⬛⬛⬜⬜",IF(R18=9,"⬛⬛⬛⬛⬛⬛⬜⬜⬜",IF(R18=8,"⬛⬛⬛⬛⬛⬜⬜⬜⬜",IF(R18=6,"⬛⬛⬛⬛⬜⬜⬜⬜⬜",IF(R18=4,"⬛⬛⬛⬜⬜⬜⬜⬜⬜",IF(R18=3,"⬛⬛⬜⬜⬜⬜⬜⬜⬜",IF(R18=2,"⬛⬜⬜⬜⬜⬜⬜⬜⬜",""))))))))))) -> Feito ✅ | L18: 46169 | M18: TRUE | N18: =IF(H18="Alta",3,IF(H18="Média",2,IF(H18="Baixa",1))) -> 2 | O18: =IF(I18="Baixo",1,IF(I18="Médio",2,IF(I18="Alto",3,0))) -> 2 | P18: =IF(J18="Fácil",3,IF(J18="Médio",2,IF(J18="Difícil",1,0))) -> 2 | Q18: =IF(P18=0,"",(N18*O18)) -> 4 | R18: =IF(H18="Faço bem",0,(N18*Q18)) -> 8
N19: =IF(H19="Alta",3,IF(H19="Média",2,IF(H19="Baixa",1))) -> FALSE | O19: =IF(I19="Baixo",1,IF(I19="Médio",2,IF(I19="Alto",3,0))) -> 0 | P19: =IF(J19="Fácil",3,IF(J19="Médio",2,IF(J19="Difícil",1,0))) -> 0 | Q19: =IF(P19=0,"",(N19*O19)) | R19: =IF(H19="Faço bem",0,(N19*Q19)) -> 0
N20: =IF(H20="Alta",3,IF(H20="Média",2,IF(H20="Baixa",1))) -> FALSE | O20: =IF(I20="Baixo",1,IF(I20="Médio",2,IF(I20="Alto",3,0))) -> 0 | P20: =IF(J20="Fácil",3,IF(J20="Médio",2,IF(J20="Difícil",1,0))) -> 0 | Q20: =IF(P20=0,"",(N20*O20)) | R20: =IF(H20="Faço bem",0,(N20*Q20)) -> 0
N21: =IF(H21="Alta",3,IF(H21="Média",2,IF(H21="Baixa",1))) -> FALSE | O21: =IF(I21="Baixo",1,IF(I21="Médio",2,IF(I21="Alto",3,0))) -> 0 | P21: =IF(J21="Fácil",3,IF(J21="Médio",2,IF(J21="Difícil",1,0))) -> 0 | Q21: =IF(P21=0,"",(N21*O21)) | R21: =IF(H21="Faço bem",0,(N21*Q21)) -> 0
N22: =IF(H22="Alta",3,IF(H22="Média",2,IF(H22="Baixa",1))) -> FALSE | O22: =IF(I22="Baixo",1,IF(I22="Médio",2,IF(I22="Alto",3,0))) -> 0 | P22: =IF(J22="Fácil",3,IF(J22="Médio",2,IF(J22="Difícil",1,0))) -> 0 | Q22: =IF(P22=0,"",(N22*O22)) | R22: =IF(H22="Faço bem",0,(N22*Q22)) -> 0
N23: =IF(H23="Alta",3,IF(H23="Média",2,IF(H23="Baixa",1))) -> FALSE | O23: =IF(I23="Baixo",1,IF(I23="Médio",2,IF(I23="Alto",3,0))) -> 0 | P23: =IF(J23="Fácil",3,IF(J23="Médio",2,IF(J23="Difícil",1,0))) -> 0 | Q23: =IF(P23=0,"",(N23*O23)) | R23: =IF(H23="Faço bem",0,(N23*Q23)) -> 0
N24: =IF(H24="Alta",3,IF(H24="Média",2,IF(H24="Baixa",1))) -> FALSE | O24: =IF(I24="Baixo",1,IF(I24="Médio",2,IF(I24="Alto",3,0))) -> 0 | P24: =IF(J24="Fácil",3,IF(J24="Médio",2,IF(J24="Difícil",1,0))) -> 0 | Q24: =IF(P24=0,"",(N24*O24)) | R24: =IF(H24="Faço bem",0,(N24*Q24)) -> 0
N25: =IF(H25="Alta",3,IF(H25="Média",2,IF(H25="Baixa",1))) -> FALSE | O25: =IF(I25="Baixo",1,IF(I25="Médio",2,IF(I25="Alto",3,0))) -> 0 | P25: =IF(J25="Fácil",3,IF(J25="Médio",2,IF(J25="Difícil",1,0))) -> 0 | Q25: =IF(P25=0,"",(N25*O25)) | R25: =IF(H25="Faço bem",0,(N25*Q25)) -> 0
N26: =IF(H26="Alta",3,IF(H26="Média",2,IF(H26="Baixa",1))) -> FALSE | O26: =IF(I26="Baixo",1,IF(I26="Médio",2,IF(I26="Alto",3,0))) -> 0 | P26: =IF(J26="Fácil",3,IF(J26="Médio",2,IF(J26="Difícil",1,0))) -> 0 | Q26: =IF(P26=0,"",(N26*O26)) | R26: =IF(H26="Faço bem",0,(N26*Q26)) -> 0
N27: =IF(H27="Alta",3,IF(H27="Média",2,IF(H27="Baixa",1))) -> FALSE | O27: =IF(I27="Baixo",1,IF(I27="Médio",2,IF(I27="Alto",3,0))) -> 0 | P27: =IF(J27="Fácil",3,IF(J27="Médio",2,IF(J27="Difícil",1,0))) -> 0 | Q27: =IF(P27=0,"",(N27*O27)) | R27: =IF(H27="Faço bem",0,(N27*Q27)) -> 0
N28: =IF(H28="Alta",3,IF(H28="Média",2,IF(H28="Baixa",1))) -> FALSE | O28: =IF(I28="Baixo",1,IF(I28="Médio",2,IF(I28="Alto",3,0))) -> 0 | P28: =IF(J28="Fácil",3,IF(J28="Médio",2,IF(J28="Difícil",1,0))) -> 0 | Q28: =IF(P28=0,"",(N28*O28)) | R28: =IF(H28="Faço bem",0,(N28*Q28)) -> 0
N29: =IF(H29="Alta",3,IF(H29="Média",2,IF(H29="Baixa",1))) -> FALSE | O29: =IF(I29="Baixo",1,IF(I29="Médio",2,IF(I29="Alto",3,0))) -> 0 | P29: =IF(J29="Fácil",3,IF(J29="Médio",2,IF(J29="Difícil",1,0))) -> 0 | Q29: =IF(P29=0,"",(N29*O29)) | R29: =IF(H29="Faço bem",0,(N29*Q29)) -> 0
N30: =IF(H30="Alta",3,IF(H30="Média",2,IF(H30="Baixa",1))) -> FALSE | O30: =IF(I30="Baixo",1,IF(I30="Médio",2,IF(I30="Alto",3,0))) -> 0 | P30: =IF(J30="Fácil",3,IF(J30="Médio",2,IF(J30="Difícil",1,0))) -> 0 | Q30: =IF(P30=0,"",(N30*O30)) | R30: =IF(H30="Faço bem",0,(N30*Q30)) -> 0
... N95: =IF(H95="Alta",3,IF(H95="Média",2,IF(H95="Baixa",1))) -> FALSE | O95: =IF(I95="Baixo",1,IF(I95="Médio",2,IF(I95="Alto",3,0))) -> 0 | P95: =IF(J95="Fácil",3,IF(J95="Médio",2,IF(J95="Difícil",1,0))) -> 0 | Q95: =IF(P95=0,"",(N95*O95)) | R95: =IF(H95="Faço bem",0,(N95*Q95)) -> 0

Sheet 2. Relatório Consolidado Semana
A1: Funil Inside Sales 2025
A2: Data inicio | B2: 46082 | C2: =B2+7 -> 46089 | D2: =C2+7 -> 46096 | E2: =D2+7 -> 46103 | F2: =E2+7 -> 46110 | G2: 46082 | H2: =F2+7 -> 46117 | I2: =H2+7 -> 46124 | J2: =I2+7 -> 46131 | K2: =J2+7 -> 46138 | L2: 46113 | M2: =K2+7 -> 46145 | N2: =M2+7 -> 46152 | O2: =N2+7 -> 46159 | P2: =O2+7 -> 46166 | Q2: 46143 | R2: =P2+7 -> 46173 | S2: =R2+7 -> 46180 | T2: =S2+7 -> 46187 | U2: =T2+7 -> 46194 | V2: 46174
A3: Data fim | B3: 46088 | C3: =B3+7 -> 46095 | D3: =C3+7 -> 46102 | E3: =D3+7 -> 46109 | F3: =E3+7 -> 46116 | G3: 46112 | H3: =F3+7 -> 46123 | I3: =H3+7 -> 46130 | J3: =I3+7 -> 46137 | K3: =J3+7 -> 46144 | L3: 46142 | M3: =K3+7 -> 46151 | N3: =M3+7 -> 46158 | O3: =N3+7 -> 46165 | P3: =O3+7 -> 46172 | Q3: 46173 | R3: =P3+7 -> 46179 | S3: =R3+7 -> 46186 | T3: =S3+7 -> 46193 | U3: =T3+7 -> 46200 | V3: 46203
A5: Dados Totais
A6: Semanas | B6: =B2 -> 46082 | C6: =C2 -> 46089 | D6: =D2 -> 46096 | E6: =E2 -> 46103 | F6: =F2 -> 46110 | G6: Março | H6: =H2 -> 46117 | I6: =I2 -> 46124 | J6: =J2 -> 46131 | K6: =K2 -> 46138 | L6: Abril | M6: =M2 -> 46145 | N6: =N2 -> 46152 | O6: =O2 -> 46159 | P6: =P2 -> 46166 | Q6: Maio | R6: =R2 -> 46173 | S6: =S2 -> 46180 | T6: =T2 -> 46187 | U6: =U2 -> 46194 | V6: Junho
A7: Investido | B7: =IFERROR(SUM(B49,B81)," ") -> 20.73 | C7: =IFERROR(SUM(C49,C81)," ") -> 35.93 | D7: =IFERROR(SUM(D49,D81)," ") -> 165.54 | E7: =IFERROR(SUM(E49,E81)," ") -> 208.31 | F7: =IFERROR(SUM(F49,F81)," ") -> 354.67 | G7: =IFERROR(SUM(G49,G81)," ") -> 525.29 | H7: =IFERROR(SUM(H49,H81)," ") -> 496.12 | I7: =IFERROR(SUM(I49,I81)," ") -> 726.76 | ... V7: =IFERROR(SUM(V49,V81)," ") -> 123.89
A8: Faturado | B8: =IFERROR(SUM(B50,B82)," ") -> 0 | C8: =IFERROR(SUM(C50,C82)," ") -> 0 | D8: =IFERROR(SUM(D50,D82)," ") -> 0 | E8: =IFERROR(SUM(E50,E82)," ") -> 0 | F8: =IFERROR(SUM(F50,F82)," ") -> 0 | G8: =IFERROR(SUM(G50,G82)," ") -> 0 | H8: =IFERROR(SUM(H50,H82)," ") -> 0 | I8: =IFERROR(SUM(I50,I82)," ") -> 0 | ... V8: =IFERROR(SUM(V50,V82)," ") -> 0
A10: Impressões | B10: =IFERROR(SUM(B52,B84)," ") -> 51 | C10: =IFERROR(SUM(C52,C84)," ") -> 61 | D10: =IFERROR(SUM(D52,D84)," ") -> 11902 | E10: =IFERROR(SUM(E52,E84)," ") -> 27639 | F10: =IFERROR(SUM(F52,F84)," ") -> 41646 | G10: =IFERROR(SUM(G52,G84)," ") -> 57382 | H10: =IFERROR(SUM(H52,H84)," ") -> 41483 | I10: =IFERROR(SUM(I52,I84)," ") -> 51546 | ... V10: =IFERROR(SUM(V52,V84)," ") -> 6323
A11: Cliques | B11: =IFERROR(SUM(B53,B85)," ") -> 13 | C11: =IFERROR(SUM(C53,C85)," ") -> 13 | D11: =IFERROR(SUM(D53,D85)," ") -> 26 | E11: =IFERROR(SUM(E53,E85)," ") -> 35 | F11: =IFERROR(SUM(F53,F85)," ") -> 112 | G11: =IFERROR(SUM(G53,G85)," ") -> 119 | H11: =IFERROR(SUM(H53,H85)," ") -> 524 | I11: =IFERROR(SUM(I53,I85)," ") -> 1359 | ... V11: =IFERROR(SUM(V53,V85)," ") -> 304
A12: Lead | B12: =IFERROR(SUM(B54,B86)," ") -> 0 | C12: =IFERROR(SUM(C54,C86)," ") -> 0 | D12: =IFERROR(SUM(D54,D86)," ") -> 0 | E12: =IFERROR(SUM(E54,E86)," ") -> 0 | F12: =IFERROR(SUM(F54,F86)," ") -> 0 | G12: =IFERROR(SUM(G54,G86)," ") -> 0 | H12: =IFERROR(SUM(H54,H86)," ") -> 3 | I12: =IFERROR(SUM(I54,I86)," ") -> 5 | ... V12: =IFERROR(SUM(V54,V86)," ") -> 9
A13: Lead Converteu P/Grupo | H13: =H87 -> 25 | I13: =I87 -> 105 | J13: =J87 -> 35 | K13: =K87 -> 6 | L13: =L87 -> 168 | M13: =M87 -> 10 | N13: =N87 -> 11 | O13: =O87 -> 39 | P13: =P87 -> 49 | Q13: =Q54+Q87 -> 127 | R13: =R87 -> 36 | S13: =S87 -> 0 | T13: =T87 -> 0 | U13: =U87 -> 0 | V13: =V54+V87 -> 26
A14: Lead entrou no grupo | H14: =H88 -> 15 | I14: =I88 -> 83 | J14: =J88 -> 23 | K14: =K88 -> 5 | L14: =L88 -> 123 | M14: =M88 -> 6 | N14: =N88 -> 8 | O14: =O88 -> 26 | P14: =P88 -> 39 | Q14: =Q55+Q88 -> 92 | R14: =R88 -> 28 | S14: =S88 -> 0 | T14: =T88 -> 0 | U14: =U88 -> 0 | V14: =V55+V88 -> 21
A15: MQL (Lead Qualificado) | B15: =IFERROR(SUM(B56,B89)," ") -> 0 | C15: =IFERROR(SUM(C56,C89)," ") -> 0 | D15: =IFERROR(SUM(D56,D89)," ") -> 0 | E15: =IFERROR(SUM(E56,E89)," ") -> 0 | F15: =IFERROR(SUM(F56,F89)," ") -> 0 | G15: =IFERROR(SUM(G56,G89)," ") -> 0 | H15: =IFERROR(SUM(H56,H89)," ") -> 0 | I15: =IFERROR(SUM(I56,I89)," ") -> 0 | ... V15: =IFERROR(SUM(V56,V89)," ") -> 0
A16: SQL (Oportunidade) | B16: =IFERROR(SUM(B57,B90)," ") -> 0 | C16: =IFERROR(SUM(C57,C90)," ") -> 0 | D16: =IFERROR(SUM(D57,D90)," ") -> 0 | E16: =IFERROR(SUM(E57,E90)," ") -> 0 | F16: =IFERROR(SUM(F57,F90)," ") -> 0 | G16: =IFERROR(SUM(G57,G90)," ") -> 0 | H16: =IFERROR(SUM(H57,H90)," ") -> 0 | I16: =IFERROR(SUM(I57,I90)," ") -> 0 | ... V16: =IFERROR(SUM(V57,V90)," ") -> 0
A17: Venda | B17: =IFERROR(SUM(B58,B91)," ") -> 0 | C17: =IFERROR(SUM(C58,C91)," ") -> 0 | D17: =IFERROR(SUM(D58,D91)," ") -> 0 | E17: =IFERROR(SUM(E58,E91)," ") -> 0 | F17: =IFERROR(SUM(F58,F91)," ") -> 0 | G17: =IFERROR(SUM(G58,G91)," ") -> 0 | H17: =IFERROR(SUM(H58,H91)," ") -> 0 | I17: =IFERROR(SUM(I58,I91)," ") -> 0 | ... V17: =IFERROR(SUM(V58,V91)," ") -> 0
A19: CTR | B19: =IFERROR(B11/B10,"") -> 0.25490196 | C19: =IFERROR(C11/C10,"") -> 0.21311475 | D19: =IFERROR(D11/D10,"") -> 0.0021845068 | E19: =IFERROR(E11/E10,"") -> 0.0012663266 | F19: =IFERROR(F11/F10,"") -> 0.0026893339 | G19: =IFERROR(G11/G10,"") -> 0.0020738211 | H19: =IFERROR(H11/H10,"") -> 0.01263168 | I19: =IFERROR(I11/I10,"") -> 0.0263648 | ... V19: =IFERROR(V11/V10,"") -> 0.048078444
A20: Tx Clique em Lead | B20: =IFERROR(B12/B11,"") -> 0 | C20: =IFERROR(C12/C11,"") -> 0 | D20: =IFERROR(D12/D11,"") -> 0 | E20: =IFERROR(E12/E11,"") -> 0 | F20: =IFERROR(F12/F11,"") -> 0 | G20: =IFERROR(G12/G11,"") -> 0 | H20: =IFERROR(H12/H11,"") -> 0.0057251908 | I20: =IFERROR(I12/I11,"") -> 0.0036791759 | ... V20: =IFERROR(V12/V11,"") -> 0.029605263
A21: Tx Lead em MQL | B21: =IFERROR(B15/B12,"") | C21: =IFERROR(C15/C12,"") | D21: =IFERROR(D15/D12,"") | E21: =IFERROR(E15/E12,"") | F21: =IFERROR(F15/F12,"") | G21: =IFERROR(G15/G12,"") | H21: =IFERROR(H15/H12,"") -> 0 | I21: =IFERROR(I15/I12,"") -> 0 | ... V21: =IFERROR(V15/V12,"") -> 0
A22: Tx MQL em Oport. | B22: =IFERROR(B16/B15,"") | C22: =IFERROR(C16/C15,"") | D22: =IFERROR(D16/D15,"") | E22: =IFERROR(E16/E15,"") | F22: =IFERROR(F16/F15,"") | G22: =IFERROR(G16/G15,"") | H22: =IFERROR(H16/H15,"") | I22: =IFERROR(I16/I15,"") | ... V22: =IFERROR(V16/V15,"")
A23: Tx Oport. em Venda | B23: =IFERROR(B17/B16,"") | C23: =IFERROR(C17/C16,"") | D23: =IFERROR(D17/D16,"") | E23: =IFERROR(E17/E16,"") | F23: =IFERROR(F17/F16,"") | G23: =IFERROR(G17/G16,"") | H23: =IFERROR(H17/H16,"") | I23: =IFERROR(I17/I16,"") | ... V23: =IFERROR(V17/V16,"")
A24: Tx MQL em Venda | B24: =IFERROR(B17/B15,"") | C24: =IFERROR(C17/C15,"") | D24: =IFERROR(D17/D15,"") | E24: =IFERROR(E17/E15,"") | F24: =IFERROR(F17/F15,"") | G24: =IFERROR(G17/G15,"") | H24: =IFERROR(H17/H15,"") | I24: =IFERROR(I17/I15,"") | ... V24: =IFERROR(V17/V15,"")
A25: Tx Clique em Lead Conv | H25: =IFERROR(H87/H85,"") -> 0.058275058 | I25: =IFERROR(I87/I85,"") -> 0.082872928 | J25: =IFERROR(J87/J85,"") -> 0.048209366 | K25: =IFERROR(K87/K85,"") -> 0.02690583 | L25: =IFERROR(L87/L85,"") -> 0.063902625 | M25: =IFERROR(M87/M85,"") -> 0.050761421 | N25: =IFERROR(N87/N85,"") -> 0.06626506 | O25: =IFERROR(O87/O85,"") -> 0.104 | ... V25: =IFERROR(V87/V85,"") -> 0.088737201
A26: Tx Lead no Grupo | H26: =IFERROR(H14/H13,"") -> 0.6 | I26: =IFERROR(I14/I13,"") -> 0.79047619 | J26: =IFERROR(J14/J13,"") -> 0.65714286 | K26: =IFERROR(K14/K13,"") -> 0.83333333 | L26: =IFERROR(L14/L13,"") -> 0.73214286 | M26: =IFERROR(M14/M13,"") -> 0.6 | N26: =IFERROR(N14/N13,"") -> 0.72727273 | O26: =IFERROR(O14/O13,"") -> 0.66666667 | ... V26: =IFERROR(V14/V13,"") -> 0.80769231
A28: CPM | B28: =IFERROR((B7/B10)*1000,"") -> 406.47059 | C28: =IFERROR((C7/C10)*1000,"") -> 589.01639 | D28: =IFERROR((D7/D10)*1000,"") -> 13.908587 | E28: =IFERROR((E7/E10)*1000,"") -> 7.5368139 | F28: =IFERROR((F7/F10)*1000,"") -> 8.5163041 | G28: =IFERROR((G7/G10)*1000,"") -> 9.1542644 | H28: =IFERROR((H7/H10)*1000,"") -> 11.959598 | I28: =IFERROR((I7/I10)*1000,"") -> 14.099251 | ... V28: =IFERROR((V7/V10)*1000,"") -> 19.593547
A29: Custo por Clique | B29: =IFERROR(B7/B11,"") -> 1.5946154 | C29: =IFERROR(C7/C11,"") -> 2.7638462 | D29: =IFERROR(D7/D11,"") -> 6.3669231 | E29: =IFERROR(E7/E11,"") -> 5.9517143 | F29: =IFERROR(F7/F11,"") -> 3.1666964 | G29: =IFERROR(G7/G11,"") -> 4.4142017 | H29: =IFERROR(H7/H11,"") -> 0.94679389 | I29: =IFERROR(I7/I11,"") -> 0.53477557 | ... V29: =IFERROR(V7/V11,"") -> 0.40753289
A30: Custo por Lead | B30: =IFERROR(B7/B12,"") | C30: =IFERROR(C7/C12,"") | D30: =IFERROR(D7/D12,"") | E30: =IFERROR(E7/E12,"") | F30: =IFERROR(F7/F12,"") | G30: =IFERROR(G7/G12,"") | H30: =IFERROR(H7/H12,"") -> 165.37333 | I30: =IFERROR(I7/I12,"") -> 145.352 | ... V30: =IFERROR(V7/V12,"") -> 13.765556
A31: Custo por MQL | B31: =IFERROR(B7/B15,"") | C31: =IFERROR(C7/C15,"") | D31: =IFERROR(D7/D15,"") | E31: =IFERROR(E7/E15,"") | F31: =IFERROR(F7/F15,"") | G31: =IFERROR(G7/G15,"") | H31: =IFERROR(H7/H15,"") | I31: =IFERROR(I7/I15,"") | ... V31: =IFERROR(V7/V15,"")
A32: Custo por Oportunidade | B32: =IFERROR(B7/B16,"") | C32: =IFERROR(C7/C16,"") | D32: =IFERROR(D7/D16,"") | E32: =IFERROR(E7/E16,"") | F32: =IFERROR(F7/F16,"") | G32: =IFERROR(G7/G16,"") | H32: =IFERROR(H7/H16,"") | I32: =IFERROR(I7/I16,"") | ... V32: =IFERROR(V7/V16,"")
A33: Custo por Venda | B33: =IFERROR(B7/B17,"") | C33: =IFERROR(C7/C17,"") | D33: =IFERROR(D7/D17,"") | E33: =IFERROR(E7/E17,"") | F33: =IFERROR(F7/F17,"") | G33: =IFERROR(G7/G17,"") | H33: =IFERROR(H7/H17,"") | I33: =IFERROR(I7/I17,"") | ... V33: =IFERROR(V7/V17,"")
A34: Custo por Lead Conv | H34: =IFERROR(H7/H13,"") -> 19.8448 | I34: =IFERROR(I7/I13,"") -> 6.9215238 | J34: =IFERROR(J7/J13,"") -> 19.206 | K34: =IFERROR(K7/K13,"") -> 70.148333 | L34: =IFERROR(L7/L13,"") -> 14.462083 | M34: =IFERROR(M7/M13,"") -> 36.567 | N34: =IFERROR(N7/N13,"") -> 27.017273 | O34: =IFERROR(O7/O13,"") -> 6.9569231 | ... V34: =IFERROR(V7/V13,"") -> 4.765
A35: Custo por Lead Grupo | H35: =IFERROR(H7/H14,"") -> 33.074667 | I35: =IFERROR(I7/I14,"") -> 8.7561446 | J35: =IFERROR(J7/J14,"") -> 29.226522 | K35: =IFERROR(K7/K14,"") -> 84.178 | L35: =IFERROR(L7/L14,"") -> 19.753089 | M35: =IFERROR(M7/M14,"") -> 60.945 | N35: =IFERROR(N7/N14,"") -> 37.14875 | O35: =IFERROR(O7/O14,"") -> 10.435385 | ... V35: =IFERROR(V7/V14,"") -> 5.8995238
A37: ROAS | B37: =IFERROR(B8/B7,"") -> 0 | C37: =IFERROR(C8/C7,"") -> 0 | D37: =IFERROR(D8/D7,"") -> 0 | E37: =IFERROR(E8/E7,"") -> 0 | F37: =IFERROR(F8/F7,"") -> 0 | G37: =IFERROR(G8/G7,"") -> 0 | H37: =IFERROR(H8/H7,"") -> 0 | I37: =IFERROR(I8/I7,"") -> 0 | ... V37: =IFERROR(V8/V7,"") -> 0
A38: Ticket Médio | B38: =IFERROR(B8/B17,"") | C38: =IFERROR(C8/C17,"") | D38: =IFERROR(D8/D17,"") | E38: =IFERROR(E8/E17,"") | F38: =IFERROR(F8/F17,"") | G38: =IFERROR(G8/G17,"") | H38: =IFERROR(H8/H17,"") | I38: =IFERROR(I8/I17,"") | ... V38: =IFERROR(V8/V17,"")
A39: Margem de Contribuição
A40: Fee V4
A41: ROI | B41: =IFERROR(B8*B39/B7,"") -> 0 | C41: =IFERROR(C8*C39/C7,"") -> 0 | D41: =IFERROR(D8*D39/D7,"") -> 0 | E41: =IFERROR(E8*E39/E7,"") -> 0 | F41: =IFERROR(F8*F39/F7,"") -> 0 | G41: =IFERROR(G8*G39/G7,"") -> 0 | H41: =IFERROR(H8*H39/H7,"") -> 0 | I41: =IFERROR(I8*I39/I7,"") -> 0 | ... V41: =IFERROR(V8*V39/V7,"") -> 0
A42: Fat. Geral
A43: Qtd. de vendas gerais
A44: % de Participação da Mídia | B44: =IFERROR(B7/B42," ") | C44: =IFERROR(C7/C42," ") | D44: =IFERROR(D7/D42," ") | E44: =IFERROR(E7/E42," ") | F44: =IFERROR(F7/F42," ") | G44: =IFERROR(G7/G42," ") | H44: =IFERROR(H7/H42," ") | I44: =IFERROR(I7/I42," ") | ... V44: =IFERROR(V7/V42," ")
A47: Dados Google
A48: Semanas | B48: =B6 -> 46082 | C48: =C6 -> 46089 | D48: =D6 -> 46096 | E48: =E6 -> 46103 | F48: =F6 -> 46110 | G48: =G6 -> Março | H48: =H6 -> 46117 | I48: =I6 -> 46124 | ... V48: =V6 -> Junho
A49: Investido | B49: =IFERROR(SUMIFS('2.1 Relatório Diário'!$P:$P,'2.1 Relatório Diário'!$B:$B,">="&$B$2,'2.1 Relatório Diário'!$B:$B,"<="&$B$3),"") -> 20.73 | C49: =SUMIFS('2.1 Relatório Diário'!$P:$P,'2.1 Relatório Diário'!$B:$B,">="&C2,'2.1 Relatório Diário'!$B:$B,"<="&C3) -> 35.93 | D49: =SUMIFS('2.1 Relatório Diário'!$P:$P,'2.1 Relatório Diário'!$B:$B,">="&D2,'2.1 Relatório Diário'!$B:$B,"<="&D3) -> 97.08 | E49: =SUMIFS('2.1 Relatório Diário'!$P:$P,'2.1 Relatório Diário'!$B:$B,">="&E2,'2.1 Relatório Diário'!$B:$B,"<="&E3) -> 48.69 | F49: =SUMIFS('2.1 Relatório Diário'!$P:$P,'2.1 Relatório Diário'!$B:$B,">="&F2,'2.1 Relatório Diário'!$B:$B,"<="&F3) -> 150.12 | G49: =SUMIFS('2.1 Relatório Diário'!$P:$P,'2.1 Relatório Diário'!$B:$B,">="&G2,'2.1 Relatório Diário'!$B:$B,"<="&G3) -> 206.73 | H49: =SUMIFS('2.1 Relatório Diário'!$P:$P,'2.1 Relatório Diário'!$B:$B,">="&H2,'2.1 Relatório Diário'!$B:$B,"<="&H3) -> 224.19 | I49: =SUMIFS('2.1 Relatório Diário'!$P:$P,'2.1 Relatório Diário'!$B:$B,">="&I2,'2.1 Relatório Diário'!$B:$B,"<="&I3) -> 359.66 | J49: =SUMIFS('2.1 Relatório Diário'!$P:$P,'2.1 Relatório Diário'!$B:$B,">="&J2,'2.1 Relatório Diário'!$B:$B,"<="&J3) -> 349.76 | ... V49: =SUMIFS('2.1 Relatório Diário'!$P:$P,'2.1 Relatório Diário'!$B:$B,">="&V2,'2.1 Relatório Diário'!$B:$B,"<="&V3) -> 25.14
A50: Faturado | B50: =IFERROR(SUMIFS('2.1 Relatório Diário'!$R:$R,'2.1 Relatório Diário'!$B:$B,">="&B2,'2.1 Relatório Diário'!$B:$B,"<="&B3),"") -> 0 | C50: =IFERROR(SUMIFS('2.1 Relatório Diário'!$R:$R,'2.1 Relatório Diário'!$B:$B,">="&C2,'2.1 Relatório Diário'!$B:$B,"<="&C3),"") -> 0 | D50: =IFERROR(SUMIFS('2.1 Relatório Diário'!$R:$R,'2.1 Relatório Diário'!$B:$B,">="&D2,'2.1 Relatório Diário'!$B:$B,"<="&D3),"") -> 0 | E50: =IFERROR(SUMIFS('2.1 Relatório Diário'!$R:$R,'2.1 Relatório Diário'!$B:$B,">="&E2,'2.1 Relatório Diário'!$B:$B,"<="&E3),"") -> 0 | F50: =IFERROR(SUMIFS('2.1 Relatório Diário'!$R:$R,'2.1 Relatório Diário'!$B:$B,">="&F2,'2.1 Relatório Diário'!$B:$B,"<="&F3),"") -> 0 | G50: =IFERROR(SUMIFS('2.1 Relatório Diário'!$R:$R,'2.1 Relatório Diário'!$B:$B,">="&G2,'2.1 Relatório Diário'!$B:$B,"<="&G3),"") -> 0 | H50: =IFERROR(SUMIFS('2.1 Relatório Diário'!$R:$R,'2.1 Relatório Diário'!$B:$B,">="&H2,'2.1 Relatório Diário'!$B:$B,"<="&H3),"") -> 0 | I50: =IFERROR(SUMIFS('2.1 Relatório Diário'!$R:$R,'2.1 Relatório Diário'!$B:$B,">="&I2,'2.1 Relatório Diário'!$B:$B,"<="&I3),"") -> 0 | ... V50: =IFERROR(SUMIFS('2.1 Relatório Diário'!$R:$R,'2.1 Relatório Diário'!$B:$B,">="&V2,'2.1 Relatório Diário'!$B:$B,"<="&V3),"") -> 0
A52: Impressões | B52: =IFERROR(SUMIFS('2.1 Relatório Diário'!$S:$S,'2.1 Relatório Diário'!$B:$B,">="&B2,'2.1 Relatório Diário'!$B:$B,"<="&B3),"") -> 51 | C52: =IFERROR(SUMIFS('2.1 Relatório Diário'!$S:$S,'2.1 Relatório Diário'!$B:$B,">="&C2,'2.1 Relatório Diário'!$B:$B,"<="&C3),"") -> 61 | D52: =IFERROR(SUMIFS('2.1 Relatório Diário'!$S:$S,'2.1 Relatório Diário'!$B:$B,">="&D2,'2.1 Relatório Diário'!$B:$B,"<="&D3),"") -> 67 | E52: =IFERROR(SUMIFS('2.1 Relatório Diário'!$S:$S,'2.1 Relatório Diário'!$B:$B,">="&E2,'2.1 Relatório Diário'!$B:$B,"<="&E3),"") -> 86 | F52: =IFERROR(SUMIFS('2.1 Relatório Diário'!$S:$S,'2.1 Relatório Diário'!$B:$B,">="&F2,'2.1 Relatório Diário'!$B:$B,"<="&F3),"") -> 2192 | G52: =IFERROR(SUMIFS('2.1 Relatório Diário'!$S:$S,'2.1 Relatório Diário'!$B:$B,">="&G2,'2.1 Relatório Diário'!$B:$B,"<="&G3),"") -> 309 | H52: =IFERROR(SUMIFS('2.1 Relatório Diário'!$S:$S,'2.1 Relatório Diário'!$B:$B,">="&H2,'2.1 Relatório Diário'!$B:$B,"<="&H3),"") -> 8910 | I52: =IFERROR(SUMIFS('2.1 Relatório Diário'!$S:$S,'2.1 Relatório Diário'!$B:$B,">="&I2,'2.1 Relatório Diário'!$B:$B,"<="&I3),"") -> 7909 | ... V52: =IFERROR(SUMIFS('2.1 Relatório Diário'!$S:$S,'2.1 Relatório Diário'!$B:$B,">="&V2,'2.1 Relatório Diário'!$B:$B,"<="&V3),"") -> 41
